Workbook

Sheet Copy of Sunbird ED Execution Da
A1: Sunbird ED Regression Dashboard
A2: ED Component | B2: Portal/Mobile/Desktop app | C2: Total | E2: Not Applicable | G2: To be Executed | I2: Passed | K2: Fail | M2: Blocked | O2: For retest (Failed & Blocked) | Q2: Execution % circle wise
C3: P1 | D3: P2 | E3: P1 | F3: P2 | G3: P1 | H3: P2 | I3: P1 | J3: P2 | K3: P1 | L3: P2 | M3: P1 | N3: P2 | O3: P1 | P3: P2 | Q3: P1 | R3: P2
A4: Sanity | B4: Portal | C4: =COUNTA('Portal Sanity'!D2:D1005) -> 110 | D4: 0 | E4: =COUNTIF('Portal Sanity'!K2:K1005,"NA") -> 2 | F4: 0 | G4: =C4-(I4+O4+E4) -> 0 | H4: 0 | I4: =COUNTIF('Portal Sanity'!K2:K1005,"Pass") -> 108 | J4: 0 | K4: =COUNTIF('Portal Sanity'!K2:K1005,"Fail") -> 0 | L4: 0 | M4: =COUNTIF('Portal Sanity'!K2:K1005,"Blocked") -> 0 | N4: 0 | O4: =SUM(K4+M4) -> 0 | P4: 0 | Q4: =(E4+I4)/C4 -> 1 | R4: 0
B5: Mobile | C5: =COUNTA('Mobile Sanity'!D2:D1005) -> 111 | D5: 0 | E5: =COUNTIF('Mobile Sanity'!K2:K1005,"NA") -> 4 | F5: 0 | G5: =C5-(I5+O5+E5) -> 0 | H5: 0 | I5: =COUNTIF('Mobile Sanity'!K2:K1005,"Pass") -> 107 | J5: 0 | K5: =COUNTIF('Mobile Sanity'!K2:K1005,"Fail") -> 0 | L5: 0 | M5: =COUNTIF('Mobile Sanity'!K2:K1005,"Blocked") -> 0 | N5: 0 | O5: =SUM(K5+M5) -> 0 | P5: 0 | Q5: =(E5+I5)/C5 -> 1 | R5: 0
B6: Desktop | C6: =COUNTA('Desktop Sanity'!D2:D1005) -> 53 | D6: 0 | E6: =COUNTIF('Desktop Sanity'!K2:K1005,"NA") -> 6 | F6: 0 | G6: =C6-(I6+O6+E6) -> 0 | H6: 0 | I6: =COUNTIF('Desktop Sanity'!K2:K1005,"Pass") -> 47 | J6: 0 | K6: =COUNTIF('Desktop Sanity'!K2:K1005,"Fail") -> 0 | L6: 0 | M6: =COUNTIF('Desktop Sanity'!K2:K1005,"Blocked") -> 0 | N6: 0 | O6: =SUM(K6+M6) -> 0 | P6: 0 | Q6: =(E6+I6)/C6 -> 1 | R6: 0
A7: Sanity New Framework | B7: Portal | C7: =COUNTA('Portal Sanity'!D2:D1005) -> 110 | D7: 0 | E7: =COUNTIF('Portal Sanity'!O2:O1005,"NA") -> 1 | F7: 0 | G7: =C7-(I7+O7+E7) -> 0 | H7: 0 | I7: =COUNTIF('Portal Sanity'!O2:O1005,"Pass") -> 109 | J7: 0 | K7: =COUNTIF('Portal Sanity'!O2:O1005,"Fail") -> 0 | L7: 0 | M7: =COUNTIF('Portal Sanity'!O2:O1005,"Blocked") -> 0 | N7: 0 | O7: =SUM(K7+M7) -> 0 | P7: 0 | Q7: =(E7+I7)/C7 -> 1 | R7: 0
B8: Mobile | C8: =COUNTA('Mobile Sanity'!D2:D1005) -> 111 | D8: 0 | E8: =COUNTIF('Mobile Sanity'!O2:O1005,"NA") -> 5 | F8: 0 | G8: =C8-(I8+O8+E8) -> 0 | H8: 0 | I8: =COUNTIF('Mobile Sanity'!O2:O1005,"Pass") -> 106 | J8: 0 | K8: =COUNTIF('Mobile Sanity'!O2:O1005,"Fail") -> 0 | L8: 0 | M8: =COUNTIF('Mobile Sanity'!O2:O1005,"Blocked") -> 0 | N8: 0 | O8: =SUM(K8+M8) -> 0 | P8: 0 | Q8: =(E8+I8)/C8 -> 1 | R8: 0
B9: Desktop | C9: =COUNTA('Desktop Sanity'!D2:D1005) -> 53 | D9: 0 | E9: =COUNTIF('Desktop Sanity'!O2:O1005,"NA") -> 6 | F9: 0 | G9: =C9-(I9+O9+E9) -> 0 | H9: 0 | I9: =COUNTIF('Desktop Sanity'!O2:O1005,"Pass") -> 47 | J9: 0 | K9: =COUNTIF('Desktop Sanity'!S2:S1005,"Fail") -> 0 | L9: 0 | M9: =COUNTIF('Desktop Sanity'!S2:S1005,"Blocked") -> 0 | N9: 0 | O9: =SUM(K9+M9) -> 0 | P9: 0 | Q9: =(E9+I9)/C9 -> 1 | R9: 0
A10: 7.0.0 New Feature S1 Defects | B10: Portal/Mobile/Offline Desktop | C10: =COUNTA('7.0.0 New Feature S1 Defects'!B2:B1005) -> 45 | D10: 0 | E10: =COUNTIF('7.0.0 New Feature S1 Defects'!E2:E1005,"NA") -> 1 | F10: 0 | G10: =C10-(I10+O10+E10) -> 0 | H10: 0 | I10: =COUNTIF('7.0.0 New Feature S1 Defects'!E2:E1005,"Pass") -> 44 | J10: 0 | K10: =COUNTIF('7.0.0 New Feature S1 Defects'!E2:E1005,"Fail") -> 0 | L10: 0 | M10: =COUNTIF('7.0.0 New Feature S1 Defects'!E2:E1005,"Blocked") -> 0 | N10: 0 | O10: =SUM(K10+M10) -> 0 | P10: 0 | Q10: =(E10+I10)/C10 -> 1 | R10: 0
A11: 6.0.0 OCI S1 Defects | B11: Portal/Mobile/Offline Desktop | C11: =COUNTA('6.0.0 OCI S1 Defects'!B2:B1005) -> 46 | D11: 0 | E11: =COUNTIF('6.0.0 OCI S1 Defects'!E2:E1005,"NA") -> 1 | F11: 0 | G11: =C11-(I11+O11+E11) -> 0 | H11: 0 | I11: =COUNTIF('6.0.0 OCI S1 Defects'!E2:E1005,"Pass") -> 45 | J11: 0 | K11: =COUNTIF('6.0.0 OCI S1 Defects'!E2:E1005,"Fail") -> 0 | L11: 0 | M11: =COUNTIF('6.0.0 OCI S1 Defects'!E2:E1005,"Blocked") -> 0 | N11: 0 | O11: =SUM(K11+M11) -> 0 | P11: 0 | Q11: =(E11+I11)/C11 -> 1 | R11: 0
A12: WorkSpace | B12: Portal | C12: =COUNTIF(Workspace!F2:F1005,"P1") -> 264 | D12: =COUNTIF(Workspace!F2:F1005,"P2") -> 327 | E12: =COUNTIFS(Workspace!F2:F1005,"P1",Workspace!T2:T1005,"NA") -> 14 | F12: =COUNTIFS(Workspace!F2:F1005,"P2",Workspace!T2:T1005,"NA") -> 26 | G12: =C12-(I12+K12+M12+E12) -> 0 | H12: =D12-(J12+L12+N12+F12) -> 0 | I12: =COUNTIFS(Workspace!F2:F1005,"P1",Workspace!T2:T1005,"Pass") -> 250 | J12: =COUNTIFS(Workspace!F2:F1005,"P2",Workspace!T2:T1005,"Pass") -> 301 | K12: =COUNTIFS(Workspace!F2:F1005,"P1",Workspace!T2:T1005,"Fail") -> 0 | L12: =COUNTIFS(Workspace!F2:F1005,"P2",Workspace!T2:T1005,"Fail") -> 0 | M12: =COUNTIFS(Workspace!F2:F1005,"P1",Workspace!T2:T1005,"Blocked") -> 0 | N12: =COUNTIFS(Workspace!F2:F1005,"P2",Workspace!T2:T1005,"Blocked") -> 0 | O12: =SUM(K12+M12) -> 0 | P12: =SUM(L12+N12) -> 0 | Q12: =(E12+I12)/C12 -> 1 | R12: =(F12+J12)/D12 -> 1
A13: Login | B13: Portal | C13: =COUNTIFS(Login!D2:D1005,"Reference Learning Web App",Login!F2:F1005,"P1") -> 61 | D13: =COUNTIFS(Login!D2:D1005,"Reference Learning Web App",Login!F2:F1005,"P2") -> 73 | E13: =COUNTIFS(Login!D2:D1005,"Reference Learning Web App",Login!F2:F1005,"P1",Login!R2:R1005,"NA") -> 2 | F13: =COUNTIFS(Login!D2:D1005,"Reference Learning Web App",Login!F2:F1005,"P2",Login!R2:R1005,"NA") -> 5 | G13: =C13-(I13+K13+M13+E13) -> 0 | H13: =D13-(J13+L13+N13+F13) -> 0 | I13: =COUNTIFS(Login!D2:D1005,"Reference Learning Web App",Login!F2:F1005,"P1",Login!R2:R1005,"Pass") -> 59 | J13: =COUNTIFS(Login!D2:D1005,"Reference Learning Web App",Login!F2:F1005,"P2",Login!R2:R1005,"Pass") -> 68 | K13: =COUNTIFS(Login!D2:D1005,"Reference Learning Web App",Login!F2:F1005,"P1",Login!R2:R1005,"Fail") -> 0 | L13: =COUNTIFS(Login!D2:D1005,"Reference Learning Web App",Login!F2:F1005,"P2",Login!R2:R1005,"Fail") -> 0 | M13: =COUNTIFS(Login!D2:D1005,"Reference Learning Web App",Login!F2:F1005,"P1",Login!R2:R1005,"Blocked") -> 0 | N13: =COUNTIFS(Login!D2:D1005,"Reference Learning Web App",Login!F2:F1005,"P2",Login!R2:R1005,"Blocked") -> 0 | O13: =SUM(K13+M13) -> 0 | P13: =SUM(L13+N13) -> 0 | Q13: =(E13+I13)/C13 -> 1 | R13: =(F13+J13)/D13 -> 1
B14: Mobile | C14: =COUNTIFS(Login!D2:D1005,"Reference Learning Mobile App",Login!F2:F1005,"P1") -> 62 | D14: =COUNTIFS(Login!D2:D1005,"Reference Learning Mobile App",Login!F2:F1005,"P2") -> 87 | E14: =COUNTIFS(Login!D2:D1005,"Reference Learning Mobile App",Login!F2:F1005,"P1",Login!R2:R1005,"NA") -> 1 | F14: =COUNTIFS(Login!D2:D1005,"Reference Learning Mobile App",Login!F2:F1005,"P2",Login!R2:R1005,"NA") -> 4 | G14: =C14-(I14+K14+M14+E14) -> 0 | H14: =D14-(J14+L14+N14+F14) -> 0 | I14: =COUNTIFS(Login!D2:D1005,"Reference Learning Mobile App",Login!F2:F1005,"P1",Login!R2:R1005,"Pass") -> 61 | J14: =COUNTIFS(Login!D2:D1005,"Reference Learning Mobile App",Login!F2:F1005,"P2",Login!R2:R1005,"Pass") -> 83 | K14: =COUNTIFS(Login!D2:D1005,"Reference Learning Mobile App",Login!F2:F1005,"P1",Login!R2:R1005,"Fail") -> 0 | L14: =COUNTIFS(Login!D2:D1005,"Reference Learning Mobile App",Login!F2:F1005,"P2",Login!R2:R1005,"Fail") -> 0 | M14: =COUNTIFS(Login!D2:D1005,"Reference Learning Mobile App",Login!F2:F1005,"P1",Login!R2:R1005,"Blocked") -> 0 | N14: =COUNTIFS(Login!D2:D1005,"Reference Learning Mobile App",Login!F2:F1005,"P2",Login!R2:R1005,"Blocked") -> 0 | O14: =SUM(K14+M14) -> 0 | P14: =SUM(L14+N14) -> 0 | Q14: =(E14+I14)/C14 -> 1 | R14: =(F14+J14)/D14 -> 1
B15: Offline Desktop | C15: =COUNTIFS(Login!D2:D1005,"Reference Learning Desktop App",Login!F2:F1005,"P1") -> 22 | D15: =COUNTIFS(Login!D2:D1005,"Reference Learning Desktop App",Login!F2:F1005,"P2") -> 26 | E15: =COUNTIFS(Login!D2:D1005,"Reference Learning Desktop App",Login!F2:F1005,"P1",Login!R2:R1005,"NA") -> 0 | F15: =COUNTIFS(Login!D2:D1005,"Reference Learning Desktop App",Login!F2:F1005,"P2",Login!R2:R1005,"NA") -> 0 | G15: =C15-(I15+K15+M15+E15) -> 0 | H15: =D15-(J15+L15+N15+F15) -> 0 | I15: =COUNTIFS(Login!D2:D1005,"Reference Learning Desktop App",Login!F2:F1005,"P1",Login!R2:R1005,"Pass") -> 22 | J15: =COUNTIFS(Login!D2:D1005,"Reference Learning Desktop App",Login!F2:F1005,"P2",Login!R2:R1005,"Pass") -> 26 | K15: =COUNTIFS(Login!D2:D1005,"Reference Learning Desktop App",Login!F2:F1005,"P1",Login!R2:R1005,"Fail") -> 0 | L15: =COUNTIFS(Login!D2:D1005,"Reference Learning Desktop App",Login!F2:F1005,"P2",Login!R2:R1005,"Fail") -> 0 | M15: =COUNTIFS(Login!D2:D1005,"Reference Learning Desktop App",Login!F2:F1005,"P1",Login!R2:R1005,"Blocked") -> 0 | N15: =COUNTIFS(Login!D2:D1005,"Reference Learning Desktop App",Login!F2:F1005,"P2",Login!R2:R1005,"Blocked") -> 0 | O15: =SUM(K15+M15) -> 0 | P15: =SUM(L15+N15) -> 0 | Q15: =(E15+I15)/C15 -> 1 | R15: =(F15+J15)/D15 -> 1
A16: Course Consumption | B16: Portal | C16: =COUNTIFS('Course Consumption'!D2:D1005,"Reference Learning Web App",'Course Consumption'!F2:F1005,"P1") -> 163 | D16: =COUNTIFS('Course Consumption'!D2:D1005,"Reference Learning Web App",'Course Consumption'!F2:F1005,"P2") -> 59 | E16: =COUNTIFS('Course Consumption'!D2:D1005,"Reference Learning Web App",'Course Consumption'!F2:F1005,"P1",'Course Consumption'!R2:R1005,"NA") -> 8 | F16: =COUNTIFS('Course Consumption'!D2:D1005,"Reference Learning Web App",'Course Consumption'!F2:F1005,"P2",'Course Consumption'!R2:R1005,"NA") -> 1 | G16: =C16-(I16+K16+M16+E16) -> 0 | H16: =D16-(J16+L16+N16+F16) -> 0 | I16: =COUNTIFS('Course Consumption'!D2:D1005,"Reference Learning Web App",'Course Consumption'!F2:F1005,"P1",'Course Consumption'!R2:R1005,"Pass") -> 155 | J16: =COUNTIFS('Course Consumption'!D2:D1005,"Reference Learning Web App",'Course Consumption'!F2:F1005,"P2",'Course Consumption'!R2:R1005,"Pass") -> 58 | K16: =COUNTIFS('Course Consumption'!D2:D1005,"Reference Learning Web App",'Course Consumption'!F2:F1005,"P1",'Course Consumption'!R2:R1005,"Fail") -> 0 | L16: =COUNTIFS('Course Consumption'!D2:D1005,"Reference Learning Web App",'Course Consumption'!F2:F1005,"P2",'Course Consumption'!R2:R1005,"Fail") -> 0 | M16: =COUNTIFS('Course Consumption'!D2:D1005,"Reference Learning Web App",'Course Consumption'!F2:F1005,"P1",'Course Consumption'!R2:R1005,"Blocked") -> 0 | N16: =COUNTIFS('Course Consumption'!D2:D1005,"Reference Learning Web App",'Course Consumption'!F2:F1005,"P2",'Course Consumption'!R2:R1005,"Blocked") -> 0 | O16: =SUM(K16+M16) -> 0 | P16: =SUM(L16+N16) -> 0 | Q16: =(E16+I16)/C16 -> 1 | R16: =(F16+J16)/D16 -> 1
B17: Mobile | C17: =COUNTIFS('Course Consumption'!D2:D1005,"Reference Learning Mobile App",'Course Consumption'!F2:F1005,"P1") -> 119 | D17: =COUNTIFS('Course Consumption'!D2:D1005,"Reference Learning Mobile App",'Course Consumption'!F2:F1005,"P2") -> 164 | E17: =COUNTIFS('Course Consumption'!D2:D1005,"Reference Learning Mobile App",'Course Consumption'!F2:F1005,"P1",'Course Consumption'!R2:R1005,"NA") -> 3 | F17: =COUNTIFS('Course Consumption'!D2:D1005,"Reference Learning Mobile App",'Course Consumption'!F2:F1005,"P2",'Course Consumption'!R2:R1005,"NA") -> 7 | G17: =C17-(I17+K17+M17+E17) -> 0 | H17: =D17-(J17+L17+N17+F17) -> 0 | I17: =COUNTIFS('Course Consumption'!D2:D1005,"Reference Learning Mobile App",'Course Consumption'!F2:F1005,"P1",'Course Consumption'!R2:R1005,"Pass") -> 116 | J17: =COUNTIFS('Course Consumption'!D2:D1005,"Reference Learning Mobile App",'Course Consumption'!F2:F1005,"P2",'Course Consumption'!R2:R1005,"Pass") -> 157 | K17: =COUNTIFS('Course Consumption'!D2:D1005,"Reference Learning Mobile App",'Course Consumption'!F2:F1005,"P1",'Course Consumption'!R2:R1005,"Fail") -> 0 | L17: =COUNTIFS('Course Consumption'!D2:D1005,"Reference Learning Mobile App",'Course Consumption'!F2:F1005,"P2",'Course Consumption'!R2:R1005,"Fail") -> 0 | M17: =COUNTIFS('Course Consumption'!D2:D1005,"Reference Learning Mobile App",'Course Consumption'!F2:F1005,"P1",'Course Consumption'!R2:R1005,"Blocked") -> 0 | N17: =COUNTIFS('Course Consumption'!D2:D1005,"Reference Learning Mobile App",'Course Consumption'!F2:F1005,"P2",'Course Consumption'!R2:R1005,"Blocked") -> 0 | O17: =SUM(K17+M17) -> 0 | P17: =SUM(L17+N17) -> 0 | Q17: =(E17+I17)/C17 -> 1 | R17: =(F17+J17)/D17 -> 1
B18: Offline Desktop | C18: =COUNTIFS('Course Consumption'!D2:D1005,"Reference Learning Desktop App",'Course Consumption'!F2:F1005,"P1") -> 40 | D18: =COUNTIFS('Course Consumption'!D2:D1005,"Reference Learning Desktop App",'Course Consumption'!F2:F1005,"P2") -> 38 | E18: =COUNTIFS('Course Consumption'!D2:D1005,"Reference Learning Desktop App",'Course Consumption'!F2:F1005,"P1",'Course Consumption'!R2:R1005,"NA") -> 3 | F18: =COUNTIFS('Course Consumption'!D2:D1005,"Reference Learning Desktop App",'Course Consumption'!F2:F1005,"P2",'Course Consumption'!R2:R1005,"NA") -> 2 | G18: =C18-(I18+K18+M18+E18) -> 0 | H18: =D18-(J18+L18+N18+F18) -> 0 | I18: =COUNTIFS('Course Consumption'!D2:D1005,"Reference Learning Desktop App",'Course Consumption'!F2:F1005,"P1",'Course Consumption'!R2:R1005,"Pass") -> 37 | J18: =COUNTIFS('Course Consumption'!D2:D1005,"Reference Learning Desktop App",'Course Consumption'!F2:F1005,"P2",'Course Consumption'!R2:R1005,"Pass") -> 36 | K18: =COUNTIFS('Course Consumption'!D2:D1005,"Reference Learning Desktop App",'Course Consumption'!F2:F1005,"P1",'Course Consumption'!R2:R1005,"Fail") -> 0 | L18: =COUNTIFS('Course Consumption'!D2:D1005,"Reference Learning Desktop App",'Course Consumption'!F2:F1005,"P2",'Course Consumption'!R2:R1005,"Fail") -> 0 | M18: =COUNTIFS('Course Consumption'!D2:D1005,"Reference Learning Desktop App",'Course Consumption'!F2:F1005,"P1",'Course Consumption'!R2:R1005,"Blocked") -> 0 | N18: =COUNTIFS('Course Consumption'!D2:D1005,"Reference Learning Desktop App",'Course Consumption'!F2:F1005,"P2",'Course Consumption'!R2:R1005,"Blocked") -> 0 | O18: =SUM(K18+M18) -> 0 | P18: =SUM(L18+N18) -> 0 | Q18: =(E18+I18)/C18 -> 1 | R18: =(F18+J18)/D18 -> 1
A19: Batch Creation | B19: Portal | C19: =COUNTIFS('Batch Creation'!D2:D1005,"Reference Learning Web App",'Batch Creation'!F2:F1005,"P1") -> 43 | D19: =COUNTIFS('Batch Creation'!D2:D1005,"Reference Learning Web App",'Batch Creation'!F2:F1005,"P2") -> 10 | E19: =COUNTIFS('Batch Creation'!D2:D1005,"Reference Learning Web App",'Batch Creation'!F2:F1005,"P1",'Batch Creation'!Q2:Q1005,"NA") -> 0 | F19: =COUNTIFS('Batch Creation'!D2:D1005,"Reference Learning Web App",'Batch Creation'!F2:F1005,"P2",'Batch Creation'!Q2:Q1005,"NA") -> 0 | G19: =C19-(I19+K19+M19+E19) -> 0 | H19: =D19-(J19+L19+N19+F19) -> 0 | I19: =COUNTIFS('Batch Creation'!D2:D1005,"Reference Learning Web App",'Batch Creation'!F2:F1005,"P1",'Batch Creation'!Q2:Q1005,"Pass") -> 43 | J19: =COUNTIFS('Batch Creation'!D2:D1005,"Reference Learning Web App",'Batch Creation'!F2:F1005,"P2",'Batch Creation'!Q2:Q1005,"Pass") -> 10 | K19: =COUNTIFS('Batch Creation'!D2:D1005,"Reference Learning Web App",'Batch Creation'!F2:F1005,"P1",'Batch Creation'!Q2:Q1005,"Fail") -> 0 | L19: =COUNTIFS('Batch Creation'!D2:D1005,"Reference Learning Web App",'Batch Creation'!F2:F1005,"P2",'Batch Creation'!Q2:Q1005,"Fail") -> 0 | M19: =COUNTIFS('Batch Creation'!D2:D1005,"Reference Learning Web App",'Batch Creation'!F2:F1005,"P1",'Batch Creation'!Q2:Q1005,"Blocked") -> 0 | N19: =COUNTIFS('Batch Creation'!D2:D1005,"Reference Learning Web App",'Batch Creation'!F2:F1005,"P2",'Batch Creation'!Q2:Q1005,"Blocked") -> 0 | O19: =SUM(K19+M19) -> 0 | P19: =SUM(L19+N19) -> 0 | Q19: =(E19+I19)/C19 -> 1 | R19: =(F19+J19)/D19 -> 1
A20: Digital Textbook Consumption | B20: Portal | C20: =COUNTIFS('Digital Textbook Consumption'!D2:D1005,"Reference Learning Web App",'Digital Textbook Consumption'!F2:F1005,"P1") -> 41 | D20: =COUNTIFS('Digital Textbook Consumption'!D2:D1005,"Reference Learning Web App",'Digital Textbook Consumption'!F2:F1005,"P2") -> 30 | E20: =COUNTIFS('Digital Textbook Consumption'!D5:D1005,"Reference Learning Web App",'Digital Textbook Consumption'!F5:F1005,"P1",'Digital Textbook Consumption'!Q5:Q1005,"NA") -> 0 | F20: =COUNTIFS('Digital Textbook Consumption'!D2:D1005,"Reference Learning Web App",'Digital Textbook Consumption'!F2:F1005,"P2",'Digital Textbook Consumption'!Q2:Q1005,"NA") -> 3 | G20: =C20-(I20+K20+M20+E20) -> 0 | H20: =D20-(J20+L20+N20+F20) -> 0 | I20: =COUNTIFS('Digital Textbook Consumption'!D2:D1005,"Reference Learning Web App",'Digital Textbook Consumption'!F2:F1005,"P1",'Digital Textbook Consumption'!Q2:Q1005,"Pass") -> 41 | J20: =COUNTIFS('Digital Textbook Consumption'!D2:D1005,"Reference Learning Web App",'Digital Textbook Consumption'!F2:F1005,"P2",'Digital Textbook Consumption'!Q2:Q1005,"Pass") -> 27 | K20: =COUNTIFS('Digital Textbook Consumption'!D2:D1005,"Reference Learning Web App",'Digital Textbook Consumption'!F2:F1005,"P1",'Digital Textbook Consumption'!Q2:Q1005,"Fail") -> 0 | L20: =COUNTIFS('Digital Textbook Consumption'!D2:D1005,"Reference Learning Web App",'Digital Textbook Consumption'!F2:F1005,"P2",'Digital Textbook Consumption'!Q2:Q1005,"Fail") -> 0 | M20: =COUNTIFS('Digital Textbook Consumption'!D2:D1005,"Reference Learning Web App",'Digital Textbook Consumption'!F2:F1005,"P1",'Digital Textbook Consumption'!Q2:Q1005,"Blocked") -> 0 | N20: =COUNTIFS('Digital Textbook Consumption'!D2:D1005,"Reference Learning Web App",'Digital Textbook Consumption'!F2:F1005,"P2",'Digital Textbook Consumption'!Q2:Q1005,"Blocked") -> 0 | O20: =SUM(K20+M20) -> 0 | P20: =SUM(L20+N20) -> 0 | Q20: =(E20+I20)/C20 -> 1 | R20: =(F20+J20)/D20 -> 1
B21: Mobile | C21: =COUNTIFS('Digital Textbook Consumption'!D2:D1005,"Reference Learning Mobile App",'Digital Textbook Consumption'!F2:F1005,"P1") -> 23 | D21: =COUNTIFS('Digital Textbook Consumption'!D2:D1005,"Reference Learning Mobile App",'Digital Textbook Consumption'!F2:F1005,"P2") -> 34 | E21: =COUNTIFS('Digital Textbook Consumption'!D2:D1005,"Reference Learning Mobile App",'Digital Textbook Consumption'!F2:F1005,"P1",'Digital Textbook Consumption'!Q2:Q1005,"NA") -> 1 | F21: =COUNTIFS('Digital Textbook Consumption'!D2:D1005,"Reference Learning Mobile App",'Digital Textbook Consumption'!F2:F1005,"P2",'Digital Textbook Consumption'!Q2:Q1005,"NA") -> 0 | G21: =C21-(I21+K21+M21+E21) -> 0 | H21: =D21-(J21+L21+N21+F21) -> 0 | I21: =COUNTIFS('Digital Textbook Consumption'!D2:D1005,"Reference Learning Mobile App",'Digital Textbook Consumption'!F2:F1005,"P1",'Digital Textbook Consumption'!Q2:Q1005,"Pass") -> 22 | J21: =COUNTIFS('Digital Textbook Consumption'!D2:D1005,"Reference Learning Mobile App",'Digital Textbook Consumption'!F2:F1005,"P2",'Digital Textbook Consumption'!Q2:Q1005,"Pass") -> 34 | K21: =COUNTIFS('Digital Textbook Consumption'!D2:D1005,"Reference Learning Mobile App",'Digital Textbook Consumption'!F2:F1005,"P1",'Digital Textbook Consumption'!Q2:Q1005,"Fail") -> 0 | L21: =COUNTIFS('Digital Textbook Consumption'!D2:D1005,"Reference Learning Mobile App",'Digital Textbook Consumption'!F2:F1005,"P2",'Digital Textbook Consumption'!Q2:Q1005,"Fail") -> 0 | M21: =COUNTIFS('Digital Textbook Consumption'!D2:D1005,"Reference Learning Mobile App",'Digital Textbook Consumption'!F2:F1005,"P1",'Digital Textbook Consumption'!Q2:Q1005,"Blocked") -> 0 | N21: =COUNTIFS('Digital Textbook Consumption'!D2:D1005,"Reference Learning Mobile App",'Digital Textbook Consumption'!F2:F1005,"P2",'Digital Textbook Consumption'!Q2:Q1005,"Blocked") -> 0 | O21: =SUM(K21+M21) -> 0 | P21: =SUM(L21+N21) -> 0 | Q21: =(E21+I21)/C21 -> 1 | R21: =(F21+J21)/D21 -> 1
B22: Offline Desktop | C22: =COUNTIFS('Digital Textbook Consumption'!D2:D1005,"Reference Learning Desktop App",'Digital Textbook Consumption'!F2:F1005,"P1") -> 15 | D22: =COUNTIFS('Digital Textbook Consumption'!D2:D1005,"Reference Learning Desktop App",'Digital Textbook Consumption'!F2:F1005,"P2") -> 41 | E22: =COUNTIFS('Digital Textbook Consumption'!D2:D1005,"Reference Learning Desktop App",'Digital Textbook Consumption'!F2:F1005,"P1",'Digital Textbook Consumption'!Q2:Q1005,"NA") -> 2 | F22: =COUNTIFS('Digital Textbook Consumption'!D2:D1005,"Reference Learning Desktop App",'Digital Textbook Consumption'!F2:F1005,"P2",'Digital Textbook Consumption'!Q2:Q1005,"NA") -> 2 | G22: =C22-(I22+K22+M22+E22) -> 0 | H22: =D22-(J22+L22+N22+F22) -> 0 | I22: =COUNTIFS('Digital Textbook Consumption'!D2:D1005,"Reference Learning Desktop App",'Digital Textbook Consumption'!F2:F1005,"P1",'Digital Textbook Consumption'!Q2:Q1005,"Pass") -> 13 | J22: =COUNTIFS('Digital Textbook Consumption'!D2:D1005,"Reference Learning Desktop App",'Digital Textbook Consumption'!F2:F1005,"P2",'Digital Textbook Consumption'!Q2:Q1005,"Pass") -> 39 | K22: =COUNTIFS('Digital Textbook Consumption'!D2:D1005,"Reference Learning Desktop App",'Digital Textbook Consumption'!F2:F1005,"P1",'Digital Textbook Consumption'!Q2:Q1005,"Fail") -> 0 | L22: =COUNTIFS('Digital Textbook Consumption'!D2:D1005,"Reference Learning Desktop App",'Digital Textbook Consumption'!F2:F1005,"P2",'Digital Textbook Consumption'!Q2:Q1005,"Fail") -> 0 | M22: =COUNTIFS('Digital Textbook Consumption'!D2:D1005,"Reference Learning Desktop App",'Digital Textbook Consumption'!F2:F1005,"P1",'Digital Textbook Consumption'!Q2:Q1005,"Blocked") -> 0 | N22: =COUNTIFS('Digital Textbook Consumption'!D2:D1005,"Reference Learning Desktop App",'Digital Textbook Consumption'!F2:F1005,"P2",'Digital Textbook Consumption'!Q2:Q1005,"Blocked") -> 0 | O22: =SUM(K22+M22) -> 0 | P22: =SUM(L22+N22) -> 0 | Q22: =(E22+I22)/C22 -> 1 | R22: =(F22+J22)/D22 -> 1
A23: Content Consumption | B23: Portal | C23: =COUNTIFS('Content Consumption'!D2:D1005,"Reference Learning Web App",'Content Consumption'!F2:F1005,"P1") -> 90 | D23: =COUNTIFS('Content Consumption'!D2:D1005,"Reference Learning Web App",'Content Consumption'!F2:F1005,"P2") -> 52 | E23: =COUNTIFS('Content Consumption'!D5:D1005,"Reference Learning Web App",'Content Consumption'!F5:F1005,"P1",'Content Consumption'!Q5:Q1005,"NA") -> 0 | F23: =COUNTIFS('Content Consumption'!D2:D1005,"Reference Learning Web App",'Content Consumption'!F2:F1005,"P2",'Content Consumption'!R2:R1005,"NA") -> 1 | G23: =C23-(I23+K23+M23+E23) -> 0 | H23: =D23-(J23+L23+N23+F23) -> 0 | I23: =COUNTIFS('Content Consumption'!D2:D1005,"Reference Learning Web App",'Content Consumption'!F2:F1005,"P1",'Content Consumption'!R2:R1005,"Pass") -> 90 | J23: =COUNTIFS('Content Consumption'!D2:D1005,"Reference Learning Web App",'Content Consumption'!F2:F1005,"P2",'Content Consumption'!R2:R1005,"Pass") -> 51 | K23: =COUNTIFS('Content Consumption'!D2:D1005,"Reference Learning Web App",'Content Consumption'!F2:F1005,"P1",'Content Consumption'!R2:R1005,"Fail") -> 0 | L23: =COUNTIFS('Content Consumption'!D2:D1005,"Reference Learning Web App",'Content Consumption'!F2:F1005,"P2",'Content Consumption'!R2:R1005,"Fail") -> 0 | M23: =COUNTIFS('Content Consumption'!D2:D1005,"Reference Learning Web App",'Content Consumption'!F2:F1005,"P1",'Content Consumption'!R2:R1005,"Blocked") -> 0 | N23: =COUNTIFS('Content Consumption'!D2:D1005,"Reference Learning Web App",'Content Consumption'!F2:F1005,"P2",'Content Consumption'!R2:R1005,"Blocked") -> 0 | O23: =SUM(K23+M23) -> 0 | P23: =SUM(L23+N23) -> 0 | Q23: =(E23+I23)/C23 -> 1 | R23: =(F23+J23)/D23 -> 1
B24: Mobile | C24: =COUNTIFS('Content Consumption'!D2:D1005,"Reference Learning Mobile App",'Content Consumption'!F2:F1005,"P1") -> 31 | D24: =COUNTIFS('Content Consumption'!D3:D1005,"Reference Learning Mobile App",'Content Consumption'!F3:F1005,"P2") -> 84 | E24: =COUNTIFS('Content Consumption'!D2:D1005,"Reference Learning Mobile App",'Content Consumption'!F2:F1005,"P1",'Content Consumption'!R2:R1005,"NA") -> 1 | F24: =COUNTIFS('Content Consumption'!D2:D1005,"Reference Learning Mobile App",'Content Consumption'!F2:F1005,"P2",'Content Consumption'!R2:R1005,"NA") -> 0 | G24: =C24-(I24+K24+M24+E24) -> 0 | H24: =D24-(J24+L24+N24+F24) -> 0 | I24: =COUNTIFS('Content Consumption'!D2:D1005,"Reference Learning Mobile App",'Content Consumption'!F2:F1005,"P1",'Content Consumption'!R2:R1005,"Pass") -> 30 | J24: =COUNTIFS('Content Consumption'!D2:D1005,"Reference Learning Mobile App",'Content Consumption'!F2:F1005,"P2",'Content Consumption'!R2:R1005,"Pass") -> 84 | K24: =COUNTIFS('Content Consumption'!D2:D1005,"Reference Learning Mobile App",'Content Consumption'!F2:F1005,"P1",'Content Consumption'!R2:R1005,"Fail") -> 0 | L24: =COUNTIFS('Content Consumption'!D2:D1005,"Reference Learning Mobile App",'Content Consumption'!F2:F1005,"P2",'Content Consumption'!R2:R1005,"Fail") -> 0 | M24: =COUNTIFS('Content Consumption'!D2:D1005,"Reference Learning Mobile App",'Content Consumption'!F2:F1005,"P1",'Content Consumption'!R2:R1005,"Blocked") -> 0 | N24: =COUNTIFS('Content Consumption'!D2:D1005,"Reference Learning Mobile App",'Content Consumption'!F2:F1005,"P2",'Content Consumption'!R2:R1005,"Blocked") -> 0 | O24: =SUM(K24+M24) -> 0 | P24: =SUM(L24+N24) -> 0 | Q24: =(E24+I24)/C24 -> 1 | R24: =(F24+J24)/D24 -> 1
B25: Offline Desktop | C25: =COUNTIFS('Content Consumption'!D2:D1005,"Reference Learning Desktop App",'Content Consumption'!F2:F1005,"P1") -> 42 | D25: =COUNTIFS('Content Consumption'!D3:D1005,"Reference Learning Desktop App",'Content Consumption'!F3:F1005,"P2") -> 32 | E25: =COUNTIFS('Content Consumption'!D2:D1005,"Reference Learning Desktop App",'Content Consumption'!F2:F1005,"P1",'Content Consumption'!R2:R1005,"NA") -> 0 | F25: =COUNTIFS('Content Consumption'!D2:D1005,"Reference Learning Desktop App",'Content Consumption'!F2:F1005,"P2",'Content Consumption'!R2:R1005,"NA") -> 0 | G25: =C25-(I25+K25+M25+E25) -> 0 | H25: =D25-(J25+L25+N25+F25) -> 0 | I25: =COUNTIFS('Content Consumption'!D2:D1005,"Reference Learning Desktop App",'Content Consumption'!F2:F1005,"P1",'Content Consumption'!R2:R1005,"Pass") -> 42 | J25: =COUNTIFS('Content Consumption'!D2:D1005,"Reference Learning Desktop App",'Content Consumption'!F2:F1005,"P2",'Content Consumption'!R2:R1005,"Pass") -> 32 | K25: =COUNTIFS('Content Consumption'!D2:D1005,"Reference Learning Desktop App",'Content Consumption'!F2:F1005,"P1",'Content Consumption'!R2:R1005,"Fail") -> 0 | L25: =COUNTIFS('Content Consumption'!D2:D1005,"Reference Learning Desktop App",'Content Consumption'!F2:F1005,"P2",'Content Consumption'!R2:R1005,"Fail") -> 0 | M25: =COUNTIFS('Content Consumption'!D2:D1005,"Reference Learning Desktop App",'Content Consumption'!F2:F1005,"P1",'Content Consumption'!R2:R1005,"Blocked") -> 0 | N25: =COUNTIFS('Content Consumption'!D2:D1005,"Reference Learning Desktop App",'Content Consumption'!F2:F1005,"P2",'Content Consumption'!R2:R1005,"Blocked") -> 0 | O25: =SUM(K25+M25) -> 0 | P25: =SUM(L25+N25) -> 0 | Q25: =(E25+I25)/C25 -> 1 | R25: =(F25+J25)/D25 -> 1
A26: Profile | B26: Portal | C26: =COUNTIFS(Profile!D2:D1005,"Reference Learning Web App",Profile!F2:F1005,"P1") -> 42 | D26: =COUNTIFS(Profile!D2:D1005,"Reference Learning Web App",Profile!F2:F1005,"P2") -> 74 | E26: =COUNTIFS(Profile!D5:D1005,"Reference Learning Web App",Profile!F5:F1005,"P1",Profile!Q5:Q1005,"NA") -> 0 | F26: =COUNTIFS(Profile!D2:D1005,"Reference Learning Web App",Profile!F2:F1005,"P2",Profile!R2:R1005,"NA") -> 3 | G26: =C26-(I26+K26+M26+E26) -> 0 | H26: =D26-(J26+L26+N26+F26) -> 0 | I26: =COUNTIFS(Profile!D2:D1005,"Reference Learning Web App",Profile!F2:F1005,"P1",Profile!R2:R1005,"Pass") -> 42 | J26: =COUNTIFS(Profile!D2:D1005,"Reference Learning Web App",Profile!F2:F1005,"P2",Profile!R2:R1005,"Pass") -> 71 | K26: =COUNTIFS(Profile!D2:D1005,"Reference Learning Web App",Profile!F2:F1005,"P1",Profile!R2:R1005,"Fail") -> 0 | L26: =COUNTIFS(Profile!D2:D1005,"Reference Learning Web App",Profile!F2:F1005,"P2",Profile!R2:R1005,"Fail") -> 0 | M26: =COUNTIFS(Profile!D2:D1005,"Reference Learning Web App",Profile!F2:F1005,"P1",Profile!R2:R1005,"Blocked") -> 0 | N26: =COUNTIFS(Profile!D2:D1005,"Reference Learning Web App",Profile!F2:F1005,"P2",Profile!R2:R1005,"Blocked") -> 0 | O26: =SUM(K26+M26) -> 0 | P26: =SUM(L26+N26) -> 0 | Q26: =(E26+I26)/C26 -> 1 | R26: =(F26+J26)/D26 -> 1
B27: Mobile | C27: =COUNTIFS(Profile!D2:D1005,"Reference Learning Mobile App",Profile!F2:F1005,"P1") -> 43 | D27: =COUNTIFS(Profile!D2:D1005,"Reference Learning Mobile App",Profile!F2:F1005,"P2") -> 51 | E27: =COUNTIFS(Profile!D5:D1005,"Reference Learning Mobile App",Profile!F5:F1005,"P1",Profile!Q5:Q1005,"NA") -> 0 | F27: =COUNTIFS(Profile!D2:D1005,"Reference Learning Mobile App",Profile!F2:F1005,"P2",Profile!R2:R1005,"NA") -> 0 | G27: =C27-(I27+K27+M27+E27) -> 0 | H27: =D27-(J27+L27+N27+F27) -> 0 | I27: =COUNTIFS(Profile!D2:D1005,"Reference Learning Mobile App",Profile!F2:F1005,"P1",Profile!R2:R1005,"Pass") -> 43 | J27: =COUNTIFS(Profile!D2:D1005,"Reference Learning Mobile App",Profile!F2:F1005,"P2",Profile!R2:R1005,"Pass") -> 51 | K27: =COUNTIFS(Profile!D2:D1005,"Reference Learning Mobile App",Profile!F2:F1005,"P1",Profile!R2:R1005,"Fail") -> 0 | L27: =COUNTIFS(Profile!D2:D1005,"Reference Learning Mobile App",Profile!F2:F1005,"P2",Profile!R2:R1005,"Fail") -> 0 | M27: =COUNTIFS(Profile!D2:D1005,"Reference Learning Mobile App",Profile!F2:F1005,"P1",Profile!R2:R1005,"Blocked") -> 0 | N27: =COUNTIFS(Profile!D2:D1005,"Reference Learning Mobile App",Profile!F2:F1005,"P2",Profile!R2:R1005,"Blocked") -> 0 | O27: =SUM(K27+M27) -> 0 | P27: =SUM(L27+N27) -> 0 | Q27: =(E27+I27)/C27 -> 1 | R27: =(F27+J27)/D27 -> 1
B28: Offline Desktop | C28: =COUNTIFS(Profile!D2:D1005,"Reference Learning Desktop App",Profile!F2:F1005,"P1") -> 28 | D28: =COUNTIFS(Profile!D2:D1005,"Reference Learning Desktop App",Profile!F2:F1005,"P2") -> 37 | E28: =COUNTIFS(Profile!D2:D1005,"Reference Learning Desktop App",Profile!F2:F1005,"P1",Profile!R2:R1005,"NA") -> 1 | F28: =COUNTIFS(Profile!D2:D1005,"Reference Learning Desktop App",Profile!F2:F1005,"P2",Profile!R2:R1005,"NA") -> 2 | G28: =C28-(I28+K28+M28+E28) -> 0 | H28: =D28-(J28+L28+N28+F28) -> 0 | I28: =COUNTIFS(Profile!D2:D1005,"Reference Learning Desktop App",Profile!F2:F1005,"P1",Profile!R2:R1005,"Pass") -> 27 | J28: =COUNTIFS(Profile!D2:D1005,"Reference Learning Desktop App",Profile!F2:F1005,"P2",Profile!R2:R1005,"Pass") -> 35 | K28: =COUNTIFS(Profile!D2:D1005,"Reference Learning Desktop App",Profile!F2:F1005,"P1",Profile!R2:R1005,"Fail") -> 0 | L28: =COUNTIFS(Profile!D2:D1005,"Reference Learning Desktop App",Profile!F2:F1005,"P2",Profile!R2:R1005,"Fail") -> 0 | M28: =COUNTIFS(Profile!D2:D1005,"Reference Learning Desktop App",Profile!F2:F1005,"P1",Profile!R2:R1005,"Blocked") -> 0 | N28: =COUNTIFS(Profile!D2:D1005,"Reference Learning Desktop App",Profile!F2:F1005,"P2",Profile!R2:R1005,"Blocked") -> 0 | O28: =SUM(K28+M28) -> 0 | P28: =SUM(L28+N28) -> 0 | Q28: =(E28+I28)/C28 -> 1 | R28: =(F28+J28)/D28 -> 1
A29: Course reports | B29: Portal | C29: =COUNTIFS('Course reports'!D2:D1005,"Reference Learning Web App",'Course reports'!F2:F1005,"P1") -> 20 | D29: =COUNTIFS('Course reports'!D2:D1005,"Reference Learning Web App",'Course reports'!F2:F1005,"P2") -> 7 | E29: =COUNTIFS('Course reports'!D2:D1005,"Reference Learning Web App",'Course reports'!F2:F1005,"P1",'Course reports'!Q2:Q1005,"NA") -> 3 | F29: =COUNTIFS('Course reports'!D2:D1005,"Reference Learning Web App",'Course reports'!F2:F1005,"P2",'Course reports'!Q2:Q1005,"NA") -> 0 | G29: =C29-(I29+K29+M29+E29) -> 0 | H29: =D29-(J29+L29+N29+F29) -> 0 | I29: =COUNTIFS('Course reports'!D2:D1005,"Reference Learning Web App",'Course reports'!F2:F1005,"P1",'Course reports'!Q2:Q1005,"Pass") -> 17 | J29: =COUNTIFS('Course reports'!D2:D1005,"Reference Learning Web App",'Course reports'!F2:F1005,"P2",'Course reports'!Q2:Q1005,"Pass") -> 7 | K29: =COUNTIFS('Course reports'!D2:D1005,"Reference Learning Web App",'Course reports'!F2:F1005,"P1",'Course reports'!Q2:Q1005,"Fail") -> 0 | L29: =COUNTIFS('Course reports'!D2:D1005,"Reference Learning Web App",'Course reports'!F2:F1005,"P2",'Course reports'!Q2:Q1005,"Fail") -> 0 | M29: =COUNTIFS('Course reports'!D2:D1005,"Reference Learning Web App",'Course reports'!F2:F1005,"P1",'Course reports'!Q2:Q1005,"Blocked") -> 0 | N29: =COUNTIFS('Course reports'!D2:D1005,"Reference Learning Web App",'Course reports'!F2:F1005,"P2",'Course reports'!Q2:Q1005,"Blocked") -> 0 | O29: =SUM(K29+M29) -> 0 | P29: =SUM(L29+N29) -> 0 | Q29: =(E29+I29)/C29 -> 1 | R29: =(F29+J29)/D29 -> 1
B30: Mobile | C30: =COUNTIFS('Course reports'!D2:D1005,"Reference Learning Mobile App",'Course reports'!F2:F1005,"P1") -> 0 | D30: =COUNTIFS('Course reports'!D2:D1005,"Reference Learning Mobile App",'Course reports'!F2:F1005,"P2") -> 2 | E30: =COUNTIFS('Course reports'!D2:D1005,"Reference Learning Mobile App",'Course reports'!F2:F1005,"P1",'Course reports'!Q2:Q1005,"NA") -> 0 | F30: =COUNTIFS('Course reports'!D2:D1005,"Reference Learning Mobile App",'Course reports'!F2:F1005,"P2",'Course reports'!Q2:Q1005,"NA") -> 0 | G30: =C30-(I30+K30+M30+E30) -> 0 | H30: =D30-(J30+L30+N30+F30) -> 0 | I30: =COUNTIFS('Course reports'!D2:D1005,"Reference Learning Mobile App",'Course reports'!F2:F1005,"P1",'Course reports'!Q2:Q1005,"Pass") -> 0 | J30: =COUNTIFS('Course reports'!D2:D1005,"Reference Learning Mobile App",'Course reports'!F2:F1005,"P2",'Course reports'!Q2:Q1005,"Pass") -> 2 | K30: =COUNTIFS('Course reports'!D2:D1005,"Reference Learning Mobile App",'Course reports'!F2:F1005,"P1",'Course reports'!Q2:Q1005,"Fail") -> 0 | L30: =COUNTIFS('Course reports'!D2:D1005,"Reference Learning Mobile App",'Course reports'!F2:F1005,"P2",'Course reports'!Q2:Q1005,"Fail") -> 0 | M30: =COUNTIFS('Course reports'!D2:D1005,"Reference Learning Mobile App",'Course reports'!F2:F1005,"P1",'Course reports'!Q2:Q1005,"Blocked") -> 0 | N30: =COUNTIFS('Course reports'!D2:D1005,"Reference Learning Mobile App",'Course reports'!F2:F1005,"P2",'Course reports'!Q2:Q1005,"Blocked") -> 0 | O30: =SUM(K30+M30) -> 0 | P30: =SUM(L30+N30) -> 0 | Q30: =(E30+I30)/C30 -> #DIV/0! | R30: =(F30+J30)/D30 -> 1
A31: QUML | B31: Portal | C31: =COUNTIFS(QUML!D2:D1005,"Reference Learning Web App",QUML!F2:F1005,"P1") -> 225 | D31: =COUNTIFS(QUML!D2:D1005,"Reference Learning Web App",QUML!F2:F1005,"P2") -> 192 | E31: =COUNTIFS(QUML!D2:D1005,"Reference Learning Web App",QUML!F2:F1005,"P1",QUML!R2:R1005,"NA") -> 5 | F31: =COUNTIFS(QUML!D2:D1005,"Reference Learning Web App",QUML!F2:F1005,"P2",QUML!R2:R1005,"NA") -> 4 | G31: =C31-(I31+K31+M31+E31) -> 0 | H31: =D31-(J31+L31+N31+F31) -> 0 | I31: =COUNTIFS(QUML!D2:D1005,"Reference Learning Web App",QUML!F2:F1005,"P1",QUML!R2:R1005,"Pass") -> 220 | J31: =COUNTIFS(QUML!D2:D1005,"Reference Learning Web App",QUML!F2:F1005,"P2",QUML!R2:R1005,"Pass") -> 188 | K31: =COUNTIFS(QUML!D2:D1005,"Reference Learning Web App",QUML!F2:F1005,"P1",QUML!R2:R1005,"Fail") -> 0 | L31: =COUNTIFS(QUML!D2:D1005,"Reference Learning Web App",QUML!F2:F1005,"P2",QUML!R2:R1005,"Fail") -> 0 | M31: =COUNTIFS(QUML!D2:D1005,"Reference Learning Web App",QUML!F2:F1005,"P1",QUML!R2:R1005,"Blocked") -> 0 | N31: =COUNTIFS(QUML!D2:D1005,"Reference Learning Web App",QUML!F2:F1005,"P2",QUML!R2:R1005,"Blocked") -> 0 | O31: =SUM(K31+M31) -> 0 | P31: =SUM(L31+N31) -> 0 | Q31: =(E31+I31)/C31 -> 1 | R31: =(F31+J31)/D31 -> 1
B32: Mobile | C32: =COUNTIFS(QUML!D2:D1005,"Reference Learning Mobile App",QUML!F2:F1005,"P1") -> 67 | D32: =COUNTIFS(QUML!D2:D1005,"Reference Learning Mobile App",QUML!F2:F1005,"P2") -> 59 | E32: =COUNTIFS(QUML!D2:D1005,"Reference Learning Mobile App",QUML!F2:F1005,"P1",QUML!R2:R1005,"NA") -> 0 | F32: =COUNTIFS(QUML!D2:D1005,"Reference Learning Mobile App",QUML!F2:F1005,"P2",QUML!R2:R1005,"NA") -> 1 | G32: =C32-(I32+K32+M32+E32) -> 0 | H32: =D32-(J32+L32+N32+F32) -> 0 | I32: =COUNTIFS(QUML!D2:D1005,"Reference Learning Mobile App",QUML!F2:F1005,"P1",QUML!R2:R1005,"Pass") -> 67 | J32: =COUNTIFS(QUML!D2:D1005,"Reference Learning Mobile App",QUML!F2:F1005,"P2",QUML!R2:R1005,"Pass") -> 58 | K32: =COUNTIFS(QUML!D2:D1005,"Reference Learning Mobile App",QUML!F2:F1005,"P1",QUML!R2:R1005,"Fail") -> 0 | L32: =COUNTIFS(QUML!D2:D1005,"Reference Learning Mobile App",QUML!F2:F1005,"P2",QUML!R2:R1005,"Fail") -> 0 | M32: =COUNTIFS(QUML!D2:D1005,"Reference Learning Mobile App",QUML!F2:F1005,"P1",QUML!R2:R1005,"Blocked") -> 0 | N32: =COUNTIFS(QUML!D2:D1005,"Reference Learning Mobile App",QUML!F2:F1005,"P2",QUML!R2:R1005,"Blocked") -> 0 | O32: =SUM(K32+M32) -> 0 | P32: =SUM(L32+N32) -> 0 | Q32: =(E32+I32)/C32 -> 1 | R32: =(F32+J32)/D32 -> 1
B33: Offline Desktop | C33: =COUNTIFS(QUML!D2:D1005,"Reference Learning Desktop App",QUML!F2:F1005,"P1") -> 44 | D33: =COUNTIFS(QUML!D2:D1005,"Reference Learning Desktop App",QUML!F2:F1005,"P2") -> 4 | E33: =COUNTIFS(QUML!D2:D1005,"Reference Learning Offline App",QUML!F2:F1005,"P1",QUML!R2:R1005,"NA") -> 0 | F33: =COUNTIFS(QUML!D2:D1005,"Reference Learning Offline App",QUML!F2:F1005,"P2",QUML!R2:R1005,"NA") -> 0 | G33: =C33-(I33+K33+M33+E33) -> 0 | H33: =D33-(J33+L33+N33+F33) -> 0 | I33: =COUNTIFS(QUML!D2:D1005,"Reference Learning Desktop App",QUML!F2:F1005,"P1",QUML!R2:R1005,"Pass") -> 44 | J33: =COUNTIFS(QUML!D2:D1005,"Reference Learning Desktop App",QUML!F2:F1005,"P2",QUML!R2:R1005,"Pass") -> 4 | K33: =COUNTIFS(QUML!D2:D1005,"Reference Learning Offline App",QUML!F2:F1005,"P1",QUML!R2:R1005,"Fail") -> 0 | L33: =COUNTIFS(QUML!D2:D1005,"Reference Learning Offline App",QUML!F2:F1005,"P2",QUML!R2:R1005,"Fail") -> 0 | M33: =COUNTIFS(QUML!D2:D1005,"Reference Learning Offline App",QUML!F2:F1005,"P1",QUML!R2:R1005,"Blocked") -> 0 | N33: =COUNTIFS(QUML!D2:D1005,"Reference Learning Offline App",QUML!F2:F1005,"P2",QUML!R2:R1005,"Blocked") -> 0 | O33: =SUM(K33+M33) -> 0 | P33: =SUM(L33+N33) -> 0 | Q33: =(E33+I33)/C33 -> 1 | R33: =(F33+J33)/D33 -> 1
A34: Mobile specific Test Cases | B34: Mobile | C34: =COUNTIFS('Mobile specific Test Cases'!D2:D1005,"Reference Learning Mobile App",'Mobile specific Test Cases'!F2:F1005,"P1") -> 32 | D34: =COUNTIFS('Mobile specific Test Cases'!D2:D1005,"Reference Learning Mobile App",'Mobile specific Test Cases'!F2:F1005,"P2") -> 39 | E34: =COUNTIFS('Mobile specific Test Cases'!D2:D1005,"Reference Learning Mobile App",'Mobile specific Test Cases'!F2:F1005,"P1",'Mobile specific Test Cases'!Q2:Q1005,"NA") -> 2 | F34: =COUNTIFS('Mobile specific Test Cases'!D2:D1005,"Reference Learning Mobile App",'Mobile specific Test Cases'!F2:F1005,"P2",'Mobile specific Test Cases'!Q2:Q1005,"NA") -> 0 | G34: =C34-(I34+K34+M34+E34) -> 0 | H34: =D34-(J34+L34+N34+F34) -> 0 | I34: =COUNTIFS('Mobile specific Test Cases'!D2:D1005,"Reference Learning Mobile App",'Mobile specific Test Cases'!F2:F1005,"P1",'Mobile specific Test Cases'!Q2:Q1005,"Pass") -> 30 | J34: =COUNTIFS('Mobile specific Test Cases'!D2:D1005,"Reference Learning Mobile App",'Mobile specific Test Cases'!F2:F1005,"P2",'Mobile specific Test Cases'!Q2:Q1005,"Pass") -> 39 | K34: =COUNTIFS('Mobile specific Test Cases'!D2:D1005,"Reference Learning Mobile App",'Mobile specific Test Cases'!F2:F1005,"P1",'Mobile specific Test Cases'!Q2:Q1005,"Fail") -> 0 | L34: =COUNTIFS('Mobile specific Test Cases'!D2:D1005,"Reference Learning Mobile App",'Mobile specific Test Cases'!F2:F1005,"P2",'Mobile specific Test Cases'!Q2:Q1005,"Fail") -> 0 | M34: =COUNTIFS('Mobile specific Test Cases'!D2:D1005,"Reference Learning Mobile App",'Mobile specific Test Cases'!F2:F1005,"P1",'Mobile specific Test Cases'!Q2:Q1005,"Blocked") -> 0 | N34: =COUNTIFS('Mobile specific Test Cases'!D2:D1005,"Reference Learning Mobile App",'Mobile specific Test Cases'!F2:F1005,"P2",'Mobile specific Test Cases'!Q2:Q1005,"Blocked") -> 0 | O34: =SUM(K34+M34) -> 0 | P34: =SUM(L34+N34) -> 0 | Q34: =(E34+I34)/C34 -> 1 | R34: =(F34+J34)/D34 -> 1
A35: Mobile configurability | B35: Mobile | C35: =COUNTIFS('Mobile configurability'!D2:D1005,"Reference Learning Mobile App",'Mobile configurability'!F2:F1005,"P1") -> 34 | D35: =COUNTIFS('Mobile configurability'!D2:D1005,"Reference Learning Mobile App",'Mobile configurability'!F2:F1005,"P2") -> 76 | E35: =COUNTIFS('Mobile configurability'!D2:D1005,"Reference Learning Mobile App",'Mobile configurability'!F2:F1005,"P1",'Mobile configurability'!Q2:Q1005,"NA") -> 0 | F35: =COUNTIFS('Mobile configurability'!D2:D1005,"Reference Learning Mobile App",'Mobile configurability'!F2:F1005,"P2",'Mobile configurability'!Q2:Q1005,"NA") -> 7 | G35: =C35-(I35+K35+M35+E35) -> 0 | H35: =D35-(J35+L35+N35+F35) -> 0 | I35: =COUNTIFS('Mobile configurability'!D2:D1005,"Reference Learning Mobile App",'Mobile configurability'!F2:F1005,"P1",'Mobile configurability'!Q2:Q1005,"Pass") -> 34 | J35: =COUNTIFS('Mobile configurability'!D2:D1005,"Reference Learning Mobile App",'Mobile configurability'!F2:F1005,"P2",'Mobile configurability'!Q2:Q1005,"Pass") -> 69 | K35: =COUNTIFS('Mobile configurability'!D2:D1005,"Reference Learning Mobile App",'Mobile configurability'!F2:F1005,"P1",'Mobile configurability'!Q2:Q1005,"Fail") -> 0 | L35: =COUNTIFS('Mobile configurability'!D2:D1005,"Reference Learning Mobile App",'Mobile configurability'!F2:F1005,"P2",'Mobile configurability'!Q2:Q1005,"Fail") -> 0 | M35: =COUNTIFS('Mobile configurability'!D2:D1005,"Reference Learning Mobile App",'Mobile configurability'!F2:F1005,"P1",'Mobile configurability'!Q2:Q1005,"Blocked") -> 0 | N35: =COUNTIFS('Mobile configurability'!D2:D1005,"Reference Learning Mobile App",'Mobile configurability'!F2:F1005,"P2",'Mobile configurability'!Q2:Q1005,"Blocked") -> 0 | O35: =SUM(K35+M35) -> 0 | P35: =SUM(L35+N35) -> 0 | Q35: =(E35+I35)/C35 -> 1 | R35: =(F35+J35)/D35 -> 1
A36: Org admin reports | B36: Portal | C36: =COUNTIFS('Org admin reports'!D2:D1005,"Reference Learning Web App",'Org admin reports'!F2:F1005,"P1") -> 69 | D36: =COUNTIFS('Org admin reports'!D2:D1005,"Reference Learning Web App",'Org admin reports'!F2:F1005,"P2") -> 26 | E36: =COUNTIFS('Org admin reports'!D2:D1005,"Reference Learning Web App",'Org admin reports'!F2:F1005,"P1",'Org admin reports'!Q2:Q1005,"NA") -> 5 | F36: =COUNTIFS('Org admin reports'!D2:D1005,"Reference Learning Web App",'Org admin reports'!F2:F1005,"P2",'Org admin reports'!Q2:Q1005,"NA") -> 1 | G36: =C36-(I36+K36+M36+E36) -> 0 | H36: =D36-(J36+L36+N36+F36) -> 0 | I36: =COUNTIFS('Org admin reports'!D2:D1005,"Reference Learning Web App",'Org admin reports'!F2:F1005,"P1",'Org admin reports'!Q2:Q1005,"Pass") -> 64 | J36: =COUNTIFS('Org admin reports'!D2:D1005,"Reference Learning Web App",'Org admin reports'!F2:F1005,"P2",'Org admin reports'!Q2:Q1005,"Pass") -> 25 | K36: =COUNTIFS('Org admin reports'!D2:D1005,"Reference Learning Web App",'Org admin reports'!F2:F1005,"P1",'Org admin reports'!Q2:Q1005,"Fail") -> 0 | L36: =COUNTIFS('Org admin reports'!D2:D1005,"Reference Learning Web App",'Org admin reports'!F2:F1005,"P2",'Org admin reports'!Q2:Q1005,"Fail") -> 0 | M36: =COUNTIFS('Org admin reports'!D2:D1005,"Reference Learning Web App",'Org admin reports'!F2:F1005,"P1",'Org admin reports'!Q2:Q1005,"Blocked") -> 0 | N36: =COUNTIFS('Org admin reports'!D2:D1005,"Reference Learning Web App",'Org admin reports'!F2:F1005,"P2",'Org admin reports'!Q2:Q1005,"Blocked") -> 0 | O36: =SUM(K36+M36) -> 0 | P36: =SUM(L36+N36) -> 0 | Q36: =(E36+I36)/C36 -> 1 | R36: =(F36+J36)/D36 -> 1
B37: Mobile | C37: =COUNTIFS('Org admin reports'!D2:D1005,"Reference Learning Mobile App",'Org admin reports'!F2:F1005,"P1") -> 0 | D37: =COUNTIFS('Org admin reports'!D2:D1005,"Reference Learning Mobile App",'Org admin reports'!F2:F1005,"P2") -> 5 | E37: =COUNTIFS('Org admin reports'!D2:D1005,"Reference Learning Mobile App",'Org admin reports'!F2:F1005,"P1",'Org admin reports'!Q2:Q1005,"NA") -> 0 | F37: =COUNTIFS('Org admin reports'!D2:D1005,"Reference Learning Mobile App",'Org admin reports'!F2:F1005,"P2",'Org admin reports'!Q2:Q1005,"NA") -> 0 | G37: =C37-(I37+K37+M37+E37) -> 0 | H37: =D37-(J37+L37+N37+F37) -> 0 | I37: =COUNTIFS('Org admin reports'!D2:D1005,"Reference Learning Mobile App",'Org admin reports'!F2:F1005,"P1",'Org admin reports'!Q2:Q1005,"Pass") -> 0 | J37: =COUNTIFS('Org admin reports'!D2:D1005,"Reference Learning Mobile App",'Org admin reports'!F2:F1005,"P2",'Org admin reports'!Q2:Q1005,"Pass") -> 5 | K37: =COUNTIFS('Org admin reports'!D2:D1005,"Reference Learning Mobile App",'Org admin reports'!F2:F1005,"P1",'Org admin reports'!Q2:Q1005,"Fail") -> 0 | L37: =COUNTIFS('Org admin reports'!D2:D1005,"Reference Learning Mobile App",'Org admin reports'!F2:F1005,"P2",'Org admin reports'!Q2:Q1005,"Fail") -> 0 | M37: =COUNTIFS('Org admin reports'!D2:D1005,"Reference Learning Mobile App",'Org admin reports'!F2:F1005,"P1",'Org admin reports'!Q2:Q1005,"Blocked") -> 0 | N37: =COUNTIFS('Org admin reports'!D2:D1005,"Reference Learning Mobile App",'Org admin reports'!F2:F1005,"P2",'Org admin reports'!Q2:Q1005,"Blocked") -> 0 | O37: =SUM(K37+M37) -> 0 | P37: =SUM(L37+N37) -> 0 | Q37: =(E37+I37)/C37 -> #DIV/0! | R37: =(F37+J37)/D37 -> 1
A38: QR code | B38: Portal | C38: =COUNTIFS('QR code'!D2:D1005,"Reference Learning Web App",'QR code'!F2:F1005,"P1") -> 78 | D38: =COUNTIFS('QR code'!D2:D1005,"Reference Learning Web App",'QR code'!F2:F1005,"P2") -> 18 | E38: =COUNTIFS('QR code'!D2:D1005,"Reference Learning Web App",'QR code'!F2:F1005,"P1",'QR code'!R2:R1005,"NA") -> 5 | F38: =COUNTIFS('QR code'!D2:D1005,"Reference Learning Web App",'QR code'!F2:F1005,"P2",'QR code'!R2:R1005,"NA") -> 4 | G38: =C38-(I38+K38+M38+E38) -> 0 | H38: =D38-(J38+L38+N38+F38) -> 0 | I38: =COUNTIFS('QR code'!D2:D1005,"Reference Learning Web App",'QR code'!F2:F1005,"P1",'QR code'!R2:R1005,"Pass") -> 73 | J38: =COUNTIFS('QR code'!D2:D1005,"Reference Learning Web App",'QR code'!F2:F1005,"P2",'QR code'!R2:R1005,"Pass") -> 14 | K38: =COUNTIFS('QR code'!D2:D1005,"Reference Learning Web App",'QR code'!F2:F1005,"P1",'QR code'!R2:R1005,"Fail") -> 0 | L38: =COUNTIFS('QR code'!D2:D1005,"Reference Learning Web App",'QR code'!F2:F1005,"P2",'QR code'!R2:R1005,"Fail") -> 0 | M38: =COUNTIFS('QR code'!D2:D1005,"Reference Learning Web App",'QR code'!F2:F1005,"P1",'QR code'!R2:R1005,"Blocked") -> 0 | N38: =COUNTIFS('QR code'!D2:D1005,"Reference Learning Web App",'QR code'!F2:F1005,"P2",'QR code'!R2:R1005,"Blocked") -> 0 | O38: =SUM(K38+M38) -> 0 | P38: =SUM(L38+N38) -> 0 | Q38: =(E38+I38)/C38 -> 1 | R38: =(F38+J38)/D38 -> 1
B39: Mobile | C39: =COUNTIFS('QR code'!D2:D1005,"Reference Learning Mobile App",'QR code'!F2:F1005,"P1") -> 21 | D39: =COUNTIFS('QR code'!D2:D1005,"Reference Learning Mobile App",'QR code'!F2:F1005,"P2") -> 40 | E39: =COUNTIFS('QR code'!D2:D1005,"Reference Learning Mobile App",'QR code'!F2:F1005,"P1",'QR code'!R2:R1005,"NA") -> 5 | F39: =COUNTIFS('QR code'!D2:D1005,"Reference Learning Mobile App",'QR code'!F2:F1005,"P2",'QR code'!R2:R1005,"NA") -> 5 | G39: =C39-(I39+K39+M39+E39) -> 0 | H39: =D39-(J39+L39+N39+F39) -> 0 | I39: =COUNTIFS('QR code'!D2:D1005,"Reference Learning Mobile App",'QR code'!F2:F1005,"P1",'QR code'!R2:R1005,"Pass") -> 16 | J39: =COUNTIFS('QR code'!D2:D1005,"Reference Learning Mobile App",'QR code'!F2:F1005,"P2",'QR code'!R2:R1005,"Pass") -> 35 | K39: =COUNTIFS('QR code'!D2:D1005,"Reference Learning Mobile App",'QR code'!F2:F1005,"P1",'QR code'!R2:R1005,"Fail") -> 0 | L39: =COUNTIFS('QR code'!D2:D1005,"Reference Learning Mobile App",'QR code'!F2:F1005,"P2",'QR code'!R2:R1005,"Fail") -> 0 | M39: =COUNTIFS('QR code'!D2:D1005,"Reference Learning Mobile App",'QR code'!F2:F1005,"P1",'QR code'!R2:R1005,"Blocked") -> 0 | N39: =COUNTIFS('QR code'!D2:D1005,"Reference Learning Mobile App",'QR code'!F2:F1005,"P2",'QR code'!R2:R1005,"Blocked") -> 0 | O39: =SUM(K39+M39) -> 0 | P39: =SUM(L39+N39) -> 0 | Q39: =(E39+I39)/C39 -> 1 | R39: =(F39+J39)/D39 -> 1
A40: Portal/ Desktop App Configurability | B40: Portal | C40: =COUNTIFS('Portal Desktop App Configurabil'!D2:D1005,"Reference Learning Web App",'Portal Desktop App Configurabil'!F2:F1005,"P1") -> 36 | D40: =COUNTIFS('Portal Desktop App Configurabil'!D2:D1005,"Reference Learning Web App",'Portal Desktop App Configurabil'!F2:F1005,"P2") -> 25 | E40: =COUNTIFS('Portal Desktop App Configurabil'!D2:D1005,"Reference Learning Web App",'Portal Desktop App Configurabil'!F2:F1005,"P1",'Portal Desktop App Configurabil'!Q2:Q1005,"NA") -> 2 | F40: =COUNTIFS('Portal Desktop App Configurabil'!D2:D1005,"Reference Learning Web App",'Portal Desktop App Configurabil'!F2:F1005,"P2",'Portal Desktop App Configurabil'!Q2:Q1005,"NA") -> 1 | G40: =C40-(I40+K40+M40+E40) -> 0 | H40: =D40-(J40+L40+N40+F40) -> 0 | I40: =COUNTIFS('Portal Desktop App Configurabil'!D2:D1005,"Reference Learning Web App",'Portal Desktop App Configurabil'!F2:F1005,"P1",'Portal Desktop App Configurabil'!Q2:Q1005,"Pass") -> 34 | J40: =COUNTIFS('Portal Desktop App Configurabil'!D2:D1005,"Reference Learning Web App",'Portal Desktop App Configurabil'!F2:F1005,"P2",'Portal Desktop App Configurabil'!Q2:Q1005,"Pass") -> 24 | K40: =COUNTIFS('Portal Desktop App Configurabil'!D2:D1005,"Reference Learning Web App",'Portal Desktop App Configurabil'!F2:F1005,"P1",'Portal Desktop App Configurabil'!Q2:Q1005,"Fail") -> 0 | L40: =COUNTIFS('Portal Desktop App Configurabil'!D2:D1005,"Reference Learning Web App",'Portal Desktop App Configurabil'!F2:F1005,"P2",'Portal Desktop App Configurabil'!Q2:Q1005,"Fail") -> 0 | M40: =COUNTIFS('Portal Desktop App Configurabil'!D2:D1005,"Reference Learning Web App",'Portal Desktop App Configurabil'!F2:F1005,"P1",'Portal Desktop App Configurabil'!Q2:Q1005,"Blocked") -> 0 | N40: =COUNTIFS('Portal Desktop App Configurabil'!D2:D1005,"Reference Learning Web App",'Portal Desktop App Configurabil'!F2:F1005,"P2",'Portal Desktop App Configurabil'!Q2:Q1005,"Blocked") -> 0 | O40: =SUM(K40+M40) -> 0 | P40: =SUM(L40+N40) -> 0 | Q40: =(E40+I40)/C40 -> 1 | R40: =(F40+J40)/D40 -> 1
B41: Offline Desktop | C41: =COUNTIFS('Portal Desktop App Configurabil'!D2:D1005,"Reference Learning Desktop App",'Portal Desktop App Configurabil'!F2:F1005,"P1") -> 4 | D41: =COUNTIFS('Portal Desktop App Configurabil'!D2:D1005,"Reference Learning Desktop App",'Portal Desktop App Configurabil'!F2:F1005,"P2") -> 9 | E41: =COUNTIFS('Portal Desktop App Configurabil'!D2:D1005,"Reference Learning Desktop App",'Portal Desktop App Configurabil'!F2:F1005,"P1",'Portal Desktop App Configurabil'!Q2:Q1005,"NA") -> 0 | F41: =COUNTIFS('Portal Desktop App Configurabil'!D2:D1005,"Reference Learning Desktop App",'Portal Desktop App Configurabil'!F2:F1005,"P2",'Portal Desktop App Configurabil'!Q2:Q1005,"NA") -> 0 | G41: =C41-(I41+K41+M41+E41) -> 0 | H41: =D41-(J41+L41+N41+F41) -> 0 | I41: =COUNTIFS('Portal Desktop App Configurabil'!D2:D1005,"Reference Learning Desktop App",'Portal Desktop App Configurabil'!F2:F1005,"P1",'Portal Desktop App Configurabil'!Q2:Q1005,"Pass") -> 4 | J41: =COUNTIFS('Portal Desktop App Configurabil'!D2:D1005,"Reference Learning Desktop App",'Portal Desktop App Configurabil'!F2:F1005,"P2",'Portal Desktop App Configurabil'!Q2:Q1005,"Pass") -> 9 | K41: =COUNTIFS('Portal Desktop App Configurabil'!D2:D1005,"Reference Learning Desktop App",'Portal Desktop App Configurabil'!F2:F1005,"P1",'Portal Desktop App Configurabil'!Q2:Q1005,"Fail") -> 0 | L41: =COUNTIFS('Portal Desktop App Configurabil'!D2:D1005,"Reference Learning Desktop App",'Portal Desktop App Configurabil'!F2:F1005,"P2",'Portal Desktop App Configurabil'!Q2:Q1005,"Fail") -> 0 | M41: =COUNTIFS('Portal Desktop App Configurabil'!D2:D1005,"Reference Learning Desktop App",'Portal Desktop App Configurabil'!F2:F1005,"P1",'Portal Desktop App Configurabil'!Q2:Q1005,"Blocked") -> 0 | N41: =COUNTIFS('Portal Desktop App Configurabil'!D2:D1005,"Reference Learning Desktop App",'Portal Desktop App Configurabil'!F2:F1005,"P2",'Portal Desktop App Configurabil'!Q2:Q1005,"Blocked") -> 0 | O41: =SUM(K41+M41) -> 0 | P41: =SUM(L41+N41) -> 0 | Q41: =(E41+I41)/C41 -> 1 | R41: =(F41+J41)/D41 -> 1
A42: Sunbird UCI | B42: Portal | C42: =COUNTIFS('Sunbird UCI'!D2:D1005,"Portal tara",'Sunbird UCI'!F2:F1005,"P1") -> 21 | D42: =COUNTIFS('Sunbird UCI'!D2:D1005,"Portal tara",'Sunbird UCI'!F2:F1005,"P2") -> 21 | E42: =COUNTIFS('Sunbird UCI'!D2:D1005,"Portal tara",'Sunbird UCI'!F2:F1005,"P1",'Sunbird UCI'!R2:R1005,"NA") -> 21 | F42: =COUNTIFS('Sunbird UCI'!D2:D1005,"Portal tara",'Sunbird UCI'!F2:F1005,"P2",'Sunbird UCI'!R2:R1005,"NA") -> 21 | G42: =C42-(I42+K42+M42+E42) -> 0 | H42: =D42-(J42+L42+N42+F42) -> 0 | I42: =COUNTIFS('Sunbird UCI'!D2:D1005,"Portal tara",'Sunbird UCI'!F2:F1005,"P1",'Sunbird UCI'!R2:R1005,"Pass") -> 0 | J42: =COUNTIFS('Sunbird UCI'!D2:D1005,"Portal tara",'Sunbird UCI'!F2:F1005,"P2",'Sunbird UCI'!R2:R1005,"Pass") -> 0 | K42: =COUNTIFS('Sunbird UCI'!D2:D1005,"Portal tara",'Sunbird UCI'!F2:F1005,"P1",'Sunbird UCI'!R2:R1005,"Fail") -> 0 | L42: =COUNTIFS('Sunbird UCI'!D2:D1005,"Portal tara",'Sunbird UCI'!F2:F1005,"P2",'Sunbird UCI'!R2:R1005,"Fail") -> 0 | M42: =COUNTIFS('Sunbird UCI'!D2:D1005,"Portal tara",'Sunbird UCI'!F2:F1005,"P1",'Sunbird UCI'!R2:R1005,"Blocked") -> 0 | N42: =COUNTIFS('Sunbird UCI'!D2:D1005,"Portal tara",'Sunbird UCI'!F2:F1005,"P2",'Sunbird UCI'!R2:R1005,"Blocked") -> 0 | O42: =SUM(K42+M42) -> 0 | P42: =SUM(L42+N42) -> 0 | Q42: =(E42+I42)/C42 -> 1 | R42: =(F42+J42)/D42 -> 1
B43: Mobile | C43: =COUNTIFS('Sunbird UCI'!D2:D1005,"Mobile tara",'Sunbird UCI'!F2:F1005,"P1") -> 1 | D43: =COUNTIFS('Sunbird UCI'!D2:D1005,"Mobile tara",'Sunbird UCI'!F2:F1005,"P2") -> 5 | E43: =COUNTIFS('Sunbird UCI'!D2:D1005,"Mobile tara",'Sunbird UCI'!F2:F1005,"P1",'Sunbird UCI'!R2:R1005,"NA") -> 1 | F43: =COUNTIFS('Sunbird UCI'!D2:D1005,"Mobile tara",'Sunbird UCI'!F2:F1005,"P2",'Sunbird UCI'!R2:R1005,"NA") -> 5 | G43: =C43-(I43+K43+M43+E43) -> 0 | H43: =D43-(J43+L43+N43+F43) -> 0 | I43: =COUNTIFS('Sunbird UCI'!D2:D1005,"Mobile tara",'Sunbird UCI'!F2:F1005,"P1",'Sunbird UCI'!R2:R1005,"Pass") -> 0 | J43: =COUNTIFS('Sunbird UCI'!D2:D1005,"Mobile tara",'Sunbird UCI'!F2:F1005,"P2",'Sunbird UCI'!R2:R1005,"Pass") -> 0 | K43: =COUNTIFS('Sunbird UCI'!D2:D1005,"Mobile tara",'Sunbird UCI'!F2:F1005,"P1",'Sunbird UCI'!R2:R1005,"Fail") -> 0 | L43: =COUNTIFS('Sunbird UCI'!D2:D1005,"Mobile tara",'Sunbird UCI'!F2:F1005,"P2",'Sunbird UCI'!R2:R1005,"Fail") -> 0 | M43: =COUNTIFS('Sunbird UCI'!D2:D1005,"Mobile tara",'Sunbird UCI'!F2:F1005,"P1",'Sunbird UCI'!R2:R1005,"Blocked") -> 0 | N43: =COUNTIFS('Sunbird UCI'!D2:D1005,"Mobile tara",'Sunbird UCI'!F2:F1005,"P2",'Sunbird UCI'!R2:R1005,"Blocked") -> 0 | O43: =SUM(K43+M43) -> 0 | P43: =SUM(L43+N43) -> 0 | Q43: =(E43+I43)/C43 -> 1 | R43: =(F43+J43)/D43 -> 1
B44: Watsup Chatbot | C44: =COUNTIFS('Sunbird UCI'!D2:D1005,"Watsup chatbot",'Sunbird UCI'!F2:F1005,"P1") -> 40 | D44: =COUNTIFS('Sunbird UCI'!D2:D1005,"Watsup chatbot",'Sunbird UCI'!F2:F1005,"P2") -> 0 | E44: =COUNTIFS('Sunbird UCI'!D2:D1005,"Watsup Chatbot",'Sunbird UCI'!F2:F1005,"P1",'Sunbird UCI'!R2:R1005,"NA") -> 40 | F44: =COUNTIFS('Sunbird UCI'!D2:D1005,"Watsup Chatbot",'Sunbird UCI'!F2:F1005,"P2",'Sunbird UCI'!R2:R1005,"NA") -> 0 | G44: =C44-(I44+K44+M44+E44) -> 0 | H44: =D44-(J44+L44+N44+F44) -> 0 | I44: =COUNTIFS('Sunbird UCI'!D2:D1005,"Watsup Chatbot",'Sunbird UCI'!F2:F1005,"P1",'Sunbird UCI'!R2:R1005,"Pass") -> 0 | J44: =COUNTIFS('Sunbird UCI'!D2:D1005,"Watsup Chatbot",'Sunbird UCI'!F2:F1005,"P2",'Sunbird UCI'!R2:R1005,"Pass") -> 0 | K44: =COUNTIFS('Sunbird UCI'!D2:D1005,"Watsup Chatbot",'Sunbird UCI'!F2:F1005,"P1",'Sunbird UCI'!R2:R1005,"Fail") -> 0 | L44: =COUNTIFS('Sunbird UCI'!D2:D1005,"Watsup Chatbot",'Sunbird UCI'!F2:F1005,"P2",'Sunbird UCI'!R2:R1005,"Fail") -> 0 | M44: =COUNTIFS('Sunbird UCI'!D2:D1005,"Watsup Chatbot",'Sunbird UCI'!F2:F1005,"P1",'Sunbird UCI'!R2:R1005,"Blocked") -> 0 | N44: =COUNTIFS('Sunbird UCI'!D2:D1005,"Watsup Chatbot",'Sunbird UCI'!F2:F1005,"P2",'Sunbird UCI'!R2:R1005,"Blocked") -> 0 | O44: =SUM(K44+M44) -> 0 | P44: =SUM(L44+N44) -> 0 | Q44: =(E44+I44)/C44 -> 1 | R44: =(F44+J44)/D44 -> #DIV/0!
A45: Groups | B45: Portal | C45: =COUNTIFS(Groups!D2:D1005,"Reference Learning Web App",Groups!F2:F1005,"P1") -> 108 | D45: =COUNTIFS(Groups!D2:D1005,"Reference Learning Web App",Groups!F2:F1005,"P2") -> 65 | E45: =COUNTIFS(Groups!D2:D1005,"Reference Learning Web App",Groups!F2:F1005,"P1",Groups!Q2:Q1005,"NA") -> 0 | F45: =COUNTIFS(Groups!D2:D1005,"Reference Learning Web App",Groups!F2:F1005,"P2",Groups!Q2:Q1005,"NA") -> 0 | G45: =C45-(I45+K45+M45+E45) -> 0 | H45: =D45-(J45+L45+N45+F45) -> 0 | I45: =COUNTIFS(Groups!D2:D1005,"Reference Learning Web App",Groups!F2:F1005,"P1",Groups!Q2:Q1005,"Pass") -> 108 | J45: =COUNTIFS(Groups!D2:D1005,"Reference Learning Web App",Groups!F2:F1005,"P2",Groups!Q2:Q1005,"Pass") -> 65 | K45: =COUNTIFS(Groups!D2:D1005,"Reference Learning Web App",Groups!F2:F1005,"P1",Groups!Q2:Q1005,"Fail") -> 0 | L45: =COUNTIFS(Groups!D2:D1005,"Reference Learning Web App",Groups!F2:F1005,"P2",Groups!Q2:Q1005,"Fail") -> 0 | M45: =COUNTIFS(Groups!D2:D1005,"Reference Learning Web App",Groups!F2:F1005,"P1",Groups!Q2:Q1005,"Blocked") -> 0 | N45: =COUNTIFS(Groups!D2:D1005,"Reference Learning Web App",Groups!F2:F1005,"P2",Groups!Q2:Q1005,"Blocked") -> 0 | O45: =SUM(K45+M45) -> 0 | P45: =SUM(L45+N45) -> 0 | Q45: =(E45+I45)/C45 -> 1 | R45: =(F45+J45)/D45 -> 1
B46: Mobile | C46: =COUNTIFS(Groups!D2:D1005,"Reference Learning Mobile App",Groups!F2:F1005,"P1") -> 42 | D46: =COUNTIFS(Groups!D2:D1005,"Reference Learning Mobile App",Groups!F2:F1005,"P2") -> 86 | E46: =COUNTIFS(Groups!D2:D1005,"Reference Learning Mobile App",Groups!F2:F1005,"P1",Groups!Q2:Q1005,"NA") -> 0 | F46: =COUNTIFS(Groups!D2:D1005,"Reference Learning Mobile App",Groups!F2:F1005,"P2",Groups!Q2:Q1005,"NA") -> 2 | G46: =C46-(I46+K46+M46+E46) -> 0 | H46: =D46-(J46+L46+N46+F46) -> 0 | I46: =COUNTIFS(Groups!D2:D1005,"Reference Learning Mobile App",Groups!F2:F1005,"P1",Groups!Q2:Q1005,"Pass") -> 42 | J46: =COUNTIFS(Groups!D2:D1005,"Reference Learning Mobile App",Groups!F2:F1005,"P2",Groups!Q2:Q1005,"Pass") -> 84 | K46: =COUNTIFS(Groups!D2:D1005,"Reference Learning Mobile App",Groups!F2:F1005,"P1",Groups!Q2:Q1005,"Fail") -> 0 | L46: =COUNTIFS(Groups!D2:D1005,"Reference Learning Mobile App",Groups!F2:F1005,"P2",Groups!Q2:Q1005,"Fail") -> 0 | M46: =COUNTIFS(Groups!D2:D1005,"Reference Learning Mobile App",Groups!F2:F1005,"P1",Groups!Q2:Q1005,"Blocked") -> 0 | N46: =COUNTIFS(Groups!D2:D1005,"Reference Learning Mobile App",Groups!F2:F1005,"P2",Groups!Q2:Q1005,"Blocked") -> 0 | O46: =SUM(K46+M46) -> 0 | P46: =SUM(L46+N46) -> 0 | Q46: =(E46+I46)/C46 -> 1 | R46: =(F46+J46)/D46 -> 1
A47: Accessibility | B47: Portal | C47: =COUNTIFS(Accessibility!D2:D1005,"Reference Learning Web App",Accessibility!F2:F1005,"P1") -> 73 | D47: =COUNTIFS(Accessibility!D2:D1005,"Reference Learning Web App",Accessibility!F2:F1005,"P2") -> 38 | E47: =COUNTIFS(Accessibility!D2:D1005,"Reference Learning Web App",Accessibility!F2:F1005,"P1",Accessibility!Q2:Q1005,"NA") -> 1 | F47: =COUNTIFS(Accessibility!D2:D1005,"Reference Learning Web App",Accessibility!F2:F1005,"P2",Accessibility!Q2:Q1005,"NA") -> 1 | G47: =C47-(I47+K47+M47+E47) -> 0 | H47: =D47-(J47+L47+N47+F47) -> 0 | I47: =COUNTIFS(Accessibility!D2:D1005,"Reference Learning Web App",Accessibility!F2:F1005,"P1",Accessibility!Q2:Q1005,"Pass") -> 72 | J47: =COUNTIFS(Accessibility!D2:D1005,"Reference Learning Web App",Accessibility!F2:F1005,"P2",Accessibility!Q2:Q1005,"Pass") -> 37 | K47: =COUNTIFS(Accessibility!D2:D1005,"Reference Learning Web App",Accessibility!F2:F1005,"P1",Accessibility!Q2:Q1005,"Failed") -> 0 | L47: =COUNTIFS(Accessibility!D2:D1005,"Reference Learning Web App",Accessibility!F2:F1005,"P2",Accessibility!Q2:Q1005,"Failed") -> 0 | M47: =COUNTIFS(Accessibility!D2:D1005,"Reference Learning Web App",Accessibility!F2:F1005,"P1",Accessibility!Q2:Q1005,"Blocked") -> 0 | N47: =COUNTIFS(Accessibility!D2:D1005,"Reference Learning Web App",Accessibility!F2:F1005,"P2",Accessibility!Q2:Q1005,"Blocked") -> 0 | O47: =SUM(K47+M47) -> 0 | P47: =SUM(L47+N47) -> 0 | Q47: =(E47+I47)/C47 -> 1 | R47: =(F47+J47)/D47 -> 1
B48: Mobile | C48: =COUNTIFS(Accessibility!D2:D1005,"Reference Learning Mobile App",Accessibility!F2:F1005,"P1") -> 65 | D48: =COUNTIFS(Accessibility!D2:D1005,"Reference Learning Mobile App",Accessibility!F2:F1005,"P2") -> 39 | E48: =COUNTIFS(Accessibility!D2:D1005,"Reference Learning Mobile App",Accessibility!F2:F1005,"P1",Accessibility!Q2:Q1005,"NA") -> 1 | F48: =COUNTIFS(Accessibility!D2:D1005,"Reference Learning Mobile App",Accessibility!F2:F1005,"P2",Accessibility!Q2:Q1005,"NA") -> 2 | G48: =C48-(I48+K48+M48+E48) -> 0 | H48: =D48-(J48+L48+N48+F48) -> 0 | I48: =COUNTIFS(Accessibility!D2:D1005,"Reference Learning Mobile App",Accessibility!F2:F1005,"P1",Accessibility!Q2:Q1005,"Pass") -> 64 | J48: =COUNTIFS(Accessibility!D2:D1005,"Reference Learning Mobile App",Accessibility!F2:F1005,"P2",Accessibility!Q2:Q1005,"Pass") -> 37 | K48: =COUNTIFS(Accessibility!D2:D1005,"Reference Learning Mobile App",Accessibility!F2:F1005,"P1",Accessibility!Q2:Q1005,"Fail") -> 0 | L48: =COUNTIFS(Accessibility!D2:D1005,"Reference Learning Mobile App",Accessibility!F2:F1005,"P2",Accessibility!Q2:Q1005,"Fail") -> 0 | M48: =COUNTIFS(Accessibility!D2:D1005,"Reference Learning Mobile App",Accessibility!F2:F1005,"P1",Accessibility!Q2:Q1005,"Blocked") -> 0 | N48: =COUNTIFS(Accessibility!D2:D1005,"Reference Learning Mobile App",Accessibility!F2:F1005,"P2",Accessibility!Q2:Q1005,"Blocked") -> 0 | O48: =SUM(K48+M48) -> 0 | P48: =SUM(L48+N48) -> 0 | Q48: =(E48+I48)/C48 -> 1 | R48: =(F48+J48)/D48 -> 1
B49: Offline Desktop | C49: =COUNTIFS(Accessibility!D2:D1005,"Reference Learning Desktop App",Accessibility!F2:F1005,"P1") -> 18 | D49: =COUNTIFS(Accessibility!D2:D1005,"Reference Learning Desktop App",Accessibility!F2:F1005,"P2") -> 16 | E49: =COUNTIFS(Accessibility!D2:D1005,"Reference Learning Desktop App",Accessibility!F2:F1005,"P1",Accessibility!Q2:Q1005,"NA") -> 1 | F49: =COUNTIFS(Accessibility!D2:D1005,"Reference Learning Desktop App",Accessibility!F2:F1005,"P2",Accessibility!Q2:Q1005,"NA") -> 1 | G49: =C49-(I49+K49+M49+E49) -> 0 | H49: =D49-(J49+L49+N49+F49) -> 0 | I49: =COUNTIFS(Accessibility!D2:D1005,"Reference Learning Desktop App",Accessibility!F2:F1005,"P1",Accessibility!Q2:Q1005,"Pass") -> 17 | J49: =COUNTIFS(Accessibility!D2:D1005,"Reference Learning Desktop App",Accessibility!F2:F1005,"P2",Accessibility!Q2:Q1005,"Pass") -> 15 | K49: =COUNTIFS(Accessibility!D2:D1005,"Reference Learning Desktop App",Accessibility!F2:F1005,"P1",Accessibility!Q2:Q1005,"Fail") -> 0 | L49: =COUNTIFS(Accessibility!D2:D1005,"Reference Learning Desktop App",Accessibility!F2:F1005,"P2",Accessibility!Q2:Q1005,"Fail") -> 0 | M49: =COUNTIFS(Accessibility!D2:D1005,"Reference Learning Desktop App",Accessibility!F2:F1005,"P1",Accessibility!Q2:Q1005,"Blocked") -> 0 | N49: =COUNTIFS(Accessibility!D2:D1005,"Reference Learning Desktop App",Accessibility!F2:F1005,"P2",Accessibility!Q2:Q1005,"Blocked") -> 0 | O49: =SUM(K49+M49) -> 0 | P49: =SUM(L49+N49) -> 0 | Q49: =(E49+I49)/C49 -> 1 | R49: =(F49+J49)/D49 -> 1
A50: Offline Scenarios | B50: Mobile | C50: =COUNTIFS('Offline Scenarios'!D2:D1005,"Reference Learning Mobile App",'Offline Scenarios'!F2:F1005,"P1") -> 6 | D50: =COUNTIFS('Offline Scenarios'!D2:D1005,"Reference Learning Mobile App",'Offline Scenarios'!F2:F1005,"P2") -> 11 | E50: =COUNTIFS('Offline Scenarios'!D2:D1005,"Reference Learning Mobile App",'Offline Scenarios'!F2:F1005,"P1",'Offline Scenarios'!Q2:Q1005,"NA") -> 0 | F50: =COUNTIFS('Offline Scenarios'!D2:D1005,"Reference Learning Mobile App",'Offline Scenarios'!F2:F1005,"P2",'Offline Scenarios'!Q2:Q1005,"NA") -> 3 | G50: =C50-(I50+K50+M50+E50) -> 0 | H50: =D50-(J50+L50+N50+F50) -> 0 | I50: =COUNTIFS('Offline Scenarios'!D2:D1005,"Reference Learning Mobile App",'Offline Scenarios'!F2:F1005,"P1",'Offline Scenarios'!Q2:Q1005,"Pass") -> 6 | J50: =COUNTIFS('Offline Scenarios'!D2:D1005,"Reference Learning Mobile App",'Offline Scenarios'!F2:F1005,"P2",'Offline Scenarios'!Q2:Q1005,"Pass") -> 8 | K50: =COUNTIFS('Offline Scenarios'!D2:D1005,"Reference Learning Mobile App",'Offline Scenarios'!F2:F1005,"P1",'Offline Scenarios'!Q2:Q1005,"Fail") -> 0 | L50: =COUNTIFS('Offline Scenarios'!D2:D1005,"Reference Learning Mobile App",'Offline Scenarios'!F2:F1005,"P2",'Offline Scenarios'!Q2:Q1005,"Fail") -> 0 | M50: =COUNTIFS('Offline Scenarios'!D2:D1005,"Reference Learning Mobile App",'Offline Scenarios'!F2:F1005,"P1",'Offline Scenarios'!Q2:Q1005,"Blocked") -> 0 | N50: =COUNTIFS('Offline Scenarios'!D2:D1005,"Reference Learning Mobile App",'Offline Scenarios'!F2:F1005,"P2",'Offline Scenarios'!Q2:Q1005,"Blocked") -> 0 | O50: =SUM(K50+M50) -> 0 | P50: =SUM(L50+N50) -> 0 | Q50: =(E50+I50)/C50 -> 1 | R50: =(F50+J50)/D50 -> 1
B51: Offline Desktop | C51: =COUNTIFS('Offline Scenarios'!D2:D1005,"Reference Learning Desktop App",'Offline Scenarios'!F2:F1005,"P1") -> 30 | D51: =COUNTIFS('Offline Scenarios'!D2:D1005,"Reference Learning Desktop App",'Offline Scenarios'!F2:F1005,"P2") -> 21 | E51: =COUNTIFS('Offline Scenarios'!D2:D1005,"Reference Learning Desktop App",'Offline Scenarios'!F2:F1005,"P1",'Offline Scenarios'!Q2:Q1005,"NA") -> 2 | F51: =COUNTIFS('Offline Scenarios'!D2:D1005,"Reference Learning Desktop App",'Offline Scenarios'!F2:F1005,"P2",'Offline Scenarios'!Q2:Q1005,"NA") -> 1 | G51: =C51-(I51+K51+M51+E51) -> 0 | H51: =D51-(J51+L51+N51+F51) -> 0 | I51: =COUNTIFS('Offline Scenarios'!D2:D1005,"Reference Learning Desktop App",'Offline Scenarios'!F2:F1005,"P1",'Offline Scenarios'!Q2:Q1005,"Pass") -> 28 | J51: =COUNTIFS('Offline Scenarios'!D2:D1005,"Reference Learning Desktop App",'Offline Scenarios'!F2:F1005,"P2",'Offline Scenarios'!Q2:Q1005,"Pass") -> 20 | K51: =COUNTIFS('Offline Scenarios'!D2:D1005,"Reference Learning Desktop App",'Offline Scenarios'!F2:F1005,"P1",'Offline Scenarios'!Q2:Q1005,"Fail") -> 0 | L51: =COUNTIFS('Offline Scenarios'!D2:D1005,"Reference Learning Desktop App",'Offline Scenarios'!F2:F1005,"P2",'Offline Scenarios'!Q2:Q1005,"Failed") -> 0 | M51: =COUNTIFS('Offline Scenarios'!D2:D1005,"Reference Learning Desktop App",'Offline Scenarios'!F2:F1005,"P1",'Offline Scenarios'!Q2:Q1005,"Blocked") -> 0 | N51: =COUNTIFS('Offline Scenarios'!D2:D1005,"Reference Learning Desktop App",'Offline Scenarios'!F2:F1005,"P2",'Offline Scenarios'!Q2:Q1005,"Blocked") -> 0 | O51: =SUM(K51+M51) -> 0 | P51: =SUM(L51+N51) -> 0 | Q51: =(E51+I51)/C51 -> 1 | R51: =(F51+J51)/D51 -> 1
A52: Portal/Desktop App Specific test cases | B52: Portal | C52: =COUNTIFS('PortalDesktop App Specific test'!D2:D1005,"Reference Learning Web App",'PortalDesktop App Specific test'!F2:F1005,"P1") -> 41 | D52: =COUNTIFS('PortalDesktop App Specific test'!D2:D1005,"Reference Learning Web App",'PortalDesktop App Specific test'!F2:F1005,"P2") -> 33 | E52: =COUNTIFS('PortalDesktop App Specific test'!D2:D1005,"Reference Learning Web App",'PortalDesktop App Specific test'!F2:F1005,"P1",'PortalDesktop App Specific test'!Q2:Q1005,"NA") -> 0 | F52: =COUNTIFS('PortalDesktop App Specific test'!D2:D1005,"Reference Learning Web App",'PortalDesktop App Specific test'!F2:F1005,"P2",'PortalDesktop App Specific test'!Q2:Q1005,"NA") -> 1 | G52: =C52-(I52+K52+M52+E52) -> 0 | H52: =D52-(J52+L52+N52+F52) -> 0 | I52: =COUNTIFS('PortalDesktop App Specific test'!D2:D1005,"Reference Learning Web App",'PortalDesktop App Specific test'!F2:F1005,"P1",'PortalDesktop App Specific test'!Q2:Q1005,"Pass") -> 41 | J52: =COUNTIFS('PortalDesktop App Specific test'!D2:D1005,"Reference Learning Web App",'PortalDesktop App Specific test'!F2:F1005,"P2",'PortalDesktop App Specific test'!Q2:Q1005,"Pass") -> 32 | K52: =COUNTIFS('PortalDesktop App Specific test'!D2:D1005,"Reference Learning Web App",'PortalDesktop App Specific test'!F2:F1005,"P1",'PortalDesktop App Specific test'!Q2:Q1005,"Fail") -> 0 | L52: =COUNTIFS('PortalDesktop App Specific test'!D2:D1005,"Reference Learning Web App",'PortalDesktop App Specific test'!F2:F1005,"P2",'PortalDesktop App Specific test'!Q2:Q1005,"Fail") -> 0 | M52: =COUNTIFS('PortalDesktop App Specific test'!D2:D1005,"Reference Learning Web App",'PortalDesktop App Specific test'!F2:F1005,"P1",'PortalDesktop App Specific test'!Q2:Q1005,"Blocked") -> 0 | N52: =COUNTIFS('PortalDesktop App Specific test'!D2:D1005,"Reference Learning Web App",'PortalDesktop App Specific test'!F2:F1005,"P2",'PortalDesktop App Specific test'!Q2:Q1005,"Blocked") -> 0 | O52: =SUM(K52+M52) -> 0 | P52: =SUM(L52+N52) -> 0 | Q52: =(E52+I52)/C52 -> 1 | R52: =(F52+J52)/D52 -> 1
B53: Offline Desktop | C53: =COUNTIFS('PortalDesktop App Specific test'!D2:D1005,"Reference Learning Desktop App",'PortalDesktop App Specific test'!F2:F1005,"P1") -> 40 | D53: =COUNTIFS('PortalDesktop App Specific test'!D2:D1005,"Reference Learning Desktop App",'PortalDesktop App Specific test'!F2:F1005,"P2") -> 68 | E53: =COUNTIFS('PortalDesktop App Specific test'!D2:D1005,"Reference Learning Desktop App",'PortalDesktop App Specific test'!F2:F1005,"P1",'PortalDesktop App Specific test'!Q2:Q1005,"NA") -> 5 | F53: =COUNTIFS('PortalDesktop App Specific test'!D2:D1005,"Reference Learning Desktop App",'PortalDesktop App Specific test'!F2:F1005,"P2",'PortalDesktop App Specific test'!Q2:Q1005,"NA") -> 2 | G53: =C53-(I53+K53+M53+E53) -> 0 | H53: =D53-(J53+L53+N53+F53) -> 0 | I53: =COUNTIFS('PortalDesktop App Specific test'!D2:D1005,"Reference Learning Desktop App",'PortalDesktop App Specific test'!F2:F1005,"P1",'PortalDesktop App Specific test'!Q2:Q1005,"Pass") -> 35 | J53: =COUNTIFS('PortalDesktop App Specific test'!D2:D1005,"Reference Learning Desktop App",'PortalDesktop App Specific test'!F2:F1005,"P2",'PortalDesktop App Specific test'!Q2:Q1005,"Pass") -> 66 | K53: =COUNTIFS('PortalDesktop App Specific test'!D2:D1005,"Reference Learning Desktop App",'PortalDesktop App Specific test'!F2:F1005,"P1",'PortalDesktop App Specific test'!Q2:Q1005,"Fail") -> 0 | L53: =COUNTIFS('PortalDesktop App Specific test'!D2:D1005,"Reference Learning Desktop App",'PortalDesktop App Specific test'!F2:F1005,"P2",'PortalDesktop App Specific test'!Q2:Q1005,"Fail") -> 0 | M53: =COUNTIFS('PortalDesktop App Specific test'!D2:D1005,"Reference Learning Desktop App",'PortalDesktop App Specific test'!F2:F1005,"P1",'PortalDesktop App Specific test'!Q2:Q1005,"Blocked") -> 0 | N53: =COUNTIFS('PortalDesktop App Specific test'!D2:D1005,"Reference Learning Desktop App",'PortalDesktop App Specific test'!F2:F1005,"P2",'PortalDesktop App Specific test'!Q2:Q1005,"Blocked") -> 0 | O53: =SUM(K53+M53) -> 0 | P53: =SUM(L53+N53) -> 0 | Q53: =(E53+I53)/C53 -> 1 | R53: =(F53+J53)/D53 -> 1
A54: 7.0 NF Test Cases | B54: Portal/Mobile/Offline Desktop | C54: =COUNTIFS('7.0 New Features'!K2:K1005,"P1") -> 312 | D54: =COUNTIFS('7.0 New Features'!K2:K1005,"P2") -> 299 | E54: =COUNTIFS('7.0 New Features'!K2:K1005,"P1", '7.0 New Features'!U2:U1005,"NA") -> 61 | F54: =COUNTIFS('7.0 New Features'!K2:K1005,"P2", '7.0 New Features'!U2:U1005,"NA") -> 34 | G54: =C54-(I54+K54+M54+E54) -> 0 | H54: =D54-(J54+L54+N54+F54) -> 0 | I54: =COUNTIFS('7.0 New Features'!K2:K1005,"P1", '7.0 New Features'!U2:U1005,"Pass") -> 251 | J54: =COUNTIFS('7.0 New Features'!K2:K1005,"P2", '7.0 New Features'!U2:U1005,"Pass") -> 265 | K54: =COUNTIFS('NF Test Cases'!K2:K1005,"P1", 'NF Test Cases'!U2:U1005,"Fail") -> 0 | L54: =COUNTIFS('NF Test Cases'!K2:K1005,"P2", 'NF Test Cases'!U2:U1005,"Fail") -> 0 | M54: =COUNTIFS('NF Test Cases'!K2:K1005,"P1", 'NF Test Cases'!U2:U1005,"Blocked") -> 0 | N54: =COUNTIFS('NF Test Cases'!K2:K1005,"P2", 'NF Test Cases'!U2:U1005,"Blocked") -> 0 | O54: =SUM(K54+M54) -> 0 | P54: =SUM(L54+N54) -> 0 | Q54: =(E54+I54)/C54 -> 1 | R54: =(F54+J54)/D54 -> 1
A55: Total | C55: =Sum(C4:C54) -> 3195 | D55: =Sum(D4:D54) -> 2423 | E55: =Sum(E4:E54) -> 222 | F55: =Sum(F4:F54) -> 152 | G55: =Sum(G4:G54) -> 0 | H55: =Sum(H4:H54) -> 0 | I55: =Sum(I4:I54) -> 2973 | J55: =Sum(J4:J54) -> 2271 | ... N55: =Sum(N4:N54) -> 0 | O55: =SUM(O4:O54) -> 0 | P55: =SUM(P4:P54) -> 0 | Q55: =(E55+I55)/C55 -> 1 | R55: =(F55+J55)/D55 -> 1
A61: Manage Learn Regression Dashboard
A62: ED Component | B62: Portal/Mobile app | C62: Total | E62: Not Applicable | G62: To be Executed | I62: Passed | K62: Fail | M62: Blocked | O62: For retest (Failed & Blocked) | Q62: Execution % circle wise
C63: P1 | D63: P2 | E63: P1 | F63: P2 | G63: P1 | H63: P2 | I63: P1 | J63: P2 | K63: P1 | L63: P2 | M63: P1 | N63: P2 | O63: P1 | P63: P2 | Q63: P1 | R63: P2
A64: Manage Learn | B64: Portal | C64: =COUNTIFS('Manage Learn-Portal'!F2:F1005,"Web portal",'Manage Learn-Portal'!E2:E1005,"P1") -> 642 | D64: =COUNTIFS('Manage Learn-Portal'!F2:F1005,"Web portal",'Manage Learn-Portal'!E2:E1005,"P2") -> 71 | E64: =COUNTIFS('Manage Learn-Portal'!F2:F1005,"Web portal",'Manage Learn-Portal'!E2:E1005,"P1",'Manage Learn-Portal'!P2:P1005,"NA") -> 2 | F64: =COUNTIFS('Manage Learn-Portal'!F2:F1005,"Web portal",'Manage Learn-Portal'!E2:E1005,"P2",'Manage Learn-Portal'!P2:P1005,"NA") -> 0 | G64: =C64-(E64+I64+O64) -> 0 | H64: =D64-(F64+J64+P64) -> 0 | I64: =COUNTIFS('Manage Learn-Portal'!F2:F1005,"Web portal",'Manage Learn-Portal'!E2:E1005,"P1",'Manage Learn-Portal'!P2:P1005,"Pass") -> 640 | J64: =COUNTIFS('Manage Learn-Portal'!F2:F1005,"Web portal",'Manage Learn-Portal'!E2:E1005,"P2",'Manage Learn-Portal'!P2:P1005,"Pass") -> 71 | K64: =COUNTIFS('Manage Learn-Portal'!F2:F1005,"Web portal",'Manage Learn-Portal'!E2:E1005,"P1",'Manage Learn-Portal'!P2:P1005,"Fail") -> 0 | L64: =COUNTIFS('Manage Learn-Portal'!F2:F1005,"Web portal",'Manage Learn-Portal'!E2:E1005,"P2",'Manage Learn-Portal'!P2:P1005,"Fail") -> 0 | M64: =COUNTIFS('Manage Learn-Portal'!F2:F1005,"Web portal",'Manage Learn-Portal'!E2:E1005,"P1",'Manage Learn-Portal'!P2:P1005,"Blocked") -> 0 | N64: =COUNTIFS('Manage Learn-Portal'!F2:F1005,"Web portal",'Manage Learn-Portal'!E2:E1005,"P2",'Manage Learn-Portal'!P2:P1005,"Blocked") -> 0 | O64: =SUM(K64:M64) -> 0 | P64: =SUM(L64:N64) -> 0 | Q64: =(E64+I64)/C64 -> 1 | R64: =(F64+J64)/D64 -> 1
A65: Manage Learn | B65: Mobile | C65: =COUNTIFS('Manage Learn-Mobile'!F2:F1005,"Mobile",'Manage Learn-Mobile'!E2:E1005,"P1") -> 786 | D65: =COUNTIFS('Manage Learn-Mobile'!F2:F1005,"Mobile",'Manage Learn-Mobile'!E2:E1005,"P2") -> 163 | E65: =COUNTIFS('Manage Learn-Mobile'!F2:F1005,"Mobile",'Manage Learn-Mobile'!E2:E1005,"P1",'Manage Learn-Mobile'!P2:P1005,"NA") -> 14 | F65: =COUNTIFS('Manage Learn-Mobile'!F2:F1005,"Mobile",'Manage Learn-Mobile'!E2:E1005,"P2",'Manage Learn-Mobile'!P2:P1005,"NA") -> 5 | G65: =C65-(E65+I65+O65) -> 0 | H65: =D65-(F65+J65+P65) -> 0 | I65: =COUNTIFS('Manage Learn-Mobile'!F2:F1005,"Mobile",'Manage Learn-Mobile'!E2:E1005,"P1",'Manage Learn-Mobile'!P2:P1005,"Pass") -> 772 | J65: =COUNTIFS('Manage Learn-Mobile'!F2:F1005,"Mobile",'Manage Learn-Mobile'!E2:E1005,"P2",'Manage Learn-Mobile'!P2:P1005,"Pass") -> 158 | K65: =COUNTIFS('Manage Learn-Mobile'!F2:F1005,"Mobile",'Manage Learn-Mobile'!E2:E1005,"P1",'Manage Learn-Mobile'!P2:P1005,"Fail") -> 0 | L65: =COUNTIFS('Manage Learn-Mobile'!F2:F1005,"Mobile",'Manage Learn-Mobile'!E2:E1005,"P2",'Manage Learn-Mobile'!P2:P1005,"Fail") -> 0 | M65: =COUNTIFS('Manage Learn-Mobile'!F2:F1005,"Mobile",'Manage Learn-Mobile'!E2:E1005,"P1",'Manage Learn-Mobile'!P2:P1005,"Blocked") -> 0 | N65: =COUNTIFS('Manage Learn-Mobile'!F2:F1005,"Mobile",'Manage Learn-Mobile'!E2:E1005,"P2",'Manage Learn-Mobile'!P2:P1005,"Blocked") -> 0 | O65: =SUM(K65:M65) -> 0 | P65: =SUM(L65:N65) -> 0 | Q65: =(E65+I65)/C65 -> 1 | R65: =(F65+J65)/D65 -> 1
A66: Manage Learn | B66: Mobile & Portal | C66: =COUNTIFS('Manage Learn-Mobile'!F2:F1005,"Mobile & Portal",'Manage Learn-Mobile'!E2:E1005,"P1") -> 113 | D66: =COUNTIFS('Manage Learn-Mobile'!F2:F1005,"Mobile & Portal",'Manage Learn-Mobile'!E2:E1005,"P2") -> 17 | E66: =COUNTIFS('Manage Learn-Mobile'!F2:F1005,"Mobile & Portal",'Manage Learn-Mobile'!E2:E1005,"P1",'Manage Learn-Mobile'!P2:P1005,"NA") -> 2 | F66: =COUNTIFS('Manage Learn-Mobile'!F2:F1005,"Mobile & Portal",'Manage Learn-Mobile'!E2:E1005,"P2",'Manage Learn-Mobile'!P2:P1005,"NA") -> 0 | G66: =C66-(E66+I66+O66) -> 0 | H66: =D66-(F66+J66+P66) -> 0 | I66: =COUNTIFS('Manage Learn-Mobile'!F2:F1005,"Mobile & Portal",'Manage Learn-Mobile'!E2:E1005,"P1",'Manage Learn-Mobile'!P2:P1005,"Pass") -> 111 | J66: =COUNTIFS('Manage Learn-Mobile'!F2:F1005,"Mobile & Portal",'Manage Learn-Mobile'!E2:E1005,"P2",'Manage Learn-Mobile'!P2:P1005,"Pass") -> 17 | K66: =COUNTIFS('Manage Learn-Mobile'!F2:F1005,"Mobile & Portal",'Manage Learn-Mobile'!E2:E1005,"P1",'Manage Learn-Mobile'!P2:P1005,"Fail") -> 0 | L66: =COUNTIFS('Manage Learn-Mobile'!F2:F1005,"Mobile & Portal",'Manage Learn-Mobile'!E2:E1005,"P2",'Manage Learn-Mobile'!P2:P1005,"Fail") -> 0 | M66: =COUNTIFS('Manage Learn-Mobile'!F2:F1005,"Mobile & Portal",'Manage Learn-Mobile'!E2:E1005,"P1",'Manage Learn-Mobile'!P2:P1005,"Blocked") -> 0 | N66: =COUNTIFS('Manage Learn-Mobile'!F2:F1005,"Mobile & Portal",'Manage Learn-Mobile'!E2:E1005,"P2",'Manage Learn-Mobile'!P2:P1005,"Blocked") -> 0 | O66: =SUM(K66:M66) -> 0 | P66: =SUM(L66:N66) -> 0 | Q66: =(E66+I66)/C66 -> 1 | R66: =(F66+J66)/D66 -> 1
A67: Total | C67: =SUM(C64:C66) -> 1541 | D67: =SUM(D64:D66) -> 251 | E67: =SUM(E64:E66) -> 18 | F67: =SUM(F64:F66) -> 5 | G67: =SUM(G64:G66) -> 0 | H67: =SUM(H64:H66) -> 0 | I67: =SUM(I64:I66) -> 1523 | J67: =SUM(J64:J66) -> 246 | ... P67: =SUM(P64:P66) -> 0 | Q67: =(E67+I67)/C67 -> 1 | R67: =(F67+J67)/D67 -> 1
F71: With ML | I71: Without ML | L71: only ML
A72: Solution | B72: Executed | C72: Pending | D72: Total | F72: % Pending Overall | G72: % Executed Overall | I72: % Pending Overall | J72: % Executed Overall | L72: % Pending Overall | M72: % Executed Overall
A73: Sunbird ED | B73: =(Sum(E4:E54)+Sum(F4:F54))+Sum(I4:I54)+Sum(J4:J54) -> 5618 | C73: =(Sum(G4:G54)+Sum(H4:H54))+Sum(O4:O54)+Sum(P4:P54) -> 0 | D73: =SUM(B73:C73) -> 5618 | F73: =C75/D75*100 -> 0 | G73: =B75/D75*100 -> 100 | I73: =C73/D73*100 -> 0 | J73: =B73/D73*100 -> 100 | L73: =C74/D74*100 -> 0 | M73: =B74/D74*100 -> 100
A74: Manage Learn | B74: =sum(E64:E66)+SUM(F64:F66)+SUM(I64:I66)+SUM(J64:J66) -> 1792 | C74: =sum(G64:G66)+SUM(H64:H66)+SUM(O64:O66)+SUM(P64:P66) -> 0 | D74: =SUM(B74:C74) -> 1792
A75: Total | B75: =SUM(B73:B74) -> 7410 | C75: =SUM(C73:C74) -> 0 | D75: =SUM(D73:D74) -> 7410
A79: Component | C79: Known Bug | D79: Deprecated | E79: Backend Configurations
A80: WorkSpace | B80: Portal | C80: =COUNTIF(Workspace!V2:V1005,"Known Bug") -> 21 | D80: =COUNTIF(Workspace!V2:V1005,"Deprecated") -> 14 | E80: =COUNTIF(Workspace!V2:V1005,"Backend Configurations") -> 0
A81: Login | B81: Portal | C81: =COUNTIFS(Login!D2:D1005,"Reference Learning Web App",Login!T2:T1005,"Known Bug") -> 1 | D81: =COUNTIFS(Login!D2:D1005,"Reference Learning Web App",Login!T2:T1005,"Deprecated") -> 5 | E81: -
B82: Mobile | C82: =COUNTIFS(Login!D2:D1005,"Reference Learning Mobile App",Login!T2:T1005,"Known Bug") -> 5 | D82: =COUNTIFS(Login!D2:D1005,"Reference Learning Mobile App",Login!T2:T1005,"Deprecated") -> 0 | E82: -
B83: Offline Desktop | C83: =COUNTIFS(Login!D2:D1005,"Reference Learning Desktop App",Login!T2:T1005,"Known Bug") -> 0 | D83: =COUNTIFS(Login!D2:D1005,"Reference Learning Desktop App",Login!T2:T1005,"Deprecated") -> 0 | E83: -
A84: Course Consumption | B84: Portal | C84: =COUNTIFS('Course Consumption'!D2:D1005,"Reference Learning Web App",'Course Consumption'!T2:T1005,"Known Bug") -> 4 | D84: =COUNTIFS('Course Consumption'!D2:D1005,"Reference Learning Web App",'Course Consumption'!T2:T1005,"Deprecated") -> 5 | E84: -
B85: Mobile | C85: =COUNTIFS('Course Consumption'!D2:D1005,"Reference Learning Mobile App",'Course Consumption'!T2:T1005,"Known Bug") -> 1 | D85: =COUNTIFS('Course Consumption'!D2:D1005,"Reference Learning Mobile App",'Course Consumption'!T2:T1005,"Deprecated") -> 1 | E85: -
B86: Offline Desktop | C86: =COUNTIFS('Course Consumption'!D2:D1005,"Reference Learning Desktop App",'Course Consumption'!T2:T1005,"Known Bug") -> 1 | D86: =COUNTIFS('Course Consumption'!D2:D1005,"Reference Learning Desktop App",'Course Consumption'!T2:T1005,"Deprecated") -> 3 | E86: -
A87: Batch Creation | B87: Portal | C87: =COUNTIFS('Batch Creation'!D2:D1005,"Reference Learning Web App",'Batch Creation'!S2:S1005,"Known Bug") -> 0 | D87: =COUNTIFS('Batch Creation'!D2:D1005,"Reference Learning Web App",'Batch Creation'!S2:S1005,"Deprecated") -> 0 | E87: -
A88: Digital Textbook Consumption | B88: Portal | C88: =COUNTIFS('Digital Textbook Consumption'!D2:D1005,"Reference Learning Web App",'Digital Textbook Consumption'!S2:S1005,"Known Bug") -> 0 | D88: =COUNTIFS('Digital Textbook Consumption'!D2:D1005,"Reference Learning Web App",'Digital Textbook Consumption'!S2:S1005,"Deprecated") -> 0 | E88: -
B89: Mobile | C89: =COUNTIFS('Digital Textbook Consumption'!D2:D1005,"Reference Learning Mobile App",'Digital Textbook Consumption'!S2:S1005,"Known Bug") -> 5 | D89: =COUNTIFS('Digital Textbook Consumption'!D2:D1005,"Reference Learning Mobile App",'Digital Textbook Consumption'!S2:S1005,"Deprecated") -> 0 | E89: -
B90: Offline Desktop | C90: =COUNTIFS('Digital Textbook Consumption'!D2:D1005,"Reference Learning Desktop App",'Digital Textbook Consumption'!S2:S1005,"Known Bug") -> 2 | D90: =COUNTIFS('Digital Textbook Consumption'!D2:D1005,"Reference Learning Desktop App",'Digital Textbook Consumption'!S2:S1005,"Deprecated") -> 2 | E90: -
A91: Content Consumption | B91: Portal | C91: =COUNTIFS('Content Consumption'!D2:D1005,"Reference Learning Web App",'Content Consumption'!T2:T1005,"Known Bug") -> 1 | D91: =COUNTIFS('Content Consumption'!D2:D1005,"Reference Learning Web App",'Content Consumption'!T2:T1005,"Deprecated") -> 0 | E91: -
B92: Mobile | C92: =COUNTIFS('Content Consumption'!D2:D1005,"Reference Learning Mobile App",'Content Consumption'!T2:T1005,"Known Bug") -> 1 | D92: =COUNTIFS('Content Consumption'!D2:D1005,"Reference Learning Mobile App",'Content Consumption'!T2:T1005,"Deprecated") -> 0 | E92: -
B93: Offline Desktop | C93: =COUNTIFS('Content Consumption'!D2:D1005,"Reference Learning Desktop App",'Content Consumption'!T2:T1005,"Known Bug") -> 0 | D93: =COUNTIFS('Content Consumption'!D2:D1005,"Reference Learning Desktop App",'Content Consumption'!T2:T1005,"Deprecated") -> 0 | E93: -
A94: Profile | B94: Portal | C94: =COUNTIFS(Profile!D2:D1005,"Reference Learning Web App",Profile!T2:T1005,"Known Bug") -> 0 | D94: =COUNTIFS(Profile!D2:D1005,"Reference Learning Web App",Profile!T2:T1005,"Deprecated") -> 1 | E94: -
B95: Mobile | C95: =COUNTIFS(Profile!D2:D1005,"Reference Learning Mobile App",Profile!T2:T1005,"Known Bug") -> 0 | D95: =COUNTIFS(Profile!D2:D1005,"Reference Learning Mobile App",Profile!T2:T1005,"Deprecated") -> 0 | E95: -
B96: Offline Desktop | C96: =COUNTIFS(Profile!D2:D1005,"Reference Learning Desktop App",Profile!T2:T1005,"Known Bug") -> 3 | D96: =COUNTIFS(Profile!D2:D1005,"Reference Learning Desktop App",Profile!T2:T1005,"Deprecated") -> 0 | E96: -
A97: Course reports | B97: Portal | C97: =COUNTIFS('Course reports'!D2:D1005,"Reference Learning Web App",'Course reports'!S2:S1005,"Known Bug") -> 0 | D97: =COUNTIFS('Course reports'!D2:D1005,"Reference Learning Web App",'Course reports'!S2:S1005,"Deprecated") -> 0 | E97: -
B98: Mobile | C98: =COUNTIFS('Course reports'!D2:D1005,"Reference Learning Mobile App",'Course reports'!S2:S1005,"Known Bug") -> 0 | D98: =COUNTIFS('Course reports'!D2:D1005,"Reference Learning Mobile App",'Course reports'!S2:S1005,"Deprecated") -> 0 | E98: -
A99: QUML | B99: Portal | C99: =COUNTIFS(QUML!D2:D1005,"Reference Learning Web App",QUML!T2:T1005,"Known Bug") -> 3 | D99: =COUNTIFS(QUML!D2:D1005,"Reference Learning Web App",QUML!T2:T1005,"Deprecated") -> 1 | E99: -
B100: Mobile | C100: =COUNTIFS(QUML!D2:D1005,"Reference Learning Mobile App",QUML!T2:T1005,"Known Bug") -> 1 | D100: =COUNTIFS(QUML!D2:D1005,"Reference Learning Mobile App",QUML!T2:T1005,"Deprecated") -> 0 | E100: -
B101: Offline Desktop | C101: =COUNTIFS(QUML!D2:D1005,"Reference Learning Desktop App",QUML!T2:T1005,"Known Bug") -> 0 | D101: =COUNTIFS(QUML!D2:D1005,"Reference Learning Desktop App",QUML!T2:T1005,"Deprecated") -> 0 | E101: -
A102: Mobile specific Test Cases | B102: Mobile | C102: =COUNTIFS('Mobile specific Test Cases'!D2:D1005,"Reference Learning Mobile App",'Mobile specific Test Cases'!S2:S1005,"Known Bug") -> 0 | D102: =COUNTIFS('Mobile specific Test Cases'!D2:D1005,"Reference Learning Mobile App",'Mobile specific Test Cases'!S2:S1005,"Deprecated") -> 1 | E102: -
A103: Mobile configurability | B103: Mobile | C103: =COUNTIFS('Mobile configurability'!D2:D1005,"Reference Learning Mobile App",'Mobile configurability'!S2:S1005,"Known Bug") -> 0 | D103: =COUNTIFS('Mobile configurability'!D2:D1005,"Reference Learning Mobile App",'Mobile configurability'!S2:S1005,"Deprecated") -> 1 | E103: -
A104: Org admin reports | B104: Portal | C104: =COUNTIFS('Org admin reports'!D2:D1005,"Reference Learning Web App",'Org admin reports'!S2:S1005,"Known Bug") -> 0 | D104: =COUNTIFS('Org admin reports'!D2:D1005,"Reference Learning Web App",'Org admin reports'!S2:S1005,"Deprecated") -> 5 | E104: -
B105: Mobile | C105: =COUNTIFS('Org admin reports'!D2:D1005,"Reference Learning Mobile App",'Org admin reports'!S2:S1005,"Known Bug") -> 0 | D105: =COUNTIFS('Org admin reports'!D2:D1005,"Reference Learning Mobile App",'Org admin reports'!S2:S1005,"Deprecated") -> 0 | E105: -
A106: QR code | B106: Portal | C106: =COUNTIFS('QR code'!D2:D1005,"Reference Learning Web App",'QR code'!T2:T1005,"Known Bug") -> 1 | D106: =COUNTIFS('QR code'!D2:D1005,"Reference Learning Web App",'QR code'!T2:T1005,"Deprecated") -> 2 | E106: =COUNTIFS('QR code'!C2:C1005,"Reference Learning Web App",'QR code'!T2:T1005,"Backend Configuration") -> 0
B107: Mobile | C107: =COUNTIFS('QR code'!D2:D1005,"Reference Learning Mobile App",'QR code'!T2:T1005,"Known Bug") -> 0 | D107: =COUNTIFS('QR code'!D2:D1005,"Reference Learning Mobile App",'QR code'!T2:T1005,"Deprecated") -> 9 | E107: =COUNTIFS('QR code'!C2:C1005,"Reference Learning Mobile App",'QR code'!T2:T1005,"Backend Configuration") -> 0
A108: Portal/ Desktop App Configurability | B108: Portal | C108: =COUNTIFS('Portal Desktop App Configurabil'!D2:D1005,"Reference Learning Web App",'Portal Desktop App Configurabil'!S2:S1005,"Known Bug") -> 1 | D108: =COUNTIFS('Portal Desktop App Configurabil'!D2:D1005,"Reference Learning Web App",'Portal Desktop App Configurabil'!S2:S1005,"Deprecated") -> 0 | E108: -
B109: Offline Desktop | C109: =COUNTIFS('Portal Desktop App Configurabil'!D2:D1005,"Reference Learning Desktop App",'Portal Desktop App Configurabil'!S2:S1005,"Known Bug") -> 0 | D109: =COUNTIFS('Portal Desktop App Configurabil'!D2:D1005,"Reference Learning Desktop App",'Portal Desktop App Configurabil'!S2:S1005,"Deprecated") -> 0 | E109: -
A110: Sunbird UCI | B110: Portal | C110: =COUNTIFS('Sunbird UCI'!D2:D1005,"Portal tara",'Sunbird UCI'!T2:T1005,"Known Bug") -> 1 | D110: =COUNTIFS('Sunbird UCI'!D2:D1005,"Portal tara",'Sunbird UCI'!T2:T1005,"Deprecated") -> 0 | E110: -
B111: Mobile | C111: =COUNTIFS('Sunbird UCI'!D2:D1005,"Mobile tara",'Sunbird UCI'!T2:T1005,"Known Bug") -> 0 | D111: =COUNTIFS('Sunbird UCI'!D2:D1005,"Mobile tara",'Sunbird UCI'!T2:T1005,"Deprecated") -> 0 | E111: -
...

Sheet Sunbird ED Execution Dashboard
A1: Sunbird ED Regression Dashboard
A2: ED Component | B2: Portal/Mobile/Desktop app | C2: Total | E2: Not Applicable | G2: To be Executed | I2: Passed | K2: Fail | M2: Blocked | O2: For retest (Failed & Blocked) | Q2: Execution % circle wise
C3: P1 | D3: P2 | E3: P1 | F3: P2 | G3: P1 | H3: P2 | I3: P1 | J3: P2 | K3: P1 | L3: P2 | M3: P1 | N3: P2 | O3: P1 | P3: P2 | Q3: P1 | R3: P2
A4: Sanity | B4: Portal | C4: =COUNTA('Portal Sanity'!D2:D1005) -> 110 | D4: 0 | E4: =COUNTIF('Portal Sanity'!K2:K1005,"NA") -> 2 | F4: 0 | G4: =C4-(I4+O4+E4) -> 0 | H4: 0 | I4: =COUNTIF('Portal Sanity'!K2:K1005,"Pass") -> 108 | J4: 0 | K4: =COUNTIF('Portal Sanity'!K2:K1005,"Fail") -> 0 | L4: 0 | M4: =COUNTIF('Portal Sanity'!K2:K1005,"Blocked") -> 0 | N4: 0 | O4: =SUM(K4+M4) -> 0 | P4: 0 | Q4: =(E4+I4)/C4 -> 1 | R4: 0
B5: Mobile | C5: =COUNTA('Mobile Sanity'!D2:D1005) -> 111 | D5: 0 | E5: =COUNTIF('Mobile Sanity'!K2:K1005,"NA") -> 4 | F5: 0 | G5: =C5-(I5+O5+E5) -> 0 | H5: 0 | I5: =COUNTIF('Mobile Sanity'!K2:K1005,"Pass") -> 107 | J5: 0 | K5: =COUNTIF('Mobile Sanity'!K2:K1005,"Fail") -> 0 | L5: 0 | M5: =COUNTIF('Mobile Sanity'!K2:K1005,"Blocked") -> 0 | N5: 0 | O5: =SUM(K5+M5) -> 0 | P5: 0 | Q5: =(E5+I5)/C5 -> 1 | R5: 0
B6: Desktop | C6: =COUNTA('Desktop Sanity'!D2:D1005) -> 53 | D6: 0 | E6: =COUNTIF('Desktop Sanity'!K2:K1005,"NA") -> 6 | F6: 0 | G6: =C6-(I6+O6+E6) -> 0 | H6: 0 | I6: =COUNTIF('Desktop Sanity'!K2:K1005,"Pass") -> 47 | J6: 0 | K6: =COUNTIF('Desktop Sanity'!K2:K1005,"Fail") -> 0 | L6: 0 | M6: =COUNTIF('Desktop Sanity'!K2:K1005,"Blocked") -> 0 | N6: 0 | O6: =SUM(K6+M6) -> 0 | P6: 0 | Q6: =(E6+I6)/C6 -> 1 | R6: 0
A7: Sanity New Framework | B7: Portal | C7: =COUNTA('Portal Sanity'!D2:D1005) -> 110 | D7: 0 | E7: =COUNTIF('Portal Sanity'!O2:O1005,"NA") -> 1 | F7: 0 | G7: =C7-(I7+O7+E7) -> 0 | H7: 0 | I7: =COUNTIF('Portal Sanity'!O2:O1005,"Pass") -> 109 | J7: 0 | K7: =COUNTIF('Portal Sanity'!O2:O1005,"Fail") -> 0 | L7: 0 | M7: =COUNTIF('Portal Sanity'!O2:O1005,"Blocked") -> 0 | N7: 0 | O7: =SUM(K7+M7) -> 0 | P7: 0 | Q7: =(E7+I7)/C7 -> 1 | R7: 0
B8: Mobile | C8: =COUNTA('Mobile Sanity'!D2:D1005) -> 111 | D8: 0 | E8: =COUNTIF('Mobile Sanity'!O2:O1005,"NA") -> 5 | F8: 0 | G8: =C8-(I8+O8+E8) -> 0 | H8: 0 | I8: =COUNTIF('Mobile Sanity'!O2:O1005,"Pass") -> 106 | J8: 0 | K8: =COUNTIF('Mobile Sanity'!O2:O1005,"Fail") -> 0 | L8: 0 | M8: =COUNTIF('Mobile Sanity'!O2:O1005,"Blocked") -> 0 | N8: 0 | O8: =SUM(K8+M8) -> 0 | P8: 0 | Q8: =(E8+I8)/C8 -> 1 | R8: 0
B9: Desktop | C9: =COUNTA('Desktop Sanity'!D2:D1005) -> 53 | D9: 0 | E9: =COUNTIF('Desktop Sanity'!O2:O1005,"NA") -> 6 | F9: 0 | G9: =C9-(I9+O9+E9) -> 0 | H9: 0 | I9: =COUNTIF('Desktop Sanity'!O2:O1005,"Pass") -> 47 | J9: 0 | K9: =COUNTIF('Desktop Sanity'!O2:O1005,"Fail") -> 0 | L9: 0 | M9: =COUNTIF('Desktop Sanity'!O2:O1005,"Blocked") -> 0 | N9: 0 | O9: =SUM(K9+M9) -> 0 | P9: 0 | Q9: =(E9+I9)/C9 -> 1 | R9: 0
A10: 7.0.0 New Feature S1 Defects | B10: Portal/Mobile/Offline Desktop | C10: =COUNTA('7.0.0 New Feature S1 Defects'!B2:B1005) -> 45 | D10: 0 | E10: =COUNTIF('7.0.0 New Feature S1 Defects'!E2:E1005,"NA") -> 1 | F10: 0 | G10: =C10-(I10+O10+E10) -> 0 | H10: 0 | I10: =COUNTIF('7.0.0 New Feature S1 Defects'!E2:E1005,"Pass") -> 44 | J10: 0 | K10: =COUNTIF('7.0.0 New Feature S1 Defects'!E2:E1005,"Fail") -> 0 | L10: 0 | M10: =COUNTIF('7.0.0 New Feature S1 Defects'!E2:E1005,"Blocked") -> 0 | N10: 0 | O10: =SUM(K10+M10) -> 0 | P10: 0 | Q10: =(E10+I10)/C10 -> 1 | R10: 0
A11: 6.0.0 OCI S1 Defects | B11: Portal/Mobile/Offline Desktop | C11: =COUNTA('6.0.0 OCI S1 Defects'!B2:B1005) -> 46 | D11: 0 | E11: =COUNTIF('6.0.0 OCI S1 Defects'!E2:E1005,"NA") -> 1 | F11: 0 | G11: =C11-(I11+O11+E11) -> 0 | H11: 0 | I11: =COUNTIF('6.0.0 OCI S1 Defects'!E2:E1005,"Pass") -> 45 | J11: 0 | K11: =COUNTIF('6.0.0 OCI S1 Defects'!E2:E1005,"Fail") -> 0 | L11: 0 | M11: =COUNTIF('6.0.0 OCI S1 Defects'!E2:E1005,"Blocked") -> 0 | N11: 0 | O11: =SUM(K11+M11) -> 0 | P11: 0 | Q11: =(E11+I11)/C11 -> 1 | R11: 0
A12: WorkSpace | B12: Portal | C12: =COUNTIF(Workspace!F2:F1005,"P1") -> 264 | D12: =COUNTIF(Workspace!F2:F1005,"P2") -> 327 | E12: =COUNTIFS(Workspace!F2:F1005,"P1",Workspace!T2:T1005,"NA") -> 14 | F12: =COUNTIFS(Workspace!F2:F1005,"P2",Workspace!T2:T1005,"NA") -> 26 | G12: =C12-(I12+K12+M12+E12) -> 0 | H12: =D12-(J12+L12+N12+F12) -> 0 | I12: =COUNTIFS(Workspace!F2:F1005,"P1",Workspace!T2:T1005,"Pass") -> 250 | J12: =COUNTIFS(Workspace!F2:F1005,"P2",Workspace!T2:T1005,"Pass") -> 301 | K12: =COUNTIFS(Workspace!F2:F1005,"P1",Workspace!T2:T1005,"Fail") -> 0 | L12: =COUNTIFS(Workspace!F2:F1005,"P2",Workspace!T2:T1005,"Fail") -> 0 | M12: =COUNTIFS(Workspace!F2:F1005,"P1",Workspace!T2:T1005,"Blocked") -> 0 | N12: =COUNTIFS(Workspace!F2:F1005,"P2",Workspace!T2:T1005,"Blocked") -> 0 | O12: =SUM(K12+M12) -> 0 | P12: =SUM(L12+N12) -> 0 | Q12: =(E12+I12)/C12 -> 1 | R12: =(F12+J12)/D12 -> 1
A13: Login | B13: Portal | C13: =COUNTIFS(Login!D2:D1005,"Reference Learning Web App",Login!F2:F1005,"P1") -> 61 | D13: =COUNTIFS(Login!D2:D1005,"Reference Learning Web App",Login!F2:F1005,"P2") -> 73 | E13: =COUNTIFS(Login!D2:D1005,"Reference Learning Web App",Login!F2:F1005,"P1",Login!R2:R1005,"NA") -> 2 | F13: =COUNTIFS(Login!D2:D1005,"Reference Learning Web App",Login!F2:F1005,"P2",Login!R2:R1005,"NA") -> 5 | G13: =C13-(I13+K13+M13+E13) -> 0 | H13: =D13-(J13+L13+N13+F13) -> 0 | I13: =COUNTIFS(Login!D2:D1005,"Reference Learning Web App",Login!F2:F1005,"P1",Login!R2:R1005,"Pass") -> 59 | J13: =COUNTIFS(Login!D2:D1005,"Reference Learning Web App",Login!F2:F1005,"P2",Login!R2:R1005,"Pass") -> 68 | K13: =COUNTIFS(Login!D2:D1005,"Reference Learning Web App",Login!F2:F1005,"P1",Login!R2:R1005,"Fail") -> 0 | L13: =COUNTIFS(Login!D2:D1005,"Reference Learning Web App",Login!F2:F1005,"P2",Login!R2:R1005,"Fail") -> 0 | M13: =COUNTIFS(Login!D2:D1005,"Reference Learning Web App",Login!F2:F1005,"P1",Login!R2:R1005,"Blocked") -> 0 | N13: =COUNTIFS(Login!D2:D1005,"Reference Learning Web App",Login!F2:F1005,"P2",Login!R2:R1005,"Blocked") -> 0 | O13: =SUM(K13+M13) -> 0 | P13: =SUM(L13+N13) -> 0 | Q13: =(E13+I13)/C13 -> 1 | R13: =(F13+J13)/D13 -> 1
B14: Mobile | C14: =COUNTIFS(Login!D2:D1005,"Reference Learning Mobile App",Login!F2:F1005,"P1") -> 62 | D14: =COUNTIFS(Login!D2:D1005,"Reference Learning Mobile App",Login!F2:F1005,"P2") -> 87 | E14: =COUNTIFS(Login!D2:D1005,"Reference Learning Mobile App",Login!F2:F1005,"P1",Login!R2:R1005,"NA") -> 1 | F14: =COUNTIFS(Login!D2:D1005,"Reference Learning Mobile App",Login!F2:F1005,"P2",Login!R2:R1005,"NA") -> 4 | G14: =C14-(I14+K14+M14+E14) -> 0 | H14: =D14-(J14+L14+N14+F14) -> 0 | I14: =COUNTIFS(Login!D2:D1005,"Reference Learning Mobile App",Login!F2:F1005,"P1",Login!R2:R1005,"Pass") -> 61 | J14: =COUNTIFS(Login!D2:D1005,"Reference Learning Mobile App",Login!F2:F1005,"P2",Login!R2:R1005,"Pass") -> 83 | K14: =COUNTIFS(Login!D2:D1005,"Reference Learning Mobile App",Login!F2:F1005,"P1",Login!R2:R1005,"Fail") -> 0 | L14: =COUNTIFS(Login!D2:D1005,"Reference Learning Mobile App",Login!F2:F1005,"P2",Login!R2:R1005,"Fail") -> 0 | M14: =COUNTIFS(Login!D2:D1005,"Reference Learning Mobile App",Login!F2:F1005,"P1",Login!R2:R1005,"Blocked") -> 0 | N14: =COUNTIFS(Login!D2:D1005,"Reference Learning Mobile App",Login!F2:F1005,"P2",Login!R2:R1005,"Blocked") -> 0 | O14: =SUM(K14+M14) -> 0 | P14: =SUM(L14+N14) -> 0 | Q14: =(E14+I14)/C14 -> 1 | R14: =(F14+J14)/D14 -> 1
B15: Offline Desktop | C15: =COUNTIFS(Login!D2:D1005,"Reference Learning Desktop App",Login!F2:F1005,"P1") -> 22 | D15: =COUNTIFS(Login!D2:D1005,"Reference Learning Desktop App",Login!F2:F1005,"P2") -> 26 | E15: =COUNTIFS(Login!D2:D1005,"Reference Learning Desktop App",Login!F2:F1005,"P1",Login!R2:R1005,"NA") -> 0 | F15: =COUNTIFS(Login!D2:D1005,"Reference Learning Desktop App",Login!F2:F1005,"P2",Login!R2:R1005,"NA") -> 0 | G15: =C15-(I15+K15+M15+E15) -> 0 | H15: =D15-(J15+L15+N15+F15) -> 0 | I15: =COUNTIFS(Login!D2:D1005,"Reference Learning Desktop App",Login!F2:F1005,"P1",Login!R2:R1005,"Pass") -> 22 | J15: =COUNTIFS(Login!D2:D1005,"Reference Learning Desktop App",Login!F2:F1005,"P2",Login!R2:R1005,"Pass") -> 26 | K15: =COUNTIFS(Login!D2:D1005,"Reference Learning Desktop App",Login!F2:F1005,"P1",Login!R2:R1005,"Fail") -> 0 | L15: =COUNTIFS(Login!D2:D1005,"Reference Learning Desktop App",Login!F2:F1005,"P2",Login!R2:R1005,"Fail") -> 0 | M15: =COUNTIFS(Login!D2:D1005,"Reference Learning Desktop App",Login!F2:F1005,"P1",Login!R2:R1005,"Blocked") -> 0 | N15: =COUNTIFS(Login!D2:D1005,"Reference Learning Desktop App",Login!F2:F1005,"P2",Login!R2:R1005,"Blocked") -> 0 | O15: =SUM(K15+M15) -> 0 | P15: =SUM(L15+N15) -> 0 | Q15: =(E15+I15)/C15 -> 1 | R15: =(F15+J15)/D15 -> 1
A16: Course Consumption | B16: Portal | C16: =COUNTIFS('Course Consumption'!D2:D1005,"Reference Learning Web App",'Course Consumption'!F2:F1005,"P1") -> 163 | D16: =COUNTIFS('Course Consumption'!D2:D1005,"Reference Learning Web App",'Course Consumption'!F2:F1005,"P2") -> 59 | E16: =COUNTIFS('Course Consumption'!D2:D1005,"Reference Learning Web App",'Course Consumption'!F2:F1005,"P1",'Course Consumption'!R2:R1005,"NA") -> 8 | F16: =COUNTIFS('Course Consumption'!D2:D1005,"Reference Learning Web App",'Course Consumption'!F2:F1005,"P2",'Course Consumption'!R2:R1005,"NA") -> 1 | G16: =C16-(I16+K16+M16+E16) -> 0 | H16: =D16-(J16+L16+N16+F16) -> 0 | I16: =COUNTIFS('Course Consumption'!D2:D1005,"Reference Learning Web App",'Course Consumption'!F2:F1005,"P1",'Course Consumption'!R2:R1005,"Pass") -> 155 | J16: =COUNTIFS('Course Consumption'!D2:D1005,"Reference Learning Web App",'Course Consumption'!F2:F1005,"P2",'Course Consumption'!R2:R1005,"Pass") -> 58 | K16: =COUNTIFS('Course Consumption'!D2:D1005,"Reference Learning Web App",'Course Consumption'!F2:F1005,"P1",'Course Consumption'!R2:R1005,"Fail") -> 0 | L16: =COUNTIFS('Course Consumption'!D2:D1005,"Reference Learning Web App",'Course Consumption'!F2:F1005,"P2",'Course Consumption'!R2:R1005,"Fail") -> 0 | M16: =COUNTIFS('Course Consumption'!D2:D1005,"Reference Learning Web App",'Course Consumption'!F2:F1005,"P1",'Course Consumption'!R2:R1005,"Blocked") -> 0 | N16: =COUNTIFS('Course Consumption'!D2:D1005,"Reference Learning Web App",'Course Consumption'!F2:F1005,"P2",'Course Consumption'!R2:R1005,"Blocked") -> 0 | O16: =SUM(K16+M16) -> 0 | P16: =SUM(L16+N16) -> 0 | Q16: =(E16+I16)/C16 -> 1 | R16: =(F16+J16)/D16 -> 1
B17: Mobile | C17: =COUNTIFS('Course Consumption'!D2:D1005,"Reference Learning Mobile App",'Course Consumption'!F2:F1005,"P1") -> 119 | D17: =COUNTIFS('Course Consumption'!D2:D1005,"Reference Learning Mobile App",'Course Consumption'!F2:F1005,"P2") -> 164 | E17: =COUNTIFS('Course Consumption'!D2:D1005,"Reference Learning Mobile App",'Course Consumption'!F2:F1005,"P1",'Course Consumption'!R2:R1005,"NA") -> 3 | F17: =COUNTIFS('Course Consumption'!D2:D1005,"Reference Learning Mobile App",'Course Consumption'!F2:F1005,"P2",'Course Consumption'!R2:R1005,"NA") -> 7 | G17: =C17-(I17+K17+M17+E17) -> 0 | H17: =D17-(J17+L17+N17+F17) -> 0 | I17: =COUNTIFS('Course Consumption'!D2:D1005,"Reference Learning Mobile App",'Course Consumption'!F2:F1005,"P1",'Course Consumption'!R2:R1005,"Pass") -> 116 | J17: =COUNTIFS('Course Consumption'!D2:D1005,"Reference Learning Mobile App",'Course Consumption'!F2:F1005,"P2",'Course Consumption'!R2:R1005,"Pass") -> 157 | K17: =COUNTIFS('Course Consumption'!D2:D1005,"Reference Learning Mobile App",'Course Consumption'!F2:F1005,"P1",'Course Consumption'!R2:R1005,"Fail") -> 0 | L17: =COUNTIFS('Course Consumption'!D2:D1005,"Reference Learning Mobile App",'Course Consumption'!F2:F1005,"P2",'Course Consumption'!R2:R1005,"Fail") -> 0 | M17: =COUNTIFS('Course Consumption'!D2:D1005,"Reference Learning Mobile App",'Course Consumption'!F2:F1005,"P1",'Course Consumption'!R2:R1005,"Blocked") -> 0 | N17: =COUNTIFS('Course Consumption'!D2:D1005,"Reference Learning Mobile App",'Course Consumption'!F2:F1005,"P2",'Course Consumption'!R2:R1005,"Blocked") -> 0 | O17: =SUM(K17+M17) -> 0 | P17: =SUM(L17+N17) -> 0 | Q17: =(E17+I17)/C17 -> 1 | R17: =(F17+J17)/D17 -> 1
B18: Offline Desktop | C18: =COUNTIFS('Course Consumption'!D2:D1005,"Reference Learning Desktop App",'Course Consumption'!F2:F1005,"P1") -> 40 | D18: =COUNTIFS('Course Consumption'!D2:D1005,"Reference Learning Desktop App",'Course Consumption'!F2:F1005,"P2") -> 38 | E18: =COUNTIFS('Course Consumption'!D2:D1005,"Reference Learning Desktop App",'Course Consumption'!F2:F1005,"P1",'Course Consumption'!R2:R1005,"NA") -> 3 | F18: =COUNTIFS('Course Consumption'!D2:D1005,"Reference Learning Desktop App",'Course Consumption'!F2:F1005,"P2",'Course Consumption'!R2:R1005,"NA") -> 2 | G18: =C18-(I18+K18+M18+E18) -> 0 | H18: =D18-(J18+L18+N18+F18) -> 0 | I18: =COUNTIFS('Course Consumption'!D2:D1005,"Reference Learning Desktop App",'Course Consumption'!F2:F1005,"P1",'Course Consumption'!R2:R1005,"Pass") -> 37 | J18: =COUNTIFS('Course Consumption'!D2:D1005,"Reference Learning Desktop App",'Course Consumption'!F2:F1005,"P2",'Course Consumption'!R2:R1005,"Pass") -> 36 | K18: =COUNTIFS('Course Consumption'!D2:D1005,"Reference Learning Desktop App",'Course Consumption'!F2:F1005,"P1",'Course Consumption'!R2:R1005,"Fail") -> 0 | L18: =COUNTIFS('Course Consumption'!D2:D1005,"Reference Learning Desktop App",'Course Consumption'!F2:F1005,"P2",'Course Consumption'!R2:R1005,"Fail") -> 0 | M18: =COUNTIFS('Course Consumption'!D2:D1005,"Reference Learning Desktop App",'Course Consumption'!F2:F1005,"P1",'Course Consumption'!R2:R1005,"Blocked") -> 0 | N18: =COUNTIFS('Course Consumption'!D2:D1005,"Reference Learning Desktop App",'Course Consumption'!F2:F1005,"P2",'Course Consumption'!R2:R1005,"Blocked") -> 0 | O18: =SUM(K18+M18) -> 0 | P18: =SUM(L18+N18) -> 0 | Q18: =(E18+I18)/C18 -> 1 | R18: =(F18+J18)/D18 -> 1
A19: Batch Creation | B19: Portal | C19: =COUNTIFS('Batch Creation'!D2:D1005,"Reference Learning Web App",'Batch Creation'!F2:F1005,"P1") -> 43 | D19: =COUNTIFS('Batch Creation'!D2:D1005,"Reference Learning Web App",'Batch Creation'!F2:F1005,"P2") -> 10 | E19: =COUNTIFS('Batch Creation'!D2:D1005,"Reference Learning Web App",'Batch Creation'!F2:F1005,"P1",'Batch Creation'!Q2:Q1005,"NA") -> 0 | F19: =COUNTIFS('Batch Creation'!D2:D1005,"Reference Learning Web App",'Batch Creation'!F2:F1005,"P2",'Batch Creation'!Q2:Q1005,"NA") -> 0 | G19: =C19-(I19+K19+M19+E19) -> 0 | H19: =D19-(J19+L19+N19+F19) -> 0 | I19: =COUNTIFS('Batch Creation'!D2:D1005,"Reference Learning Web App",'Batch Creation'!F2:F1005,"P1",'Batch Creation'!Q2:Q1005,"Pass") -> 43 | J19: =COUNTIFS('Batch Creation'!D2:D1005,"Reference Learning Web App",'Batch Creation'!F2:F1005,"P2",'Batch Creation'!Q2:Q1005,"Pass") -> 10 | K19: =COUNTIFS('Batch Creation'!D2:D1005,"Reference Learning Web App",'Batch Creation'!F2:F1005,"P1",'Batch Creation'!Q2:Q1005,"Fail") -> 0 | L19: =COUNTIFS('Batch Creation'!D2:D1005,"Reference Learning Web App",'Batch Creation'!F2:F1005,"P2",'Batch Creation'!Q2:Q1005,"Fail") -> 0 | M19: =COUNTIFS('Batch Creation'!D2:D1005,"Reference Learning Web App",'Batch Creation'!F2:F1005,"P1",'Batch Creation'!Q2:Q1005,"Blocked") -> 0 | N19: =COUNTIFS('Batch Creation'!D2:D1005,"Reference Learning Web App",'Batch Creation'!F2:F1005,"P2",'Batch Creation'!Q2:Q1005,"Blocked") -> 0 | O19: =SUM(K19+M19) -> 0 | P19: =SUM(L19+N19) -> 0 | Q19: =(E19+I19)/C19 -> 1 | R19: =(F19+J19)/D19 -> 1
A20: Digital Textbook Consumption | B20: Portal | C20: =COUNTIFS('Digital Textbook Consumption'!D2:D1005,"Reference Learning Web App",'Digital Textbook Consumption'!F2:F1005,"P1") -> 41 | D20: =COUNTIFS('Digital Textbook Consumption'!D2:D1005,"Reference Learning Web App",'Digital Textbook Consumption'!F2:F1005,"P2") -> 30 | E20: =COUNTIFS('Digital Textbook Consumption'!D5:D1005,"Reference Learning Web App",'Digital Textbook Consumption'!F5:F1005,"P1",'Digital Textbook Consumption'!Q5:Q1005,"NA") -> 0 | F20: =COUNTIFS('Digital Textbook Consumption'!D2:D1005,"Reference Learning Web App",'Digital Textbook Consumption'!F2:F1005,"P2",'Digital Textbook Consumption'!Q2:Q1005,"NA") -> 3 | G20: =C20-(I20+K20+M20+E20) -> 0 | H20: =D20-(J20+L20+N20+F20) -> 0 | I20: =COUNTIFS('Digital Textbook Consumption'!D2:D1005,"Reference Learning Web App",'Digital Textbook Consumption'!F2:F1005,"P1",'Digital Textbook Consumption'!Q2:Q1005,"Pass") -> 41 | J20: =COUNTIFS('Digital Textbook Consumption'!D2:D1005,"Reference Learning Web App",'Digital Textbook Consumption'!F2:F1005,"P2",'Digital Textbook Consumption'!Q2:Q1005,"Pass") -> 27 | K20: =COUNTIFS('Digital Textbook Consumption'!D2:D1005,"Reference Learning Web App",'Digital Textbook Consumption'!F2:F1005,"P1",'Digital Textbook Consumption'!Q2:Q1005,"Fail") -> 0 | L20: =COUNTIFS('Digital Textbook Consumption'!D2:D1005,"Reference Learning Web App",'Digital Textbook Consumption'!F2:F1005,"P2",'Digital Textbook Consumption'!Q2:Q1005,"Fail") -> 0 | M20: =COUNTIFS('Digital Textbook Consumption'!D2:D1005,"Reference Learning Web App",'Digital Textbook Consumption'!F2:F1005,"P1",'Digital Textbook Consumption'!Q2:Q1005,"Blocked") -> 0 | N20: =COUNTIFS('Digital Textbook Consumption'!D2:D1005,"Reference Learning Web App",'Digital Textbook Consumption'!F2:F1005,"P2",'Digital Textbook Consumption'!Q2:Q1005,"Blocked") -> 0 | O20: =SUM(K20+M20) -> 0 | P20: =SUM(L20+N20) -> 0 | Q20: =(E20+I20)/C20 -> 1 | R20: =(F20+J20)/D20 -> 1
B21: Mobile | C21: =COUNTIFS('Digital Textbook Consumption'!D2:D1005,"Reference Learning Mobile App",'Digital Textbook Consumption'!F2:F1005,"P1") -> 23 | D21: =COUNTIFS('Digital Textbook Consumption'!D2:D1005,"Reference Learning Mobile App",'Digital Textbook Consumption'!F2:F1005,"P2") -> 34 | E21: =COUNTIFS('Digital Textbook Consumption'!D2:D1005,"Reference Learning Mobile App",'Digital Textbook Consumption'!F2:F1005,"P1",'Digital Textbook Consumption'!Q2:Q1005,"NA") -> 1 | F21: =COUNTIFS('Digital Textbook Consumption'!D2:D1005,"Reference Learning Mobile App",'Digital Textbook Consumption'!F2:F1005,"P2",'Digital Textbook Consumption'!Q2:Q1005,"NA") -> 0 | G21: =C21-(I21+K21+M21+E21) -> 0 | H21: =D21-(J21+L21+N21+F21) -> 0 | I21: =COUNTIFS('Digital Textbook Consumption'!D2:D1005,"Reference Learning Mobile App",'Digital Textbook Consumption'!F2:F1005,"P1",'Digital Textbook Consumption'!Q2:Q1005,"Pass") -> 22 | J21: =COUNTIFS('Digital Textbook Consumption'!D2:D1005,"Reference Learning Mobile App",'Digital Textbook Consumption'!F2:F1005,"P2",'Digital Textbook Consumption'!Q2:Q1005,"Pass") -> 34 | K21: =COUNTIFS('Digital Textbook Consumption'!D2:D1005,"Reference Learning Mobile App",'Digital Textbook Consumption'!F2:F1005,"P1",'Digital Textbook Consumption'!Q2:Q1005,"Fail") -> 0 | L21: =COUNTIFS('Digital Textbook Consumption'!D2:D1005,"Reference Learning Mobile App",'Digital Textbook Consumption'!F2:F1005,"P2",'Digital Textbook Consumption'!Q2:Q1005,"Fail") -> 0 | M21: =COUNTIFS('Digital Textbook Consumption'!D2:D1005,"Reference Learning Mobile App",'Digital Textbook Consumption'!F2:F1005,"P1",'Digital Textbook Consumption'!Q2:Q1005,"Blocked") -> 0 | N21: =COUNTIFS('Digital Textbook Consumption'!D2:D1005,"Reference Learning Mobile App",'Digital Textbook Consumption'!F2:F1005,"P2",'Digital Textbook Consumption'!Q2:Q1005,"Blocked") -> 0 | O21: =SUM(K21+M21) -> 0 | P21: =SUM(L21+N21) -> 0 | Q21: =(E21+I21)/C21 -> 1 | R21: =(F21+J21)/D21 -> 1
B22: Offline Desktop | C22: =COUNTIFS('Digital Textbook Consumption'!D2:D1005,"Reference Learning Desktop App",'Digital Textbook Consumption'!F2:F1005,"P1") -> 15 | D22: =COUNTIFS('Digital Textbook Consumption'!D2:D1005,"Reference Learning Desktop App",'Digital Textbook Consumption'!F2:F1005,"P2") -> 41 | E22: =COUNTIFS('Digital Textbook Consumption'!D2:D1005,"Reference Learning Desktop App",'Digital Textbook Consumption'!F2:F1005,"P1",'Digital Textbook Consumption'!Q2:Q1005,"NA") -> 2 | F22: =COUNTIFS('Digital Textbook Consumption'!D2:D1005,"Reference Learning Desktop App",'Digital Textbook Consumption'!F2:F1005,"P2",'Digital Textbook Consumption'!Q2:Q1005,"NA") -> 2 | G22: =C22-(I22+K22+M22+E22) -> 0 | H22: =D22-(J22+L22+N22+F22) -> 0 | I22: =COUNTIFS('Digital Textbook Consumption'!D2:D1005,"Reference Learning Desktop App",'Digital Textbook Consumption'!F2:F1005,"P1",'Digital Textbook Consumption'!Q2:Q1005,"Pass") -> 13 | J22: =COUNTIFS('Digital Textbook Consumption'!D2:D1005,"Reference Learning Desktop App",'Digital Textbook Consumption'!F2:F1005,"P2",'Digital Textbook Consumption'!Q2:Q1005,"Pass") -> 39 | K22: =COUNTIFS('Digital Textbook Consumption'!D2:D1005,"Reference Learning Desktop App",'Digital Textbook Consumption'!F2:F1005,"P1",'Digital Textbook Consumption'!Q2:Q1005,"Fail") -> 0 | L22: =COUNTIFS('Digital Textbook Consumption'!D2:D1005,"Reference Learning Desktop App",'Digital Textbook Consumption'!F2:F1005,"P2",'Digital Textbook Consumption'!Q2:Q1005,"Fail") -> 0 | M22: =COUNTIFS('Digital Textbook Consumption'!D2:D1005,"Reference Learning Desktop App",'Digital Textbook Consumption'!F2:F1005,"P1",'Digital Textbook Consumption'!Q2:Q1005,"Blocked") -> 0 | N22: =COUNTIFS('Digital Textbook Consumption'!D2:D1005,"Reference Learning Desktop App",'Digital Textbook Consumption'!F2:F1005,"P2",'Digital Textbook Consumption'!Q2:Q1005,"Blocked") -> 0 | O22: =SUM(K22+M22) -> 0 | P22: =SUM(L22+N22) -> 0 | Q22: =(E22+I22)/C22 -> 1 | R22: =(F22+J22)/D22 -> 1
A23: Content Consumption | B23: Portal | C23: =COUNTIFS('Content Consumption'!D2:D1005,"Reference Learning Web App",'Content Consumption'!F2:F1005,"P1") -> 90 | D23: =COUNTIFS('Content Consumption'!D2:D1005,"Reference Learning Web App",'Content Consumption'!F2:F1005,"P2") -> 52 | E23: =COUNTIFS('Content Consumption'!D5:D1005,"Reference Learning Web App",'Content Consumption'!F5:F1005,"P1",'Content Consumption'!Q5:Q1005,"NA") -> 0 | F23: =COUNTIFS('Content Consumption'!D2:D1005,"Reference Learning Web App",'Content Consumption'!F2:F1005,"P2",'Content Consumption'!R2:R1005,"NA") -> 1 | G23: =C23-(I23+K23+M23+E23) -> 0 | H23: =D23-(J23+L23+N23+F23) -> 0 | I23: =COUNTIFS('Content Consumption'!D2:D1005,"Reference Learning Web App",'Content Consumption'!F2:F1005,"P1",'Content Consumption'!R2:R1005,"Pass") -> 90 | J23: =COUNTIFS('Content Consumption'!D2:D1005,"Reference Learning Web App",'Content Consumption'!F2:F1005,"P2",'Content Consumption'!R2:R1005,"Pass") -> 51 | K23: =COUNTIFS('Content Consumption'!D2:D1005,"Reference Learning Web App",'Content Consumption'!F2:F1005,"P1",'Content Consumption'!R2:R1005,"Fail") -> 0 | L23: =COUNTIFS('Content Consumption'!D2:D1005,"Reference Learning Web App",'Content Consumption'!F2:F1005,"P2",'Content Consumption'!R2:R1005,"Fail") -> 0 | M23: =COUNTIFS('Content Consumption'!D2:D1005,"Reference Learning Web App",'Content Consumption'!F2:F1005,"P1",'Content Consumption'!R2:R1005,"Blocked") -> 0 | N23: =COUNTIFS('Content Consumption'!D2:D1005,"Reference Learning Web App",'Content Consumption'!F2:F1005,"P2",'Content Consumption'!R2:R1005,"Blocked") -> 0 | O23: =SUM(K23+M23) -> 0 | P23: =SUM(L23+N23) -> 0 | Q23: =(E23+I23)/C23 -> 1 | R23: =(F23+J23)/D23 -> 1
B24: Mobile | C24: =COUNTIFS('Content Consumption'!D2:D1005,"Reference Learning Mobile App",'Content Consumption'!F2:F1005,"P1") -> 31 | D24: =COUNTIFS('Content Consumption'!D3:D1005,"Reference Learning Mobile App",'Content Consumption'!F3:F1005,"P2") -> 84 | E24: =COUNTIFS('Content Consumption'!D2:D1005,"Reference Learning Mobile App",'Content Consumption'!F2:F1005,"P1",'Content Consumption'!R2:R1005,"NA") -> 1 | F24: =COUNTIFS('Content Consumption'!D2:D1005,"Reference Learning Mobile App",'Content Consumption'!F2:F1005,"P2",'Content Consumption'!R2:R1005,"NA") -> 0 | G24: =C24-(I24+K24+M24+E24) -> 0 | H24: =D24-(J24+L24+N24+F24) -> 0 | I24: =COUNTIFS('Content Consumption'!D2:D1005,"Reference Learning Mobile App",'Content Consumption'!F2:F1005,"P1",'Content Consumption'!R2:R1005,"Pass") -> 30 | J24: =COUNTIFS('Content Consumption'!D2:D1005,"Reference Learning Mobile App",'Content Consumption'!F2:F1005,"P2",'Content Consumption'!R2:R1005,"Pass") -> 84 | K24: =COUNTIFS('Content Consumption'!D2:D1005,"Reference Learning Mobile App",'Content Consumption'!F2:F1005,"P1",'Content Consumption'!R2:R1005,"Fail") -> 0 | L24: =COUNTIFS('Content Consumption'!D2:D1005,"Reference Learning Mobile App",'Content Consumption'!F2:F1005,"P2",'Content Consumption'!R2:R1005,"Fail") -> 0 | M24: =COUNTIFS('Content Consumption'!D2:D1005,"Reference Learning Mobile App",'Content Consumption'!F2:F1005,"P1",'Content Consumption'!R2:R1005,"Blocked") -> 0 | N24: =COUNTIFS('Content Consumption'!D2:D1005,"Reference Learning Mobile App",'Content Consumption'!F2:F1005,"P2",'Content Consumption'!R2:R1005,"Blocked") -> 0 | O24: =SUM(K24+M24) -> 0 | P24: =SUM(L24+N24) -> 0 | Q24: =(E24+I24)/C24 -> 1 | R24: =(F24+J24)/D24 -> 1
B25: Offline Desktop | C25: =COUNTIFS('Content Consumption'!D2:D1005,"Reference Learning Desktop App",'Content Consumption'!F2:F1005,"P1") -> 42 | D25: =COUNTIFS('Content Consumption'!D3:D1005,"Reference Learning Desktop App",'Content Consumption'!F3:F1005,"P2") -> 32 | E25: =COUNTIFS('Content Consumption'!D2:D1005,"Reference Learning Desktop App",'Content Consumption'!F2:F1005,"P1",'Content Consumption'!R2:R1005,"NA") -> 0 | F25: =COUNTIFS('Content Consumption'!D2:D1005,"Reference Learning Desktop App",'Content Consumption'!F2:F1005,"P2",'Content Consumption'!R2:R1005,"NA") -> 0 | G25: =C25-(I25+K25+M25+E25) -> 0 | H25: =D25-(J25+L25+N25+F25) -> 0 | I25: =COUNTIFS('Content Consumption'!D2:D1005,"Reference Learning Desktop App",'Content Consumption'!F2:F1005,"P1",'Content Consumption'!R2:R1005,"Pass") -> 42 | J25: =COUNTIFS('Content Consumption'!D2:D1005,"Reference Learning Desktop App",'Content Consumption'!F2:F1005,"P2",'Content Consumption'!R2:R1005,"Pass") -> 32 | K25: =COUNTIFS('Content Consumption'!D2:D1005,"Reference Learning Desktop App",'Content Consumption'!F2:F1005,"P1",'Content Consumption'!R2:R1005,"Fail") -> 0 | L25: =COUNTIFS('Content Consumption'!D2:D1005,"Reference Learning Desktop App",'Content Consumption'!F2:F1005,"P2",'Content Consumption'!R2:R1005,"Fail") -> 0 | M25: =COUNTIFS('Content Consumption'!D2:D1005,"Reference Learning Desktop App",'Content Consumption'!F2:F1005,"P1",'Content Consumption'!R2:R1005,"Blocked") -> 0 | N25: =COUNTIFS('Content Consumption'!D2:D1005,"Reference Learning Desktop App",'Content Consumption'!F2:F1005,"P2",'Content Consumption'!R2:R1005,"Blocked") -> 0 | O25: =SUM(K25+M25) -> 0 | P25: =SUM(L25+N25) -> 0 | Q25: =(E25+I25)/C25 -> 1 | R25: =(F25+J25)/D25 -> 1
A26: Profile | B26: Portal | C26: =COUNTIFS(Profile!D2:D1005,"Reference Learning Web App",Profile!F2:F1005,"P1") -> 42 | D26: =COUNTIFS(Profile!D2:D1005,"Reference Learning Web App",Profile!F2:F1005,"P2") -> 74 | E26: =COUNTIFS(Profile!D5:D1005,"Reference Learning Web App",Profile!F5:F1005,"P1",Profile!Q5:Q1005,"NA") -> 0 | F26: =COUNTIFS(Profile!D2:D1005,"Reference Learning Web App",Profile!F2:F1005,"P2",Profile!R2:R1005,"NA") -> 3 | G26: =C26-(I26+K26+M26+E26) -> 0 | H26: =D26-(J26+L26+N26+F26) -> 0 | I26: =COUNTIFS(Profile!D2:D1005,"Reference Learning Web App",Profile!F2:F1005,"P1",Profile!R2:R1005,"Pass") -> 42 | J26: =COUNTIFS(Profile!D2:D1005,"Reference Learning Web App",Profile!F2:F1005,"P2",Profile!R2:R1005,"Pass") -> 71 | K26: =COUNTIFS(Profile!D2:D1005,"Reference Learning Web App",Profile!F2:F1005,"P1",Profile!R2:R1005,"Fail") -> 0 | L26: =COUNTIFS(Profile!D2:D1005,"Reference Learning Web App",Profile!F2:F1005,"P2",Profile!R2:R1005,"Fail") -> 0 | M26: =COUNTIFS(Profile!D2:D1005,"Reference Learning Web App",Profile!F2:F1005,"P1",Profile!R2:R1005,"Blocked") -> 0 | N26: =COUNTIFS(Profile!D2:D1005,"Reference Learning Web App",Profile!F2:F1005,"P2",Profile!R2:R1005,"Blocked") -> 0 | O26: =SUM(K26+M26) -> 0 | P26: =SUM(L26+N26) -> 0 | Q26: =(E26+I26)/C26 -> 1 | R26: =(F26+J26)/D26 -> 1
B27: Mobile | C27: =COUNTIFS(Profile!D2:D1005,"Reference Learning Mobile App",Profile!F2:F1005,"P1") -> 43 | D27: =COUNTIFS(Profile!D2:D1005,"Reference Learning Mobile App",Profile!F2:F1005,"P2") -> 51 | E27: =COUNTIFS(Profile!D5:D1005,"Reference Learning Mobile App",Profile!F5:F1005,"P1",Profile!Q5:Q1005,"NA") -> 0 | F27: =COUNTIFS(Profile!D2:D1005,"Reference Learning Mobile App",Profile!F2:F1005,"P2",Profile!R2:R1005,"NA") -> 0 | G27: =C27-(I27+K27+M27+E27) -> 0 | H27: =D27-(J27+L27+N27+F27) -> 0 | I27: =COUNTIFS(Profile!D2:D1005,"Reference Learning Mobile App",Profile!F2:F1005,"P1",Profile!R2:R1005,"Pass") -> 43 | J27: =COUNTIFS(Profile!D2:D1005,"Reference Learning Mobile App",Profile!F2:F1005,"P2",Profile!R2:R1005,"Pass") -> 51 | K27: =COUNTIFS(Profile!D2:D1005,"Reference Learning Mobile App",Profile!F2:F1005,"P1",Profile!R2:R1005,"Fail") -> 0 | L27: =COUNTIFS(Profile!D2:D1005,"Reference Learning Mobile App",Profile!F2:F1005,"P2",Profile!R2:R1005,"Fail") -> 0 | M27: =COUNTIFS(Profile!D2:D1005,"Reference Learning Mobile App",Profile!F2:F1005,"P1",Profile!R2:R1005,"Blocked") -> 0 | N27: =COUNTIFS(Profile!D2:D1005,"Reference Learning Mobile App",Profile!F2:F1005,"P2",Profile!R2:R1005,"Blocked") -> 0 | O27: =SUM(K27+M27) -> 0 | P27: =SUM(L27+N27) -> 0 | Q27: =(E27+I27)/C27 -> 1 | R27: =(F27+J27)/D27 -> 1
B28: Offline Desktop | C28: =COUNTIFS(Profile!D2:D1005,"Reference Learning Desktop App",Profile!F2:F1005,"P1") -> 28 | D28: =COUNTIFS(Profile!D2:D1005,"Reference Learning Desktop App",Profile!F2:F1005,"P2") -> 37 | E28: =COUNTIFS(Profile!D2:D1005,"Reference Learning Desktop App",Profile!F2:F1005,"P1",Profile!R2:R1005,"NA") -> 1 | F28: =COUNTIFS(Profile!D2:D1005,"Reference Learning Desktop App",Profile!F2:F1005,"P2",Profile!R2:R1005,"NA") -> 2 | G28: =C28-(I28+K28+M28+E28) -> 0 | H28: =D28-(J28+L28+N28+F28) -> 0 | I28: =COUNTIFS(Profile!D2:D1005,"Reference Learning Desktop App",Profile!F2:F1005,"P1",Profile!R2:R1005,"Pass") -> 27 | J28: =COUNTIFS(Profile!D2:D1005,"Reference Learning Desktop App",Profile!F2:F1005,"P2",Profile!R2:R1005,"Pass") -> 35 | K28: =COUNTIFS(Profile!D2:D1005,"Reference Learning Desktop App",Profile!F2:F1005,"P1",Profile!R2:R1005,"Fail") -> 0 | L28: =COUNTIFS(Profile!D2:D1005,"Reference Learning Desktop App",Profile!F2:F1005,"P2",Profile!R2:R1005,"Fail") -> 0 | M28: =COUNTIFS(Profile!D2:D1005,"Reference Learning Desktop App",Profile!F2:F1005,"P1",Profile!R2:R1005,"Blocked") -> 0 | N28: =COUNTIFS(Profile!D2:D1005,"Reference Learning Desktop App",Profile!F2:F1005,"P2",Profile!R2:R1005,"Blocked") -> 0 | O28: =SUM(K28+M28) -> 0 | P28: =SUM(L28+N28) -> 0 | Q28: =(E28+I28)/C28 -> 1 | R28: =(F28+J28)/D28 -> 1
A29: Course reports | B29: Portal | C29: =COUNTIFS('Course reports'!D2:D1005,"Reference Learning Web App",'Course reports'!F2:F1005,"P1") -> 20 | D29: =COUNTIFS('Course reports'!D2:D1005,"Reference Learning Web App",'Course reports'!F2:F1005,"P2") -> 7 | E29: =COUNTIFS('Course reports'!D2:D1005,"Reference Learning Web App",'Course reports'!F2:F1005,"P1",'Course reports'!Q2:Q1005,"NA") -> 3 | F29: =COUNTIFS('Course reports'!D2:D1005,"Reference Learning Web App",'Course reports'!F2:F1005,"P2",'Course reports'!Q2:Q1005,"NA") -> 0 | G29: =C29-(I29+K29+M29+E29) -> 0 | H29: =D29-(J29+L29+N29+F29) -> 0 | I29: =COUNTIFS('Course reports'!D2:D1005,"Reference Learning Web App",'Course reports'!F2:F1005,"P1",'Course reports'!Q2:Q1005,"Pass") -> 17 | J29: =COUNTIFS('Course reports'!D2:D1005,"Reference Learning Web App",'Course reports'!F2:F1005,"P2",'Course reports'!Q2:Q1005,"Pass") -> 7 | K29: =COUNTIFS('Course reports'!D2:D1005,"Reference Learning Web App",'Course reports'!F2:F1005,"P1",'Course reports'!Q2:Q1005,"Fail") -> 0 | L29: =COUNTIFS('Course reports'!D2:D1005,"Reference Learning Web App",'Course reports'!F2:F1005,"P2",'Course reports'!Q2:Q1005,"Fail") -> 0 | M29: =COUNTIFS('Course reports'!D2:D1005,"Reference Learning Web App",'Course reports'!F2:F1005,"P1",'Course reports'!Q2:Q1005,"Blocked") -> 0 | N29: =COUNTIFS('Course reports'!D2:D1005,"Reference Learning Web App",'Course reports'!F2:F1005,"P2",'Course reports'!Q2:Q1005,"Blocked") -> 0 | O29: =SUM(K29+M29) -> 0 | P29: =SUM(L29+N29) -> 0 | Q29: =(E29+I29)/C29 -> 1 | R29: =(F29+J29)/D29 -> 1
B30: Mobile | C30: =COUNTIFS('Course reports'!D2:D1005,"Reference Learning Mobile App",'Course reports'!F2:F1005,"P1") -> 0 | D30: =COUNTIFS('Course reports'!D2:D1005,"Reference Learning Mobile App",'Course reports'!F2:F1005,"P2") -> 2 | E30: =COUNTIFS('Course reports'!D2:D1005,"Reference Learning Mobile App",'Course reports'!F2:F1005,"P1",'Course reports'!Q2:Q1005,"NA") -> 0 | F30: =COUNTIFS('Course reports'!D2:D1005,"Reference Learning Mobile App",'Course reports'!F2:F1005,"P2",'Course reports'!Q2:Q1005,"NA") -> 0 | G30: =C30-(I30+K30+M30+E30) -> 0 | H30: =D30-(J30+L30+N30+F30) -> 0 | I30: =COUNTIFS('Course reports'!D2:D1005,"Reference Learning Mobile App",'Course reports'!F2:F1005,"P1",'Course reports'!Q2:Q1005,"Pass") -> 0 | J30: =COUNTIFS('Course reports'!D2:D1005,"Reference Learning Mobile App",'Course reports'!F2:F1005,"P2",'Course reports'!Q2:Q1005,"Pass") -> 2 | K30: =COUNTIFS('Course reports'!D2:D1005,"Reference Learning Mobile App",'Course reports'!F2:F1005,"P1",'Course reports'!Q2:Q1005,"Fail") -> 0 | L30: =COUNTIFS('Course reports'!D2:D1005,"Reference Learning Mobile App",'Course reports'!F2:F1005,"P2",'Course reports'!Q2:Q1005,"Fail") -> 0 | M30: =COUNTIFS('Course reports'!D2:D1005,"Reference Learning Mobile App",'Course reports'!F2:F1005,"P1",'Course reports'!Q2:Q1005,"Blocked") -> 0 | N30: =COUNTIFS('Course reports'!D2:D1005,"Reference Learning Mobile App",'Course reports'!F2:F1005,"P2",'Course reports'!Q2:Q1005,"Blocked") -> 0 | O30: =SUM(K30+M30) -> 0 | P30: =SUM(L30+N30) -> 0 | Q30: =(E30+I30)/C30 -> #DIV/0! | R30: =(F30+J30)/D30 -> 1
A31: QUML | B31: Portal | C31: =COUNTIFS(QUML!D2:D1005,"Reference Learning Web App",QUML!F2:F1005,"P1") -> 225 | D31: =COUNTIFS(QUML!D2:D1005,"Reference Learning Web App",QUML!F2:F1005,"P2") -> 192 | E31: =COUNTIFS(QUML!D2:D1005,"Reference Learning Web App",QUML!F2:F1005,"P1",QUML!R2:R1005,"NA") -> 5 | F31: =COUNTIFS(QUML!D2:D1005,"Reference Learning Web App",QUML!F2:F1005,"P2",QUML!R2:R1005,"NA") -> 4 | G31: =C31-(I31+K31+M31+E31) -> 0 | H31: =D31-(J31+L31+N31+F31) -> 0 | I31: =COUNTIFS(QUML!D2:D1005,"Reference Learning Web App",QUML!F2:F1005,"P1",QUML!R2:R1005,"Pass") -> 220 | J31: =COUNTIFS(QUML!D2:D1005,"Reference Learning Web App",QUML!F2:F1005,"P2",QUML!R2:R1005,"Pass") -> 188 | K31: =COUNTIFS(QUML!D2:D1005,"Reference Learning Web App",QUML!F2:F1005,"P1",QUML!R2:R1005,"Fail") -> 0 | L31: =COUNTIFS(QUML!D2:D1005,"Reference Learning Web App",QUML!F2:F1005,"P2",QUML!R2:R1005,"Fail") -> 0 | M31: =COUNTIFS(QUML!D2:D1005,"Reference Learning Web App",QUML!F2:F1005,"P1",QUML!R2:R1005,"Blocked") -> 0 | N31: =COUNTIFS(QUML!D2:D1005,"Reference Learning Web App",QUML!F2:F1005,"P2",QUML!R2:R1005,"Blocked") -> 0 | O31: =SUM(K31+M31) -> 0 | P31: =SUM(L31+N31) -> 0 | Q31: =(E31+I31)/C31 -> 1 | R31: =(F31+J31)/D31 -> 1
B32: Mobile | C32: =COUNTIFS(QUML!D2:D1005,"Reference Learning Mobile App",QUML!F2:F1005,"P1") -> 67 | D32: =COUNTIFS(QUML!D2:D1005,"Reference Learning Mobile App",QUML!F2:F1005,"P2") -> 59 | E32: =COUNTIFS(QUML!D2:D1005,"Reference Learning Mobile App",QUML!F2:F1005,"P1",QUML!R2:R1005,"NA") -> 0 | F32: =COUNTIFS(QUML!D2:D1005,"Reference Learning Mobile App",QUML!F2:F1005,"P2",QUML!R2:R1005,"NA") -> 1 | G32: =C32-(I32+K32+M32+E32) -> 0 | H32: =D32-(J32+L32+N32+F32) -> 0 | I32: =COUNTIFS(QUML!D2:D1005,"Reference Learning Mobile App",QUML!F2:F1005,"P1",QUML!R2:R1005,"Pass") -> 67 | J32: =COUNTIFS(QUML!D2:D1005,"Reference Learning Mobile App",QUML!F2:F1005,"P2",QUML!R2:R1005,"Pass") -> 58 | K32: =COUNTIFS(QUML!D2:D1005,"Reference Learning Mobile App",QUML!F2:F1005,"P1",QUML!R2:R1005,"Fail") -> 0 | L32: =COUNTIFS(QUML!D2:D1005,"Reference Learning Mobile App",QUML!F2:F1005,"P2",QUML!R2:R1005,"Fail") -> 0 | M32: =COUNTIFS(QUML!D2:D1005,"Reference Learning Mobile App",QUML!F2:F1005,"P1",QUML!R2:R1005,"Blocked") -> 0 | N32: =COUNTIFS(QUML!D2:D1005,"Reference Learning Mobile App",QUML!F2:F1005,"P2",QUML!R2:R1005,"Blocked") -> 0 | O32: =SUM(K32+M32) -> 0 | P32: =SUM(L32+N32) -> 0 | Q32: =(E32+I32)/C32 -> 1 | R32: =(F32+J32)/D32 -> 1
B33: Offline Desktop | C33: =COUNTIFS(QUML!D2:D1005,"Reference Learning Desktop App",QUML!F2:F1005,"P1") -> 44 | D33: =COUNTIFS(QUML!D2:D1005,"Reference Learning Desktop App",QUML!F2:F1005,"P2") -> 4 | E33: =COUNTIFS(QUML!D2:D1005,"Reference Learning Offline App",QUML!F2:F1005,"P1",QUML!R2:R1005,"NA") -> 0 | F33: =COUNTIFS(QUML!D2:D1005,"Reference Learning Offline App",QUML!F2:F1005,"P2",QUML!R2:R1005,"NA") -> 0 | G33: =C33-(I33+K33+M33+E33) -> 0 | H33: =D33-(J33+L33+N33+F33) -> 0 | I33: =COUNTIFS(QUML!D2:D1005,"Reference Learning Desktop App",QUML!F2:F1005,"P1",QUML!R2:R1005,"Pass") -> 44 | J33: =COUNTIFS(QUML!D2:D1005,"Reference Learning Desktop App",QUML!F2:F1005,"P2",QUML!R2:R1005,"Pass") -> 4 | K33: =COUNTIFS(QUML!D2:D1005,"Reference Learning Offline App",QUML!F2:F1005,"P1",QUML!R2:R1005,"Fail") -> 0 | L33: =COUNTIFS(QUML!D2:D1005,"Reference Learning Offline App",QUML!F2:F1005,"P2",QUML!R2:R1005,"Fail") -> 0 | M33: =COUNTIFS(QUML!D2:D1005,"Reference Learning Offline App",QUML!F2:F1005,"P1",QUML!R2:R1005,"Blocked") -> 0 | N33: =COUNTIFS(QUML!D2:D1005,"Reference Learning Offline App",QUML!F2:F1005,"P2",QUML!R2:R1005,"Blocked") -> 0 | O33: =SUM(K33+M33) -> 0 | P33: =SUM(L33+N33) -> 0 | Q33: =(E33+I33)/C33 -> 1 | R33: =(F33+J33)/D33 -> 1
A34: Mobile configurability | B34: Mobile | C34: =COUNTIFS('Mobile configurability'!D2:D1005,"Reference Learning Mobile App",'Mobile configurability'!F2:F1005,"P1") -> 34 | D34: =COUNTIFS('Mobile configurability'!D2:D1005,"Reference Learning Mobile App",'Mobile configurability'!F2:F1005,"P2") -> 76 | E34: =COUNTIFS('Mobile configurability'!D2:D1005,"Reference Learning Mobile App",'Mobile configurability'!F2:F1005,"P1",'Mobile configurability'!Q2:Q1005,"NA") -> 0 | F34: =COUNTIFS('Mobile configurability'!D2:D1005,"Reference Learning Mobile App",'Mobile configurability'!F2:F1005,"P2",'Mobile configurability'!Q2:Q1005,"NA") -> 7 | G34: =C34-(I34+K34+M34+E34) -> 0 | H34: =D34-(J34+L34+N34+F34) -> 0 | I34: =COUNTIFS('Mobile configurability'!D2:D1005,"Reference Learning Mobile App",'Mobile configurability'!F2:F1005,"P1",'Mobile configurability'!Q2:Q1005,"Pass") -> 34 | J34: =COUNTIFS('Mobile configurability'!D2:D1005,"Reference Learning Mobile App",'Mobile configurability'!F2:F1005,"P2",'Mobile configurability'!Q2:Q1005,"Pass") -> 69 | K34: =COUNTIFS('Mobile configurability'!D2:D1005,"Reference Learning Mobile App",'Mobile configurability'!F2:F1005,"P1",'Mobile configurability'!Q2:Q1005,"Fail") -> 0 | L34: =COUNTIFS('Mobile configurability'!D2:D1005,"Reference Learning Mobile App",'Mobile configurability'!F2:F1005,"P2",'Mobile configurability'!Q2:Q1005,"Fail") -> 0 | M34: =COUNTIFS('Mobile configurability'!D2:D1005,"Reference Learning Mobile App",'Mobile configurability'!F2:F1005,"P1",'Mobile configurability'!Q2:Q1005,"Blocked") -> 0 | N34: =COUNTIFS('Mobile configurability'!D2:D1005,"Reference Learning Mobile App",'Mobile configurability'!F2:F1005,"P2",'Mobile configurability'!Q2:Q1005,"Blocked") -> 0 | O34: =SUM(K34+M34) -> 0 | P34: =SUM(L34+N34) -> 0 | Q34: =(E34+I34)/C34 -> 1 | R34: =(F34+J34)/D34 -> 1
A35: Mobile specific Test Cases | B35: Mobile | C35: =COUNTIFS('Mobile specific Test Cases'!D2:D1005,"Reference Learning Mobile App",'Mobile specific Test Cases'!F2:F1005,"P1") -> 32 | D35: =COUNTIFS('Mobile specific Test Cases'!D2:D1005,"Reference Learning Mobile App",'Mobile specific Test Cases'!F2:F1005,"P2") -> 39 | E35: =COUNTIFS('Mobile specific Test Cases'!D2:D1005,"Reference Learning Mobile App",'Mobile specific Test Cases'!F2:F1005,"P1",'Mobile specific Test Cases'!Q2:Q1005,"NA") -> 2 | F35: =COUNTIFS('Mobile specific Test Cases'!D2:D1005,"Reference Learning Mobile App",'Mobile specific Test Cases'!F2:F1005,"P2",'Mobile specific Test Cases'!Q2:Q1005,"NA") -> 0 | G35: =C35-(I35+K35+M35+E35) -> 0 | H35: =D35-(J35+L35+N35+F35) -> 0 | I35: =COUNTIFS('Mobile specific Test Cases'!D2:D1005,"Reference Learning Mobile App",'Mobile specific Test Cases'!F2:F1005,"P1",'Mobile specific Test Cases'!Q2:Q1005,"Pass") -> 30 | J35: =COUNTIFS('Mobile specific Test Cases'!D2:D1005,"Reference Learning Mobile App",'Mobile specific Test Cases'!F2:F1005,"P2",'Mobile specific Test Cases'!Q2:Q1005,"Pass") -> 39 | K35: =COUNTIFS('Mobile specific Test Cases'!D2:D1005,"Reference Learning Mobile App",'Mobile specific Test Cases'!F2:F1005,"P1",'Mobile specific Test Cases'!Q2:Q1005,"Fail") -> 0 | L35: =COUNTIFS('Mobile specific Test Cases'!D2:D1005,"Reference Learning Mobile App",'Mobile specific Test Cases'!F2:F1005,"P2",'Mobile specific Test Cases'!Q2:Q1005,"Fail") -> 0 | M35: =COUNTIFS('Mobile specific Test Cases'!D2:D1005,"Reference Learning Mobile App",'Mobile specific Test Cases'!F2:F1005,"P1",'Mobile specific Test Cases'!Q2:Q1005,"Blocked") -> 0 | N35: =COUNTIFS('Mobile specific Test Cases'!D2:D1005,"Reference Learning Mobile App",'Mobile specific Test Cases'!F2:F1005,"P2",'Mobile specific Test Cases'!Q2:Q1005,"Blocked") -> 0 | O35: =SUM(K35+M35) -> 0 | P35: =SUM(L35+N35) -> 0 | Q35: =(E35+I35)/C35 -> 1 | R35: =(F35+J35)/D35 -> 1
A36: Org admin reports | B36: Portal | C36: =COUNTIFS('Org admin reports'!D2:D1005,"Reference Learning Web App",'Org admin reports'!F2:F1005,"P1") -> 69 | D36: =COUNTIFS('Org admin reports'!D2:D1005,"Reference Learning Web App",'Org admin reports'!F2:F1005,"P2") -> 26 | E36: =COUNTIFS('Org admin reports'!D2:D1005,"Reference Learning Web App",'Org admin reports'!F2:F1005,"P1",'Org admin reports'!Q2:Q1005,"NA") -> 5 | F36: =COUNTIFS('Org admin reports'!D2:D1005,"Reference Learning Web App",'Org admin reports'!F2:F1005,"P2",'Org admin reports'!Q2:Q1005,"NA") -> 1 | G36: =C36-(I36+K36+M36+E36) -> 0 | H36: =D36-(J36+L36+N36+F36) -> 0 | I36: =COUNTIFS('Org admin reports'!D2:D1005,"Reference Learning Web App",'Org admin reports'!F2:F1005,"P1",'Org admin reports'!Q2:Q1005,"Pass") -> 64 | J36: =COUNTIFS('Org admin reports'!D2:D1005,"Reference Learning Web App",'Org admin reports'!F2:F1005,"P2",'Org admin reports'!Q2:Q1005,"Pass") -> 25 | K36: =COUNTIFS('Org admin reports'!D2:D1005,"Reference Learning Web App",'Org admin reports'!F2:F1005,"P1",'Org admin reports'!Q2:Q1005,"Fail") -> 0 | L36: =COUNTIFS('Org admin reports'!D2:D1005,"Reference Learning Web App",'Org admin reports'!F2:F1005,"P2",'Org admin reports'!Q2:Q1005,"Fail") -> 0 | M36: =COUNTIFS('Org admin reports'!D2:D1005,"Reference Learning Web App",'Org admin reports'!F2:F1005,"P1",'Org admin reports'!Q2:Q1005,"Blocked") -> 0 | N36: =COUNTIFS('Org admin reports'!D2:D1005,"Reference Learning Web App",'Org admin reports'!F2:F1005,"P2",'Org admin reports'!Q2:Q1005,"Blocked") -> 0 | O36: =SUM(K36+M36) -> 0 | P36: =SUM(L36+N36) -> 0 | Q36: =(E36+I36)/C36 -> 1 | R36: =(F36+J36)/D36 -> 1
B37: Mobile | C37: =COUNTIFS('Org admin reports'!D2:D1005,"Reference Learning Mobile App",'Org admin reports'!F2:F1005,"P1") -> 0 | D37: =COUNTIFS('Org admin reports'!D2:D1005,"Reference Learning Mobile App",'Org admin reports'!F2:F1005,"P2") -> 5 | E37: =COUNTIFS('Org admin reports'!D2:D1005,"Reference Learning Mobile App",'Org admin reports'!F2:F1005,"P1",'Org admin reports'!Q2:Q1005,"NA") -> 0 | F37: =COUNTIFS('Org admin reports'!D2:D1005,"Reference Learning Mobile App",'Org admin reports'!F2:F1005,"P2",'Org admin reports'!Q2:Q1005,"NA") -> 0 | G37: =C37-(I37+K37+M37+E37) -> 0 | H37: =D37-(J37+L37+N37+F37) -> 0 | I37: =COUNTIFS('Org admin reports'!D2:D1005,"Reference Learning Mobile App",'Org admin reports'!F2:F1005,"P1",'Org admin reports'!Q2:Q1005,"Pass") -> 0 | J37: =COUNTIFS('Org admin reports'!D2:D1005,"Reference Learning Mobile App",'Org admin reports'!F2:F1005,"P2",'Org admin reports'!Q2:Q1005,"Pass") -> 5 | K37: =COUNTIFS('Org admin reports'!D2:D1005,"Reference Learning Mobile App",'Org admin reports'!F2:F1005,"P1",'Org admin reports'!Q2:Q1005,"Fail") -> 0 | L37: =COUNTIFS('Org admin reports'!D2:D1005,"Reference Learning Mobile App",'Org admin reports'!F2:F1005,"P2",'Org admin reports'!Q2:Q1005,"Fail") -> 0 | M37: =COUNTIFS('Org admin reports'!D2:D1005,"Reference Learning Mobile App",'Org admin reports'!F2:F1005,"P1",'Org admin reports'!Q2:Q1005,"Blocked") -> 0 | N37: =COUNTIFS('Org admin reports'!D2:D1005,"Reference Learning Mobile App",'Org admin reports'!F2:F1005,"P2",'Org admin reports'!Q2:Q1005,"Blocked") -> 0 | O37: =SUM(K37+M37) -> 0 | P37: =SUM(L37+N37) -> 0 | Q37: =(E37+I37)/C37 -> #DIV/0! | R37: =(F37+J37)/D37 -> 1
A38: QR code | B38: Portal | C38: =COUNTIFS('QR code'!D2:D1005,"Reference Learning Web App",'QR code'!F2:F1005,"P1") -> 78 | D38: =COUNTIFS('QR code'!D2:D1005,"Reference Learning Web App",'QR code'!F2:F1005,"P2") -> 18 | E38: =COUNTIFS('QR code'!D2:D1005,"Reference Learning Web App",'QR code'!F2:F1005,"P1",'QR code'!R2:R1005,"NA") -> 5 | F38: =COUNTIFS('QR code'!D2:D1005,"Reference Learning Web App",'QR code'!F2:F1005,"P2",'QR code'!R2:R1005,"NA") -> 4 | G38: =C38-(I38+K38+M38+E38) -> 0 | H38: =D38-(J38+L38+N38+F38) -> 0 | I38: =COUNTIFS('QR code'!D2:D1005,"Reference Learning Web App",'QR code'!F2:F1005,"P1",'QR code'!R2:R1005,"Pass") -> 73 | J38: =COUNTIFS('QR code'!D2:D1005,"Reference Learning Web App",'QR code'!F2:F1005,"P2",'QR code'!R2:R1005,"Pass") -> 14 | K38: =COUNTIFS('QR code'!D2:D1005,"Reference Learning Web App",'QR code'!F2:F1005,"P1",'QR code'!R2:R1005,"Fail") -> 0 | L38: =COUNTIFS('QR code'!D2:D1005,"Reference Learning Web App",'QR code'!F2:F1005,"P2",'QR code'!R2:R1005,"Fail") -> 0 | M38: =COUNTIFS('QR code'!D2:D1005,"Reference Learning Web App",'QR code'!F2:F1005,"P1",'QR code'!R2:R1005,"Blocked") -> 0 | N38: =COUNTIFS('QR code'!D2:D1005,"Reference Learning Web App",'QR code'!F2:F1005,"P2",'QR code'!R2:R1005,"Blocked") -> 0 | O38: =SUM(K38+M38) -> 0 | P38: =SUM(L38+N38) -> 0 | Q38: =(E38+I38)/C38 -> 1 | R38: =(F38+J38)/D38 -> 1
B39: Mobile | C39: =COUNTIFS('QR code'!D2:D1005,"Reference Learning Mobile App",'QR code'!F2:F1005,"P1") -> 21 | D39: =COUNTIFS('QR code'!D2:D1005,"Reference Learning Mobile App",'QR code'!F2:F1005,"P2") -> 40 | E39: =COUNTIFS('QR code'!D2:D1005,"Reference Learning Mobile App",'QR code'!F2:F1005,"P1",'QR code'!R2:R1005,"NA") -> 5 | F39: =COUNTIFS('QR code'!D2:D1005,"Reference Learning Mobile App",'QR code'!F2:F1005,"P2",'QR code'!R2:R1005,"NA") -> 5 | G39: =C39-(I39+K39+M39+E39) -> 0 | H39: =D39-(J39+L39+N39+F39) -> 0 | I39: =COUNTIFS('QR code'!D2:D1005,"Reference Learning Mobile App",'QR code'!F2:F1005,"P1",'QR code'!R2:R1005,"Pass") -> 16 | J39: =COUNTIFS('QR code'!D2:D1005,"Reference Learning Mobile App",'QR code'!F2:F1005,"P2",'QR code'!R2:R1005,"Pass") -> 35 | K39: =COUNTIFS('QR code'!D2:D1005,"Reference Learning Mobile App",'QR code'!F2:F1005,"P1",'QR code'!R2:R1005,"Fail") -> 0 | L39: =COUNTIFS('QR code'!D2:D1005,"Reference Learning Mobile App",'QR code'!F2:F1005,"P2",'QR code'!R2:R1005,"Fail") -> 0 | M39: =COUNTIFS('QR code'!D2:D1005,"Reference Learning Mobile App",'QR code'!F2:F1005,"P1",'QR code'!R2:R1005,"Blocked") -> 0 | N39: =COUNTIFS('QR code'!D2:D1005,"Reference Learning Mobile App",'QR code'!F2:F1005,"P2",'QR code'!R2:R1005,"Blocked") -> 0 | O39: =SUM(K39+M39) -> 0 | P39: =SUM(L39+N39) -> 0 | Q39: =(E39+I39)/C39 -> 1 | R39: =(F39+J39)/D39 -> 1
A40: Portal/ Desktop App Configurability | B40: Portal | C40: =COUNTIFS('Portal Desktop App Configurabil'!D2:D1005,"Reference Learning Web App",'Portal Desktop App Configurabil'!F2:F1005,"P1") -> 36 | D40: =COUNTIFS('Portal Desktop App Configurabil'!D2:D1005,"Reference Learning Web App",'Portal Desktop App Configurabil'!F2:F1005,"P2") -> 25 | E40: =COUNTIFS('Portal Desktop App Configurabil'!D2:D1005,"Reference Learning Web App",'Portal Desktop App Configurabil'!F2:F1005,"P1",'Portal Desktop App Configurabil'!Q2:Q1005,"NA") -> 2 | F40: =COUNTIFS('Portal Desktop App Configurabil'!D2:D1005,"Reference Learning Web App",'Portal Desktop App Configurabil'!F2:F1005,"P2",'Portal Desktop App Configurabil'!Q2:Q1005,"NA") -> 1 | G40: =C40-(I40+K40+M40+E40) -> 0 | H40: =D40-(J40+L40+N40+F40) -> 0 | I40: =COUNTIFS('Portal Desktop App Configurabil'!D2:D1005,"Reference Learning Web App",'Portal Desktop App Configurabil'!F2:F1005,"P1",'Portal Desktop App Configurabil'!Q2:Q1005,"Pass") -> 34 | J40: =COUNTIFS('Portal Desktop App Configurabil'!D2:D1005,"Reference Learning Web App",'Portal Desktop App Configurabil'!F2:F1005,"P2",'Portal Desktop App Configurabil'!Q2:Q1005,"Pass") -> 24 | K40: =COUNTIFS('Portal Desktop App Configurabil'!D2:D1005,"Reference Learning Web App",'Portal Desktop App Configurabil'!F2:F1005,"P1",'Portal Desktop App Configurabil'!Q2:Q1005,"Fail") -> 0 | L40: =COUNTIFS('Portal Desktop App Configurabil'!D2:D1005,"Reference Learning Web App",'Portal Desktop App Configurabil'!F2:F1005,"P2",'Portal Desktop App Configurabil'!Q2:Q1005,"Fail") -> 0 | M40: =COUNTIFS('Portal Desktop App Configurabil'!D2:D1005,"Reference Learning Web App",'Portal Desktop App Configurabil'!F2:F1005,"P1",'Portal Desktop App Configurabil'!Q2:Q1005,"Blocked") -> 0 | N40: =COUNTIFS('Portal Desktop App Configurabil'!D2:D1005,"Reference Learning Web App",'Portal Desktop App Configurabil'!F2:F1005,"P2",'Portal Desktop App Configurabil'!Q2:Q1005,"Blocked") -> 0 | O40: =SUM(K40+M40) -> 0 | P40: =SUM(L40+N40) -> 0 | Q40: =(E40+I40)/C40 -> 1 | R40: =(F40+J40)/D40 -> 1
B41: Offline Desktop | C41: =COUNTIFS('Portal Desktop App Configurabil'!D2:D1005,"Reference Learning Desktop App",'Portal Desktop App Configurabil'!F2:F1005,"P1") -> 4 | D41: =COUNTIFS('Portal Desktop App Configurabil'!D2:D1005,"Reference Learning Desktop App",'Portal Desktop App Configurabil'!F2:F1005,"P2") -> 9 | E41: =COUNTIFS('Portal Desktop App Configurabil'!D2:D1005,"Reference Learning Desktop App",'Portal Desktop App Configurabil'!F2:F1005,"P1",'Portal Desktop App Configurabil'!Q2:Q1005,"NA") -> 0 | F41: =COUNTIFS('Portal Desktop App Configurabil'!D2:D1005,"Reference Learning Desktop App",'Portal Desktop App Configurabil'!F2:F1005,"P2",'Portal Desktop App Configurabil'!Q2:Q1005,"NA") -> 0 | G41: =C41-(I41+K41+M41+E41) -> 0 | H41: =D41-(J41+L41+N41+F41) -> 0 | I41: =COUNTIFS('Portal Desktop App Configurabil'!D2:D1005,"Reference Learning Desktop App",'Portal Desktop App Configurabil'!F2:F1005,"P1",'Portal Desktop App Configurabil'!Q2:Q1005,"Pass") -> 4 | J41: =COUNTIFS('Portal Desktop App Configurabil'!D2:D1005,"Reference Learning Desktop App",'Portal Desktop App Configurabil'!F2:F1005,"P2",'Portal Desktop App Configurabil'!Q2:Q1005,"Pass") -> 9 | K41: =COUNTIFS('Portal Desktop App Configurabil'!D2:D1005,"Reference Learning Desktop App",'Portal Desktop App Configurabil'!F2:F1005,"P1",'Portal Desktop App Configurabil'!Q2:Q1005,"Fail") -> 0 | L41: =COUNTIFS('Portal Desktop App Configurabil'!D2:D1005,"Reference Learning Desktop App",'Portal Desktop App Configurabil'!F2:F1005,"P2",'Portal Desktop App Configurabil'!Q2:Q1005,"Fail") -> 0 | M41: =COUNTIFS('Portal Desktop App Configurabil'!D2:D1005,"Reference Learning Desktop App",'Portal Desktop App Configurabil'!F2:F1005,"P1",'Portal Desktop App Configurabil'!Q2:Q1005,"Blocked") -> 0 | N41: =COUNTIFS('Portal Desktop App Configurabil'!D2:D1005,"Reference Learning Desktop App",'Portal Desktop App Configurabil'!F2:F1005,"P2",'Portal Desktop App Configurabil'!Q2:Q1005,"Blocked") -> 0 | O41: =SUM(K41+M41) -> 0 | P41: =SUM(L41+N41) -> 0 | Q41: =(E41+I41)/C41 -> 1 | R41: =(F41+J41)/D41 -> 1
A42: Sunbird UCI | B42: Portal | C42: =COUNTIFS('Sunbird UCI'!D2:D1005,"Portal tara",'Sunbird UCI'!F2:F1005,"P1") -> 21 | D42: =COUNTIFS('Sunbird UCI'!D2:D1005,"Portal tara",'Sunbird UCI'!F2:F1005,"P2") -> 21 | E42: =COUNTIFS('Sunbird UCI'!D2:D1005,"Portal tara",'Sunbird UCI'!F2:F1005,"P1",'Sunbird UCI'!R2:R1005,"NA") -> 21 | F42: =COUNTIFS('Sunbird UCI'!D2:D1005,"Portal tara",'Sunbird UCI'!F2:F1005,"P2",'Sunbird UCI'!R2:R1005,"NA") -> 21 | G42: =C42-(I42+K42+M42+E42) -> 0 | H42: =D42-(J42+L42+N42+F42) -> 0 | I42: =COUNTIFS('Sunbird UCI'!D2:D1005,"Portal tara",'Sunbird UCI'!F2:F1005,"P1",'Sunbird UCI'!R2:R1005,"Pass") -> 0 | J42: =COUNTIFS('Sunbird UCI'!D2:D1005,"Portal tara",'Sunbird UCI'!F2:F1005,"P2",'Sunbird UCI'!R2:R1005,"Pass") -> 0 | K42: =COUNTIFS('Sunbird UCI'!D2:D1005,"Portal tara",'Sunbird UCI'!F2:F1005,"P1",'Sunbird UCI'!R2:R1005,"Fail") -> 0 | L42: =COUNTIFS('Sunbird UCI'!D2:D1005,"Portal tara",'Sunbird UCI'!F2:F1005,"P2",'Sunbird UCI'!R2:R1005,"Fail") -> 0 | M42: =COUNTIFS('Sunbird UCI'!D2:D1005,"Portal tara",'Sunbird UCI'!F2:F1005,"P1",'Sunbird UCI'!R2:R1005,"Blocked") -> 0 | N42: =COUNTIFS('Sunbird UCI'!D2:D1005,"Portal tara",'Sunbird UCI'!F2:F1005,"P2",'Sunbird UCI'!R2:R1005,"Blocked") -> 0 | O42: =SUM(K42+M42) -> 0 | P42: =SUM(L42+N42) -> 0 | Q42: =(E42+I42)/C42 -> 1 | R42: =(F42+J42)/D42 -> 1
B43: Mobile | C43: =COUNTIFS('Sunbird UCI'!D2:D1005,"Mobile tara",'Sunbird UCI'!F2:F1005,"P1") -> 1 | D43: =COUNTIFS('Sunbird UCI'!D2:D1005,"Mobile tara",'Sunbird UCI'!F2:F1005,"P2") -> 5 | E43: =COUNTIFS('Sunbird UCI'!D2:D1005,"Mobile tara",'Sunbird UCI'!F2:F1005,"P1",'Sunbird UCI'!R2:R1005,"NA") -> 1 | F43: =COUNTIFS('Sunbird UCI'!D2:D1005,"Mobile tara",'Sunbird UCI'!F2:F1005,"P2",'Sunbird UCI'!R2:R1005,"NA") -> 5 | G43: =C43-(I43+K43+M43+E43) -> 0 | H43: =D43-(J43+L43+N43+F43) -> 0 | I43: =COUNTIFS('Sunbird UCI'!D2:D1005,"Mobile tara",'Sunbird UCI'!F2:F1005,"P1",'Sunbird UCI'!R2:R1005,"Pass") -> 0 | J43: =COUNTIFS('Sunbird UCI'!D2:D1005,"Mobile tara",'Sunbird UCI'!F2:F1005,"P2",'Sunbird UCI'!R2:R1005,"Pass") -> 0 | K43: =COUNTIFS('Sunbird UCI'!D2:D1005,"Mobile tara",'Sunbird UCI'!F2:F1005,"P1",'Sunbird UCI'!R2:R1005,"Fail") -> 0 | L43: =COUNTIFS('Sunbird UCI'!D2:D1005,"Mobile tara",'Sunbird UCI'!F2:F1005,"P2",'Sunbird UCI'!R2:R1005,"Fail") -> 0 | M43: =COUNTIFS('Sunbird UCI'!D2:D1005,"Mobile tara",'Sunbird UCI'!F2:F1005,"P1",'Sunbird UCI'!R2:R1005,"Blocked") -> 0 | N43: =COUNTIFS('Sunbird UCI'!D2:D1005,"Mobile tara",'Sunbird UCI'!F2:F1005,"P2",'Sunbird UCI'!R2:R1005,"Blocked") -> 0 | O43: =SUM(K43+M43) -> 0 | P43: =SUM(L43+N43) -> 0 | Q43: =(E43+I43)/C43 -> 1 | R43: =(F43+J43)/D43 -> 1
B44: Watsup Chatbot | C44: =COUNTIFS('Sunbird UCI'!D2:D1005,"Watsup chatbot",'Sunbird UCI'!F2:F1005,"P1") -> 40 | D44: =COUNTIFS('Sunbird UCI'!D2:D1005,"Watsup chatbot",'Sunbird UCI'!F2:F1005,"P2") -> 0 | E44: =COUNTIFS('Sunbird UCI'!D2:D1005,"Watsup Chatbot",'Sunbird UCI'!F2:F1005,"P1",'Sunbird UCI'!R2:R1005,"NA") -> 40 | F44: =COUNTIFS('Sunbird UCI'!D2:D1005,"Watsup Chatbot",'Sunbird UCI'!F2:F1005,"P2",'Sunbird UCI'!R2:R1005,"NA") -> 0 | G44: =C44-(I44+K44+M44+E44) -> 0 | H44: =D44-(J44+L44+N44+F44) -> 0 | I44: =COUNTIFS('Sunbird UCI'!D2:D1005,"Watsup Chatbot",'Sunbird UCI'!F2:F1005,"P1",'Sunbird UCI'!R2:R1005,"Pass") -> 0 | J44: =COUNTIFS('Sunbird UCI'!D2:D1005,"Watsup Chatbot",'Sunbird UCI'!F2:F1005,"P2",'Sunbird UCI'!R2:R1005,"Pass") -> 0 | K44: =COUNTIFS('Sunbird UCI'!D2:D1005,"Watsup Chatbot",'Sunbird UCI'!F2:F1005,"P1",'Sunbird UCI'!R2:R1005,"Fail") -> 0 | L44: =COUNTIFS('Sunbird UCI'!D2:D1005,"Watsup Chatbot",'Sunbird UCI'!F2:F1005,"P2",'Sunbird UCI'!R2:R1005,"Fail") -> 0 | M44: =COUNTIFS('Sunbird UCI'!D2:D1005,"Watsup Chatbot",'Sunbird UCI'!F2:F1005,"P1",'Sunbird UCI'!R2:R1005,"Blocked") -> 0 | N44: =COUNTIFS('Sunbird UCI'!D2:D1005,"Watsup Chatbot",'Sunbird UCI'!F2:F1005,"P2",'Sunbird UCI'!R2:R1005,"Blocked") -> 0 | O44: =SUM(K44+M44) -> 0 | P44: =SUM(L44+N44) -> 0 | Q44: =(E44+I44)/C44 -> 1 | R44: =(F44+J44)/D44 -> #DIV/0!
A45: Groups | B45: Portal | C45: =COUNTIFS(Groups!D2:D1005,"Reference Learning Web App",Groups!F2:F1005,"P1") -> 108 | D45: =COUNTIFS(Groups!D2:D1005,"Reference Learning Web App",Groups!F2:F1005,"P2") -> 65 | E45: =COUNTIFS(Groups!D2:D1005,"Reference Learning Web App",Groups!F2:F1005,"P1",Groups!Q2:Q1005,"NA") -> 0 | F45: =COUNTIFS(Groups!D2:D1005,"Reference Learning Web App",Groups!F2:F1005,"P2",Groups!Q2:Q1005,"NA") -> 0 | G45: =C45-(I45+K45+M45+E45) -> 0 | H45: =D45-(J45+L45+N45+F45) -> 0 | I45: =COUNTIFS(Groups!D2:D1005,"Reference Learning Web App",Groups!F2:F1005,"P1",Groups!Q2:Q1005,"Pass") -> 108 | J45: =COUNTIFS(Groups!D2:D1005,"Reference Learning Web App",Groups!F2:F1005,"P2",Groups!Q2:Q1005,"Pass") -> 65 | K45: =COUNTIFS(Groups!D2:D1005,"Reference Learning Web App",Groups!F2:F1005,"P1",Groups!Q2:Q1005,"Fail") -> 0 | L45: =COUNTIFS(Groups!D2:D1005,"Reference Learning Web App",Groups!F2:F1005,"P2",Groups!Q2:Q1005,"Fail") -> 0 | M45: =COUNTIFS(Groups!D2:D1005,"Reference Learning Web App",Groups!F2:F1005,"P1",Groups!Q2:Q1005,"Blocked") -> 0 | N45: =COUNTIFS(Groups!D2:D1005,"Reference Learning Web App",Groups!F2:F1005,"P2",Groups!Q2:Q1005,"Blocked") -> 0 | O45: =SUM(K45+M45) -> 0 | P45: =SUM(L45+N45) -> 0 | Q45: =(E45+I45)/C45 -> 1 | R45: =(F45+J45)/D45 -> 1
B46: Mobile | C46: =COUNTIFS(Groups!D2:D1005,"Reference Learning Mobile App",Groups!F2:F1005,"P1") -> 42 | D46: =COUNTIFS(Groups!D2:D1005,"Reference Learning Mobile App",Groups!F2:F1005,"P2") -> 86 | E46: =COUNTIFS(Groups!D2:D1005,"Reference Learning Mobile App",Groups!F2:F1005,"P1",Groups!Q2:Q1005,"NA") -> 0 | F46: =COUNTIFS(Groups!D2:D1005,"Reference Learning Mobile App",Groups!F2:F1005,"P2",Groups!Q2:Q1005,"NA") -> 2 | G46: =C46-(I46+K46+M46+E46) -> 0 | H46: =D46-(J46+L46+N46+F46) -> 0 | I46: =COUNTIFS(Groups!D2:D1005,"Reference Learning Mobile App",Groups!F2:F1005,"P1",Groups!Q2:Q1005,"Pass") -> 42 | J46: =COUNTIFS(Groups!D2:D1005,"Reference Learning Mobile App",Groups!F2:F1005,"P2",Groups!Q2:Q1005,"Pass") -> 84 | K46: =COUNTIFS(Groups!D2:D1005,"Reference Learning Mobile App",Groups!F2:F1005,"P1",Groups!Q2:Q1005,"Fail") -> 0 | L46: =COUNTIFS(Groups!D2:D1005,"Reference Learning Mobile App",Groups!F2:F1005,"P2",Groups!Q2:Q1005,"Fail") -> 0 | M46: =COUNTIFS(Groups!D2:D1005,"Reference Learning Mobile App",Groups!F2:F1005,"P1",Groups!Q2:Q1005,"Blocked") -> 0 | N46: =COUNTIFS(Groups!D2:D1005,"Reference Learning Mobile App",Groups!F2:F1005,"P2",Groups!Q2:Q1005,"Blocked") -> 0 | O46: =SUM(K46+M46) -> 0 | P46: =SUM(L46+N46) -> 0 | Q46: =(E46+I46)/C46 -> 1 | R46: =(F46+J46)/D46 -> 1
A47: Accessibility | B47: Portal | C47: =COUNTIFS(Accessibility!D2:D1005,"Reference Learning Web App",Accessibility!F2:F1005,"P1") -> 73 | D47: =COUNTIFS(Accessibility!D2:D1005,"Reference Learning Web App",Accessibility!F2:F1005,"P2") -> 38 | E47: =COUNTIFS(Accessibility!D2:D1005,"Reference Learning Web App",Accessibility!F2:F1005,"P1",Accessibility!Q2:Q1005,"NA") -> 1 | F47: =COUNTIFS(Accessibility!D2:D1005,"Reference Learning Web App",Accessibility!F2:F1005,"P2",Accessibility!Q2:Q1005,"NA") -> 1 | G47: =C47-(I47+K47+M47+E47) -> 0 | H47: =D47-(J47+L47+N47+F47) -> 0 | I47: =COUNTIFS(Accessibility!D2:D1005,"Reference Learning Web App",Accessibility!F2:F1005,"P1",Accessibility!Q2:Q1005,"Pass") -> 72 | J47: =COUNTIFS(Accessibility!D2:D1005,"Reference Learning Web App",Accessibility!F2:F1005,"P2",Accessibility!Q2:Q1005,"Pass") -> 37 | K47: =COUNTIFS(Accessibility!D2:D1005,"Reference Learning Web App",Accessibility!F2:F1005,"P1",Accessibility!Q2:Q1005,"Failed") -> 0 | L47: =COUNTIFS(Accessibility!D2:D1005,"Reference Learning Web App",Accessibility!F2:F1005,"P2",Accessibility!Q2:Q1005,"Failed") -> 0 | M47: =COUNTIFS(Accessibility!D2:D1005,"Reference Learning Web App",Accessibility!F2:F1005,"P1",Accessibility!Q2:Q1005,"Blocked") -> 0 | N47: =COUNTIFS(Accessibility!D2:D1005,"Reference Learning Web App",Accessibility!F2:F1005,"P2",Accessibility!Q2:Q1005,"Blocked") -> 0 | O47: =SUM(K47+M47) -> 0 | P47: =SUM(L47+N47) -> 0 | Q47: =(E47+I47)/C47 -> 1 | R47: =(F47+J47)/D47 -> 1
B48: Mobile | C48: =COUNTIFS(Accessibility!D2:D1005,"Reference Learning Mobile App",Accessibility!F2:F1005,"P1") -> 65 | D48: =COUNTIFS(Accessibility!D2:D1005,"Reference Learning Mobile App",Accessibility!F2:F1005,"P2") -> 39 | E48: =COUNTIFS(Accessibility!D2:D1005,"Reference Learning Mobile App",Accessibility!F2:F1005,"P1",Accessibility!Q2:Q1005,"NA") -> 1 | F48: =COUNTIFS(Accessibility!D2:D1005,"Reference Learning Mobile App",Accessibility!F2:F1005,"P2",Accessibility!Q2:Q1005,"NA") -> 2 | G48: =C48-(I48+K48+M48+E48) -> 0 | H48: =D48-(J48+L48+N48+F48) -> 0 | I48: =COUNTIFS(Accessibility!D2:D1005,"Reference Learning Mobile App",Accessibility!F2:F1005,"P1",Accessibility!Q2:Q1005,"Pass") -> 64 | J48: =COUNTIFS(Accessibility!D2:D1005,"Reference Learning Mobile App",Accessibility!F2:F1005,"P2",Accessibility!Q2:Q1005,"Pass") -> 37 | K48: =COUNTIFS(Accessibility!D2:D1005,"Reference Learning Mobile App",Accessibility!F2:F1005,"P1",Accessibility!Q2:Q1005,"Fail") -> 0 | L48: =COUNTIFS(Accessibility!D2:D1005,"Reference Learning Mobile App",Accessibility!F2:F1005,"P2",Accessibility!Q2:Q1005,"Fail") -> 0 | M48: =COUNTIFS(Accessibility!D2:D1005,"Reference Learning Mobile App",Accessibility!F2:F1005,"P1",Accessibility!Q2:Q1005,"Blocked") -> 0 | N48: =COUNTIFS(Accessibility!D2:D1005,"Reference Learning Mobile App",Accessibility!F2:F1005,"P2",Accessibility!Q2:Q1005,"Blocked") -> 0 | O48: =SUM(K48+M48) -> 0 | P48: =SUM(L48+N48) -> 0 | Q48: =(E48+I48)/C48 -> 1 | R48: =(F48+J48)/D48 -> 1
B49: Offline Desktop | C49: =COUNTIFS(Accessibility!D2:D1005,"Reference Learning Desktop App",Accessibility!F2:F1005,"P1") -> 18 | D49: =COUNTIFS(Accessibility!D2:D1005,"Reference Learning Desktop App",Accessibility!F2:F1005,"P2") -> 16 | E49: =COUNTIFS(Accessibility!D2:D1005,"Reference Learning Desktop App",Accessibility!F2:F1005,"P1",Accessibility!Q2:Q1005,"NA") -> 1 | F49: =COUNTIFS(Accessibility!D2:D1005,"Reference Learning Desktop App",Accessibility!F2:F1005,"P2",Accessibility!Q2:Q1005,"NA") -> 1 | G49: =C49-(I49+K49+M49+E49) -> 0 | H49: =D49-(J49+L49+N49+F49) -> 0 | I49: =COUNTIFS(Accessibility!D2:D1005,"Reference Learning Desktop App",Accessibility!F2:F1005,"P1",Accessibility!Q2:Q1005,"Pass") -> 17 | J49: =COUNTIFS(Accessibility!D2:D1005,"Reference Learning Desktop App",Accessibility!F2:F1005,"P2",Accessibility!Q2:Q1005,"Pass") -> 15 | K49: =COUNTIFS(Accessibility!D2:D1005,"Reference Learning Desktop App",Accessibility!F2:F1005,"P1",Accessibility!Q2:Q1005,"Fail") -> 0 | L49: =COUNTIFS(Accessibility!D2:D1005,"Reference Learning Desktop App",Accessibility!F2:F1005,"P2",Accessibility!Q2:Q1005,"Fail") -> 0 | M49: =COUNTIFS(Accessibility!D2:D1005,"Reference Learning Desktop App",Accessibility!F2:F1005,"P1",Accessibility!Q2:Q1005,"Blocked") -> 0 | N49: =COUNTIFS(Accessibility!D2:D1005,"Reference Learning Desktop App",Accessibility!F2:F1005,"P2",Accessibility!Q2:Q1005,"Blocked") -> 0 | O49: =SUM(K49+M49) -> 0 | P49: =SUM(L49+N49) -> 0 | Q49: =(E49+I49)/C49 -> 1 | R49: =(F49+J49)/D49 -> 1
A50: Offline Scenarios | B50: Mobile | C50: =COUNTIFS('Offline Scenarios'!D2:D1005,"Reference Learning Mobile App",'Offline Scenarios'!F2:F1005,"P1") -> 6 | D50: =COUNTIFS('Offline Scenarios'!D2:D1005,"Reference Learning Mobile App",'Offline Scenarios'!F2:F1005,"P2") -> 11 | E50: =COUNTIFS('Offline Scenarios'!D2:D1005,"Reference Learning Mobile App",'Offline Scenarios'!F2:F1005,"P1",'Offline Scenarios'!Q2:Q1005,"NA") -> 0 | F50: =COUNTIFS('Offline Scenarios'!D2:D1005,"Reference Learning Mobile App",'Offline Scenarios'!F2:F1005,"P2",'Offline Scenarios'!Q2:Q1005,"NA") -> 3 | G50: =C50-(I50+K50+M50+E50) -> 0 | H50: =D50-(J50+L50+N50+F50) -> 0 | I50: =COUNTIFS('Offline Scenarios'!D2:D1005,"Reference Learning Mobile App",'Offline Scenarios'!F2:F1005,"P1",'Offline Scenarios'!Q2:Q1005,"Pass") -> 6 | J50: =COUNTIFS('Offline Scenarios'!D2:D1005,"Reference Learning Mobile App",'Offline Scenarios'!F2:F1005,"P2",'Offline Scenarios'!Q2:Q1005,"Pass") -> 8 | K50: =COUNTIFS('Offline Scenarios'!D2:D1005,"Reference Learning Mobile App",'Offline Scenarios'!F2:F1005,"P1",'Offline Scenarios'!Q2:Q1005,"Fail") -> 0 | L50: =COUNTIFS('Offline Scenarios'!D2:D1005,"Reference Learning Mobile App",'Offline Scenarios'!F2:F1005,"P2",'Offline Scenarios'!Q2:Q1005,"Fail") -> 0 | M50: =COUNTIFS('Offline Scenarios'!D2:D1005,"Reference Learning Mobile App",'Offline Scenarios'!F2:F1005,"P1",'Offline Scenarios'!Q2:Q1005,"Blocked") -> 0 | N50: =COUNTIFS('Offline Scenarios'!D2:D1005,"Reference Learning Mobile App",'Offline Scenarios'!F2:F1005,"P2",'Offline Scenarios'!Q2:Q1005,"Blocked") -> 0 | O50: =SUM(K50+M50) -> 0 | P50: =SUM(L50+N50) -> 0 | Q50: =(E50+I50)/C50 -> 1 | R50: =(F50+J50)/D50 -> 1
B51: Offline Desktop | C51: =COUNTIFS('Offline Scenarios'!D2:D1005,"Reference Learning Desktop App",'Offline Scenarios'!F2:F1005,"P1") -> 30 | D51: =COUNTIFS('Offline Scenarios'!D2:D1005,"Reference Learning Desktop App",'Offline Scenarios'!F2:F1005,"P2") -> 21 | E51: =COUNTIFS('Offline Scenarios'!D2:D1005,"Reference Learning Desktop App",'Offline Scenarios'!F2:F1005,"P1",'Offline Scenarios'!Q2:Q1005,"NA") -> 2 | F51: =COUNTIFS('Offline Scenarios'!D2:D1005,"Reference Learning Desktop App",'Offline Scenarios'!F2:F1005,"P2",'Offline Scenarios'!Q2:Q1005,"NA") -> 1 | G51: =C51-(I51+K51+M51+E51) -> 0 | H51: =D51-(J51+L51+N51+F51) -> 0 | I51: =COUNTIFS('Offline Scenarios'!D2:D1005,"Reference Learning Desktop App",'Offline Scenarios'!F2:F1005,"P1",'Offline Scenarios'!Q2:Q1005,"Pass") -> 28 | J51: =COUNTIFS('Offline Scenarios'!D2:D1005,"Reference Learning Desktop App",'Offline Scenarios'!F2:F1005,"P2",'Offline Scenarios'!Q2:Q1005,"Pass") -> 20 | K51: =COUNTIFS('Offline Scenarios'!D2:D1005,"Reference Learning Desktop App",'Offline Scenarios'!F2:F1005,"P1",'Offline Scenarios'!Q2:Q1005,"Fail") -> 0 | L51: =COUNTIFS('Offline Scenarios'!D2:D1005,"Reference Learning Desktop App",'Offline Scenarios'!F2:F1005,"P2",'Offline Scenarios'!Q2:Q1005,"Failed") -> 0 | M51: =COUNTIFS('Offline Scenarios'!D2:D1005,"Reference Learning Desktop App",'Offline Scenarios'!F2:F1005,"P1",'Offline Scenarios'!Q2:Q1005,"Blocked") -> 0 | N51: =COUNTIFS('Offline Scenarios'!D2:D1005,"Reference Learning Desktop App",'Offline Scenarios'!F2:F1005,"P2",'Offline Scenarios'!Q2:Q1005,"Blocked") -> 0 | O51: =SUM(K51+M51) -> 0 | P51: =SUM(L51+N51) -> 0 | Q51: =(E51+I51)/C51 -> 1 | R51: =(F51+J51)/D51 -> 1
A52: Portal/Desktop App Specific test cases | B52: Portal | C52: =COUNTIFS('PortalDesktop App Specific test'!D2:D1005,"Reference Learning Web App",'PortalDesktop App Specific test'!F2:F1005,"P1") -> 41 | D52: =COUNTIFS('PortalDesktop App Specific test'!D2:D1005,"Reference Learning Web App",'PortalDesktop App Specific test'!F2:F1005,"P2") -> 33 | E52: =COUNTIFS('PortalDesktop App Specific test'!D2:D1005,"Reference Learning Web App",'PortalDesktop App Specific test'!F2:F1005,"P1",'PortalDesktop App Specific test'!Q2:Q1005,"NA") -> 0 | F52: =COUNTIFS('PortalDesktop App Specific test'!D2:D1005,"Reference Learning Web App",'PortalDesktop App Specific test'!F2:F1005,"P2",'PortalDesktop App Specific test'!Q2:Q1005,"NA") -> 1 | G52: =C52-(I52+K52+M52+E52) -> 0 | H52: =D52-(J52+L52+N52+F52) -> 0 | I52: =COUNTIFS('PortalDesktop App Specific test'!D2:D1005,"Reference Learning Web App",'PortalDesktop App Specific test'!F2:F1005,"P1",'PortalDesktop App Specific test'!Q2:Q1005,"Pass") -> 41 | J52: =COUNTIFS('PortalDesktop App Specific test'!D2:D1005,"Reference Learning Web App",'PortalDesktop App Specific test'!F2:F1005,"P2",'PortalDesktop App Specific test'!Q2:Q1005,"Pass") -> 32 | K52: =COUNTIFS('PortalDesktop App Specific test'!D2:D1005,"Reference Learning Web App",'PortalDesktop App Specific test'!F2:F1005,"P1",'PortalDesktop App Specific test'!Q2:Q1005,"Fail") -> 0 | L52: =COUNTIFS('PortalDesktop App Specific test'!D2:D1005,"Reference Learning Web App",'PortalDesktop App Specific test'!F2:F1005,"P2",'PortalDesktop App Specific test'!Q2:Q1005,"Fail") -> 0 | M52: =COUNTIFS('PortalDesktop App Specific test'!D2:D1005,"Reference Learning Web App",'PortalDesktop App Specific test'!F2:F1005,"P1",'PortalDesktop App Specific test'!Q2:Q1005,"Blocked") -> 0 | N52: =COUNTIFS('PortalDesktop App Specific test'!D2:D1005,"Reference Learning Web App",'PortalDesktop App Specific test'!F2:F1005,"P2",'PortalDesktop App Specific test'!Q2:Q1005,"Blocked") -> 0 | O52: =SUM(K52+M52) -> 0 | P52: =SUM(L52+N52) -> 0 | Q52: =(E52+I52)/C52 -> 1 | R52: =(F52+J52)/D52 -> 1
B53: Offline Desktop | C53: =COUNTIFS('PortalDesktop App Specific test'!D2:D1005,"Reference Learning Desktop App",'PortalDesktop App Specific test'!F2:F1005,"P1") -> 40 | D53: =COUNTIFS('PortalDesktop App Specific test'!D2:D1005,"Reference Learning Desktop App",'PortalDesktop App Specific test'!F2:F1005,"P2") -> 68 | E53: =COUNTIFS('PortalDesktop App Specific test'!D2:D1005,"Reference Learning Desktop App",'PortalDesktop App Specific test'!F2:F1005,"P1",'PortalDesktop App Specific test'!Q2:Q1005,"NA") -> 5 | F53: =COUNTIFS('PortalDesktop App Specific test'!D2:D1005,"Reference Learning Desktop App",'PortalDesktop App Specific test'!F2:F1005,"P2",'PortalDesktop App Specific test'!Q2:Q1005,"NA") -> 2 | G53: =C53-(I53+K53+M53+E53) -> 0 | H53: =D53-(J53+L53+N53+F53) -> 0 | I53: =COUNTIFS('PortalDesktop App Specific test'!D2:D1005,"Reference Learning Desktop App",'PortalDesktop App Specific test'!F2:F1005,"P1",'PortalDesktop App Specific test'!Q2:Q1005,"Pass") -> 35 | J53: =COUNTIFS('PortalDesktop App Specific test'!D2:D1005,"Reference Learning Desktop App",'PortalDesktop App Specific test'!F2:F1005,"P2",'PortalDesktop App Specific test'!Q2:Q1005,"Pass") -> 66 | K53: =COUNTIFS('PortalDesktop App Specific test'!D2:D1005,"Reference Learning Desktop App",'PortalDesktop App Specific test'!F2:F1005,"P1",'PortalDesktop App Specific test'!Q2:Q1005,"Fail") -> 0 | L53: =COUNTIFS('PortalDesktop App Specific test'!D2:D1005,"Reference Learning Desktop App",'PortalDesktop App Specific test'!F2:F1005,"P2",'PortalDesktop App Specific test'!Q2:Q1005,"Fail") -> 0 | M53: =COUNTIFS('PortalDesktop App Specific test'!D2:D1005,"Reference Learning Desktop App",'PortalDesktop App Specific test'!F2:F1005,"P1",'PortalDesktop App Specific test'!Q2:Q1005,"Blocked") -> 0 | N53: =COUNTIFS('PortalDesktop App Specific test'!D2:D1005,"Reference Learning Desktop App",'PortalDesktop App Specific test'!F2:F1005,"P2",'PortalDesktop App Specific test'!Q2:Q1005,"Blocked") -> 0 | O53: =SUM(K53+M53) -> 0 | P53: =SUM(L53+N53) -> 0 | Q53: =(E53+I53)/C53 -> 1 | R53: =(F53+J53)/D53 -> 1
A54: 7.0 NF Test Cases | B54: Portal/Mobile/Offline Desktop | C54: =COUNTIFS('7.0 New Features'!K2:K1005,"P1") -> 312 | D54: =COUNTIFS('7.0 New Features'!K2:K1005,"P2") -> 299 | E54: =COUNTIFS('7.0 New Features'!K2:K1005,"P1", '7.0 New Features'!U2:U1005,"NA") -> 61 | F54: =COUNTIFS('7.0 New Features'!K2:K1005,"P2", '7.0 New Features'!U2:U1005,"NA") -> 34 | G54: =C54-(I54+K54+M54+E54) -> 0 | H54: =D54-(J54+L54+N54+F54) -> 0 | I54: =COUNTIFS('7.0 New Features'!K2:K1005,"P1", '7.0 New Features'!U2:U1005,"Pass") -> 251 | J54: =COUNTIFS('7.0 New Features'!K2:K1005,"P2", '7.0 New Features'!U2:U1005,"Pass") -> 265 | K54: =COUNTIFS('7.0 New Features'!K2:K1005,"P1", '7.0 New Features'!U2:U1005,"Fail") -> 0 | L54: =COUNTIFS('7.0 New Features'!K2:K1005,"P2", '7.0 New Features'!U2:U1005,"Fail") -> 0 | M54: =COUNTIFS('7.0 New Features'!K2:K1005,"P1", '7.0 New Features'!U2:U1005,"Blocked") -> 0 | N54: =COUNTIFS('7.0 New Features'!K2:K1005,"P2", '7.0 New Features'!U2:U1005,"Blocked") -> 0 | O54: =SUM(K54+M54) -> 0 | P54: =SUM(L54+N54) -> 0 | Q54: =(E54+I54)/C54 -> 1 | R54: =(F54+J54)/D54 -> 1
A55: Total | C55: =Sum(C4:C54) -> 3195 | D55: =Sum(D4:D54) -> 2423 | E55: =Sum(E4:E54) -> 222 | F55: =Sum(F4:F54) -> 152 | G55: =Sum(G4:G54) -> 0 | H55: =Sum(H4:H54) -> 0 | I55: =Sum(I4:I54) -> 2973 | J55: =Sum(J4:J54) -> 2271 | ... N55: =Sum(N4:N54) -> 0 | O55: =SUM(O4:O54) -> 0 | P55: =SUM(P4:P54) -> 0 | Q55: =(E55+I55)/C55 -> 1 | R55: =(F55+J55)/D55 -> 1
A61: Manage Learn Regression Dashboard
A62: ED Component | B62: Portal/Mobile app | C62: Total | E62: Not Applicable | G62: To be Executed | I62: Passed | K62: Fail | M62: Blocked | O62: For retest (Failed & Blocked) | Q62: Execution % circle wise
C63: P1 | D63: P2 | E63: P1 | F63: P2 | G63: P1 | H63: P2 | I63: P1 | J63: P2 | K63: P1 | L63: P2 | M63: P1 | N63: P2 | O63: P1 | P63: P2 | Q63: P1 | R63: P2
A64: Manage Learn-Portal | B64: Portal | C64: =COUNTIFS('Manage Learn-Portal'!F2:F1005,"Web portal",'Manage Learn-Portal'!E2:E1005,"P1") -> 642 | D64: =COUNTIFS('Manage Learn-Portal'!F2:F1005,"Web portal",'Manage Learn-Portal'!E2:E1005,"P2") -> 71 | E64: =COUNTIFS('Manage Learn-Portal'!F2:F1005,"Web portal",'Manage Learn-Portal'!E2:E1005,"P1",'Manage Learn-Portal'!P2:P1005,"NA") -> 2 | F64: =COUNTIFS('Manage Learn-Portal'!F2:F1005,"Web portal",'Manage Learn-Portal'!E2:E1005,"P2",'Manage Learn-Portal'!P2:P1005,"NA") -> 0 | G64: =C64-(E64+I64+O64) -> 0 | H64: =D64-(F64+J64+P64) -> 0 | I64: =COUNTIFS('Manage Learn-Portal'!F2:F1005,"Web portal",'Manage Learn-Portal'!E2:E1005,"P1",'Manage Learn-Portal'!P2:P1005,"Pass") -> 640 | J64: =COUNTIFS('Manage Learn-Portal'!F2:F1005,"Web portal",'Manage Learn-Portal'!E2:E1005,"P2",'Manage Learn-Portal'!P2:P1005,"Pass") -> 71 | K64: =COUNTIFS('Manage Learn-Portal'!F2:F1005,"Web portal",'Manage Learn-Portal'!E2:E1005,"P1",'Manage Learn-Portal'!P2:P1005,"Fail") -> 0 | L64: =COUNTIFS('Manage Learn-Portal'!F2:F1005,"Web portal",'Manage Learn-Portal'!E2:E1005,"P2",'Manage Learn-Portal'!P2:P1005,"Fail") -> 0 | M64: =COUNTIFS('Manage Learn-Portal'!F2:F1005,"Web portal",'Manage Learn-Portal'!E2:E1005,"P1",'Manage Learn-Portal'!P2:P1005,"Blocked") -> 0 | N64: =COUNTIFS('Manage Learn-Portal'!F2:F1005,"Web portal",'Manage Learn-Portal'!E2:E1005,"P2",'Manage Learn-Portal'!P2:P1005,"Blocked") -> 0 | O64: =SUM(K64+M64) -> 0 | P64: =SUM(L64+N64) -> 0 | Q64: =(E64+I64)/C64 -> 1 | R64: =(F64+J64)/D64 -> 1
A65: Manage Learn-Mobile | B65: Mobile | C65: =COUNTIFS('Manage Learn-Mobile'!F2:F1005,"Mobile",'Manage Learn-Mobile'!E2:E1005,"P1") -> 786 | D65: =COUNTIFS('Manage Learn-Mobile'!F2:F1005,"Mobile",'Manage Learn-Mobile'!E2:E1005,"P2") -> 163 | E65: =COUNTIFS('Manage Learn-Mobile'!F2:F1005,"Mobile",'Manage Learn-Mobile'!E2:E1005,"P1",'Manage Learn-Mobile'!P2:P1005,"NA") -> 14 | F65: =COUNTIFS('Manage Learn-Mobile'!F2:F1005,"Mobile",'Manage Learn-Mobile'!E2:E1005,"P2",'Manage Learn-Mobile'!P2:P1005,"NA") -> 5 | G65: =C65-(E65+I65+O65) -> 0 | H65: =D65-(F65+J65+P65) -> 0 | I65: =COUNTIFS('Manage Learn-Mobile'!F2:F1005,"Mobile",'Manage Learn-Mobile'!E2:E1005,"P1",'Manage Learn-Mobile'!P2:P1005,"Pass") -> 772 | J65: =COUNTIFS('Manage Learn-Mobile'!F2:F1005,"Mobile",'Manage Learn-Mobile'!E2:E1005,"P2",'Manage Learn-Mobile'!P2:P1005,"Pass") -> 158 | K65: =COUNTIFS('Manage Learn-Mobile'!F2:F1005,"Mobile",'Manage Learn-Mobile'!E2:E1005,"P1",'Manage Learn-Mobile'!P2:P1005,"Fail") -> 0 | L65: =COUNTIFS('Manage Learn-Mobile'!F2:F1005,"Mobile",'Manage Learn-Mobile'!E2:E1005,"P2",'Manage Learn-Mobile'!P2:P1005,"Fail") -> 0 | M65: =COUNTIFS('Manage Learn-Mobile'!F2:F1005,"Mobile",'Manage Learn-Mobile'!E2:E1005,"P1",'Manage Learn-Mobile'!P2:P1005,"Blocked") -> 0 | N65: =COUNTIFS('Manage Learn-Mobile'!F2:F1005,"Mobile",'Manage Learn-Mobile'!E2:E1005,"P2",'Manage Learn-Mobile'!P2:P1005,"Blocked") -> 0 | O65: =SUM(K65+M65) -> 0 | P65: =SUM(L65+N65) -> 0 | Q65: =(E65+I65)/C65 -> 1 | R65: =(F65+J65)/D65 -> 1
A66: Manage Learn | B66: Mobile & Portal | C66: =COUNTIFS('Manage Learn-Mobile'!F2:F1005,"Mobile & Portal",'Manage Learn-Mobile'!E2:E1005,"P1") -> 113 | D66: =COUNTIFS('Manage Learn-Mobile'!F2:F1005,"Mobile & Portal",'Manage Learn-Mobile'!E2:E1005,"P2") -> 17 | E66: =COUNTIFS('Manage Learn-Mobile'!F2:F1005,"Mobile & Portal",'Manage Learn-Mobile'!E2:E1005,"P1",'Manage Learn-Mobile'!P2:P1005,"NA") -> 2 | F66: =COUNTIFS('Manage Learn-Mobile'!F2:F1005,"Mobile & Portal",'Manage Learn-Mobile'!E2:E1005,"P2",'Manage Learn-Mobile'!P2:P1005,"NA") -> 0 | G66: =C66-(E66+I66+O66) -> 0 | H66: =D66-(F66+J66+P66) -> 0 | I66: =COUNTIFS('Manage Learn-Mobile'!F2:F1005,"Mobile & Portal",'Manage Learn-Mobile'!E2:E1005,"P1",'Manage Learn-Mobile'!P2:P1005,"Pass") -> 111 | J66: =COUNTIFS('Manage Learn-Mobile'!F2:F1005,"Mobile & Portal",'Manage Learn-Mobile'!E2:E1005,"P2",'Manage Learn-Mobile'!P2:P1005,"Pass") -> 17 | K66: =COUNTIFS('Manage Learn-Mobile'!F2:F1005,"Mobile & Portal",'Manage Learn-Mobile'!E2:E1005,"P1",'Manage Learn-Mobile'!P2:P1005,"Fail") -> 0 | L66: =COUNTIFS('Manage Learn-Mobile'!F2:F1005,"Mobile & Portal",'Manage Learn-Mobile'!E2:E1005,"P2",'Manage Learn-Mobile'!P2:P1005,"Fail") -> 0 | M66: =COUNTIFS('Manage Learn-Mobile'!F2:F1005,"Mobile & Portal",'Manage Learn-Mobile'!E2:E1005,"P1",'Manage Learn-Mobile'!P2:P1005,"Blocked") -> 0 | N66: =COUNTIFS('Manage Learn-Mobile'!F2:F1005,"Mobile & Portal",'Manage Learn-Mobile'!E2:E1005,"P2",'Manage Learn-Mobile'!P2:P1005,"Blocked") -> 0 | O66: =SUM(K66+M66) -> 0 | P66: =SUM(L66+N66) -> 0 | Q66: =(E66+I66)/C66 -> 1 | R66: =(F66+J66)/D66 -> 1
A67: Total | C67: =SUM(C64:C66) -> 1541 | D67: =SUM(D64:D66) -> 251 | E67: =SUM(E64:E66) -> 18 | F67: =SUM(F64:F66) -> 5 | G67: =SUM(G64:G66) -> 0 | H67: =SUM(H64:H66) -> 0 | I67: =SUM(I64:I66) -> 1523 | J67: =SUM(J64:J66) -> 246 | ... P67: =SUM(P64:P66) -> 0 | Q67: =(E67+I67)/C67 -> 1 | R67: =(F67+J67)/D67 -> 1
F71: OverAll | I71: Without ML | L71: only ML
A72: Solution | B72: Executed | C72: Pending | D72: Total | F72: % Pending Overall | G72: % Executed Overall | I72: % Pending Overall | J72: % Executed Overall | L72: % Pending Overall | M72: % Executed Overall
A73: Sunbird ED | B73: =(Sum(E4:E54)+Sum(F4:F54))+Sum(I4:I54)+Sum(J4:J54) -> 5618 | C73: =(Sum(G4:G54)+Sum(H4:H54))+Sum(O4:O54)+Sum(P4:P54) -> 0 | D73: =SUM(B73:C73) -> 5618 | F73: =C75/D75*100 -> 0 | G73: =B75/D75*100 -> 100 | I73: =C73/D73*100 -> 0 | J73: =B73/D73*100 -> 100 | L73: =C74/D74*100 -> 0 | M73: =B74/D74*100 -> 100
A74: Manage Learn | B74: =sum(E64:E66)+SUM(F64:F66)+SUM(I64:I66)+SUM(J64:J66) -> 1792 | C74: =sum(G64:G66)+SUM(H64:H66)+SUM(O64:O66)+SUM(P64:P66) -> 0 | D74: =SUM(B74:C74) -> 1792
A75: Total | B75: =SUM(B73:B74) -> 7410 | C75: =SUM(C73:C74) -> 0 | D75: =SUM(D73:D74) -> 7410
A79: Component | C79: Known Bug | D79: Deprecated | E79: Backend Configurations
A80: WorkSpace | B80: Portal | C80: =COUNTIF(Workspace!V2:V1005,"Known Bug") -> 21 | D80: =COUNTIF(Workspace!V2:V1005,"Deprecated") -> 14 | E80: =COUNTIF(Workspace!V2:V1005,"Backend Configurations") -> 0
A81: Login | B81: Portal | C81: =COUNTIFS(Login!D2:D1005,"Reference Learning Web App",Login!T2:T1005,"Known Bug") -> 1 | D81: =COUNTIFS(Login!D2:D1005,"Reference Learning Web App",Login!T2:T1005,"Deprecated") -> 5 | E81: -
B82: Mobile | C82: =COUNTIFS(Login!D2:D1005,"Reference Learning Mobile App",Login!T2:T1005,"Known Bug") -> 5 | D82: =COUNTIFS(Login!D2:D1005,"Reference Learning Mobile App",Login!T2:T1005,"Deprecated") -> 0 | E82: -
B83: Offline Desktop | C83: =COUNTIFS(Login!D2:D1005,"Reference Learning Desktop App",Login!T2:T1005,"Known Bug") -> 0 | D83: =COUNTIFS(Login!D2:D1005,"Reference Learning Desktop App",Login!T2:T1005,"Deprecated") -> 0 | E83: -
A84: Course Consumption | B84: Portal | C84: =COUNTIFS('Course Consumption'!D2:D1005,"Reference Learning Web App",'Course Consumption'!T2:T1005,"Known Bug") -> 4 | D84: =COUNTIFS('Course Consumption'!D2:D1005,"Reference Learning Web App",'Course Consumption'!T2:T1005,"Deprecated") -> 5 | E84: -
B85: Mobile | C85: =COUNTIFS('Course Consumption'!D2:D1005,"Reference Learning Mobile App",'Course Consumption'!T2:T1005,"Known Bug") -> 1 | D85: =COUNTIFS('Course Consumption'!D2:D1005,"Reference Learning Mobile App",'Course Consumption'!T2:T1005,"Deprecated") -> 1 | E85: -
B86: Offline Desktop | C86: =COUNTIFS('Course Consumption'!D2:D1005,"Reference Learning Desktop App",'Course Consumption'!T2:T1005,"Known Bug") -> 1 | D86: =COUNTIFS('Course Consumption'!D2:D1005,"Reference Learning Desktop App",'Course Consumption'!T2:T1005,"Deprecated") -> 3 | E86: -
A87: Batch Creation | B87: Portal | C87: =COUNTIFS('Batch Creation'!D2:D1005,"Reference Learning Web App",'Batch Creation'!S2:S1005,"Known Bug") -> 0 | D87: =COUNTIFS('Batch Creation'!D2:D1005,"Reference Learning Web App",'Batch Creation'!S2:S1005,"Deprecated") -> 0 | E87: -
A88: Digital Textbook Consumption | B88: Portal | C88: =COUNTIFS('Digital Textbook Consumption'!D2:D1005,"Reference Learning Web App",'Digital Textbook Consumption'!S2:S1005,"Known Bug") -> 0 | D88: =COUNTIFS('Digital Textbook Consumption'!D2:D1005,"Reference Learning Web App",'Digital Textbook Consumption'!S2:S1005,"Deprecated") -> 0 | E88: -
B89: Mobile | C89: =COUNTIFS('Digital Textbook Consumption'!D2:D1005,"Reference Learning Mobile App",'Digital Textbook Consumption'!S2:S1005,"Known Bug") -> 5 | D89: =COUNTIFS('Digital Textbook Consumption'!D2:D1005,"Reference Learning Mobile App",'Digital Textbook Consumption'!S2:S1005,"Deprecated") -> 0 | E89: -
B90: Offline Desktop | C90: =COUNTIFS('Digital Textbook Consumption'!D2:D1005,"Reference Learning Desktop App",'Digital Textbook Consumption'!S2:S1005,"Known Bug") -> 2 | D90: =COUNTIFS('Digital Textbook Consumption'!D2:D1005,"Reference Learning Desktop App",'Digital Textbook Consumption'!S2:S1005,"Deprecated") -> 2 | E90: -
A91: Content Consumption | B91: Portal | C91: =COUNTIFS('Content Consumption'!D2:D1005,"Reference Learning Web App",'Content Consumption'!T2:T1005,"Known Bug") -> 1 | D91: =COUNTIFS('Content Consumption'!D2:D1005,"Reference Learning Web App",'Content Consumption'!T2:T1005,"Deprecated") -> 0 | E91: -
B92: Mobile | C92: =COUNTIFS('Content Consumption'!D2:D1005,"Reference Learning Mobile App",'Content Consumption'!T2:T1005,"Known Bug") -> 1 | D92: =COUNTIFS('Content Consumption'!D2:D1005,"Reference Learning Mobile App",'Content Consumption'!T2:T1005,"Deprecated") -> 0 | E92: -
B93: Offline Desktop | C93: =COUNTIFS('Content Consumption'!D2:D1005,"Reference Learning Desktop App",'Content Consumption'!T2:T1005,"Known Bug") -> 0 | D93: =COUNTIFS('Content Consumption'!D2:D1005,"Reference Learning Desktop App",'Content Consumption'!T2:T1005,"Deprecated") -> 0 | E93: -
A94: Profile | B94: Portal | C94: =COUNTIFS(Profile!D2:D1005,"Reference Learning Web App",Profile!T2:T1005,"Known Bug") -> 0 | D94: =COUNTIFS(Profile!D2:D1005,"Reference Learning Web App",Profile!T2:T1005,"Deprecated") -> 1 | E94: -
B95: Mobile | C95: =COUNTIFS(Profile!D2:D1005,"Reference Learning Mobile App",Profile!T2:T1005,"Known Bug") -> 0 | D95: =COUNTIFS(Profile!D2:D1005,"Reference Learning Mobile App",Profile!T2:T1005,"Deprecated") -> 0 | E95: -
B96: Offline Desktop | C96: =COUNTIFS(Profile!D2:D1005,"Reference Learning Desktop App",Profile!T2:T1005,"Known Bug") -> 3 | D96: =COUNTIFS(Profile!D2:D1005,"Reference Learning Desktop App",Profile!T2:T1005,"Deprecated") -> 0 | E96: -
A97: Course reports | B97: Portal | C97: =COUNTIFS('Course reports'!D2:D1005,"Reference Learning Web App",'Course reports'!S2:S1005,"Known Bug") -> 0 | D97: =COUNTIFS('Course reports'!D2:D1005,"Reference Learning Web App",'Course reports'!S2:S1005,"Deprecated") -> 0 | E97: -
B98: Mobile | C98: =COUNTIFS('Course reports'!D2:D1005,"Reference Learning Mobile App",'Course reports'!S2:S1005,"Known Bug") -> 0 | D98: =COUNTIFS('Course reports'!D2:D1005,"Reference Learning Mobile App",'Course reports'!S2:S1005,"Deprecated") -> 0 | E98: -
A99: QUML | B99: Portal | C99: =COUNTIFS(QUML!D2:D1005,"Reference Learning Web App",QUML!T2:T1005,"Known Bug") -> 3 | D99: =COUNTIFS(QUML!D2:D1005,"Reference Learning Web App",QUML!T2:T1005,"Deprecated") -> 1 | E99: -
B100: Mobile | C100: =COUNTIFS(QUML!D2:D1005,"Reference Learning Mobile App",QUML!T2:T1005,"Known Bug") -> 1 | D100: =COUNTIFS(QUML!D2:D1005,"Reference Learning Mobile App",QUML!T2:T1005,"Deprecated") -> 0 | E100: -
B101: Offline Desktop | C101: =COUNTIFS(QUML!D2:D1005,"Reference Learning Desktop App",QUML!T2:T1005,"Known Bug") -> 0 | D101: =COUNTIFS(QUML!D2:D1005,"Reference Learning Desktop App",QUML!T2:T1005,"Deprecated") -> 0 | E101: -
A102: Mobile specific Test Cases | B102: Mobile | C102: =COUNTIFS('Mobile specific Test Cases'!D2:D1005,"Reference Learning Mobile App",'Mobile specific Test Cases'!S2:S1005,"Known Bug") -> 0 | D102: =COUNTIFS('Mobile specific Test Cases'!D2:D1005,"Reference Learning Mobile App",'Mobile specific Test Cases'!S2:S1005,"Deprecated") -> 1 | E102: -
A103: Mobile configurability | B103: Mobile | C103: =COUNTIFS('Mobile configurability'!D2:D1005,"Reference Learning Mobile App",'Mobile configurability'!S2:S1005,"Known Bug") -> 0 | D103: =COUNTIFS('Mobile configurability'!D2:D1005,"Reference Learning Mobile App",'Mobile configurability'!S2:S1005,"Deprecated") -> 1 | E103: -
A104: Org admin reports | B104: Portal | C104: =COUNTIFS('Org admin reports'!D2:D1005,"Reference Learning Web App",'Org admin reports'!S2:S1005,"Known Bug") -> 0 | D104: =COUNTIFS('Org admin reports'!D2:D1005,"Reference Learning Web App",'Org admin reports'!S2:S1005,"Deprecated") -> 5 | E104: -
B105: Mobile | C105: =COUNTIFS('Org admin reports'!D2:D1005,"Reference Learning Mobile App",'Org admin reports'!S2:S1005,"Known Bug") -> 0 | D105: =COUNTIFS('Org admin reports'!D2:D1005,"Reference Learning Mobile App",'Org admin reports'!S2:S1005,"Deprecated") -> 0 | E105: -
A106: QR code | B106: Portal | C106: =COUNTIFS('QR code'!D2:D1005,"Reference Learning Web App",'QR code'!T2:T1005,"Known Bug") -> 1 | D106: =COUNTIFS('QR code'!D2:D1005,"Reference Learning Web App",'QR code'!T2:T1005,"Deprecated") -> 2 | E106: =COUNTIFS('QR code'!C2:C1005,"Reference Learning Web App",'QR code'!T2:T1005,"Backend Configuration") -> 0
B107: Mobile | C107: =COUNTIFS('QR code'!D2:D1005,"Reference Learning Mobile App",'QR code'!T2:T1005,"Known Bug") -> 0 | D107: =COUNTIFS('QR code'!D2:D1005,"Reference Learning Mobile App",'QR code'!T2:T1005,"Deprecated") -> 9 | E107: =COUNTIFS('QR code'!C2:C1005,"Reference Learning Mobile App",'QR code'!T2:T1005,"Backend Configuration") -> 0
A108: Portal/ Desktop App Configurability | B108: Portal | C108: =COUNTIFS('Portal Desktop App Configurabil'!D2:D1005,"Reference Learning Web App",'Portal Desktop App Configurabil'!S2:S1005,"Known Bug") -> 1 | D108: =COUNTIFS('Portal Desktop App Configurabil'!D2:D1005,"Reference Learning Web App",'Portal Desktop App Configurabil'!S2:S1005,"Deprecated") -> 0 | E108: -
B109: Offline Desktop | C109: =COUNTIFS('Portal Desktop App Configurabil'!D2:D1005,"Reference Learning Desktop App",'Portal Desktop App Configurabil'!S2:S1005,"Known Bug") -> 0 | D109: =COUNTIFS('Portal Desktop App Configurabil'!D2:D1005,"Reference Learning Desktop App",'Portal Desktop App Configurabil'!S2:S1005,"Deprecated") -> 0 | E109: -
A110: Sunbird UCI | B110: Portal | C110: =COUNTIFS('Sunbird UCI'!D2:D1005,"Portal tara",'Sunbird UCI'!T2:T1005,"Known Bug") -> 1 | D110: =COUNTIFS('Sunbird UCI'!D2:D1005,"Portal tara",'Sunbird UCI'!T2:T1005,"Deprecated") -> 0 | E110: -
B111: Mobile | C111: =COUNTIFS('Sunbird UCI'!D2:D1005,"Mobile tara",'Sunbird UCI'!T2:T1005,"Known Bug") -> 0 | D111: =COUNTIFS('Sunbird UCI'!D2:D1005,"Mobile tara",'Sunbird UCI'!T2:T1005,"Deprecated") -> 0 | E111: -
...

Sheet R7.0 Scope
A1: ISSUE TYPE | B1: JIRA ID | C1: SUMMARY | D1: SPRINT | E1: BUILDING BLOCKS | F1: LATEST COMPONENT | G1: TO BE COVERED IN REG? | H1: QA_REQUIRED / NOT | I1: TC NEEDED | J1: TC WRITTEN? | K1: Verification Status (Sunbird ED Env) | L1: VERIFIED BY | M1: STATUS | N1: OPEN DEFECTS | O1: REMARKS | P1: CONTRIBUTOR
A2: Minor-Enhancement | B2: IQ-393 | C2: Error standardisation | D2: 6.0.0 | E2: Sunbird Inquiry | F2: Question and Question Set Service | H2: QA_Not_Required | I2: No | J2: No
A3: Minor-Enhancement | B3: IQ-385 | C3: inQuiry V2 API Implementation | D3: 6.0.0 | E3: Sunbird Inquiry | F3: Question and Question Set Service | H3: QA_Required | I3: Yes | J3: Yes | K3: Yes | L3: Naveen | M3: Pass
A4: Minor-Enhancement | B4: IQ-297 | C4: Player changes to ensure QuML compliance | D4: 6.0.0 | E4: Sunbird Inquiry | F4: Question Set Editor | G4: Yes | H4: QA_Required | I4: No | J4: No
A5: Minor-Enhancement | B5: IQ-296 | C5: Editor changes to ensure QuML compliance | D5: 6.0.0 | E5: Sunbird Inquiry | F5: Question Set Editor | H5: QA_Required | I5: Yes | J5: Yes | K5: Yes | L5: Naveen | M5: Pass
A6: Minor-Enhancement | B6: IQ-272 | C6: Sunbird Inquiry - QuML Design Changes to ensure QuML complaince | D6: 6.0.0 | E6: Sunbird Inquiry | F6: Question Set Editor | H6: QA_Not_Required | I6: No | J6: No
A7: Minor-Enhancement | B7: IQ-443 | C7: Documentation | D7: 6.0.0 | E7: Sunbird Inquiry | F7: Question and Question Set Service | H7: QA_Not_Required | I7: No | J7: No
A8: Minor-Enhancement | B8: IQ-412 | C8: Integrate latest common form library in editor | D8: 6.0.0 | E8: Sunbird Inquiry | F8: Question Set Editor | G8: Yes | H8: QA_Required | I8: No | J8: No
A9: Minor-Enhancement | B9: IQ-414 | C9: Editor/Player: Update the Node version from 14 to 16 | D9: 6.0.0 | E9: Sunbird Inquiry | F9: Question Set Editor | H9: QA_Not_Required | I9: No | J9: No
A10: Bug | B10: IQ-148 | C10: Footer is not aligned Properly when console is open. | D10: 6.0.0 | E10: Sunbird Inquiry | F10: Question Set Editor | H10: QA_Required | I10: Yes | J10: Yes | K10: Yes | L10: Naveen | M10: Pass
A11: Minor-Enhancement | B11: IQ-411 | C11: Integration of QuML player web component into the sunbird resource library | D11: 6.0.0 | E11: Sunbird Inquiry | F11: Question Set Editor | G11: Yes | H11: QA_Required | I11: No | J11: No
A12: Minor-Enhancement | B12: IQ-468 | C12: Remove hard coding in the QuML Player | D12: 6.0.0 | E12: Sunbird Inquiry | F12: Question Set Editor | H12: QA_Not_Required | I12: No | J12: No
A13: Minor-Enhancement | B13: IQ-421 | C13: Remove hard coding of content organisation and target frameworks to point to a specific framework | D13: 6.0.0 | E13: Sunbird Inquiry | F13: Question Set Editor | G13: Yes | H13: QA_Required | I13: No | J13: No
A14: Minor-Enhancement | B14: IQ-413 | C14: Mark it video, PDF, and EPUB player as optional in the resource library | D14: 6.0.0 | E14: Sunbird Inquiry | F14: Question Set Editor | G14: Yes | H14: QA_Required | I14: No | J14: No
A15: Minor-Enhancement | B15: IQ-410 | C15: Integration of QuML player web component into the editor | D15: 6.0.0 | E15: Sunbird Inquiry | F15: Question Set Editor | G15: Yes | H15: QA_Required | I15: No | J15: No
A16: Bug | B16: IQ-337 | C16: User is not able to send for review when reset the set max and warning timer for question set | D16: 6.0.0 | E16: Sunbird Inquiry | F16: Question Set Editor | H16: QA_Required | I16: Yes | J16: Yes | K16: Yes | L16: Naveen | M16: Pass
A17: Minor-Enhancement | B17: IQ-480 | C17: Integrate V2 player and Editor in the inQuiry Portal | D17: 6.0.0 | E17: Sunbird Inquiry | F17: Question Set Editor | H17: QA_Not_Required | I17: No | J17: No
A18: Bug | B18: IQ-469 | C18: User is able to see all the fields editable in review mode | D18: 6.0.0 | E18: Sunbird Inquiry | F18: Question Set Editor | H18: QA_Required | I18: Yes | J18: Yes | K18: Yes | L18: Naveen | M18: Pass
A19: Minor-Enhancement | B19: IQ-442 | C19: Integrate latest common form library in editor | D19: 6.0.0 | E19: Sunbird Inquiry | F19: Question Set Editor | G19: Yes | H19: QA_Required | I19: No | J19: No
A20: Bug | B20: IQ-378 | C20: Zoom icon and show answer button are overlapping for the subjective question with image | D20: 6.0.0 | E20: Sunbird Inquiry | F20: Question Set Editor | H20: QA_Required | I20: Yes | J20: Yes | K20: Yes | L20: Naveen | M20: Pass
A21: Bug | B21: IQ-520 | C21: User is not able to get error message if trying to add more question than the Prescribed Limit | D21: 6.1.0 | E21: Sunbird Inquiry | F21: Question and Question Set Service | H21: QA_Required | I21: Yes | J21: Yes | K21: Yes | L21: Naveen | M21: Pass
A22: Bug | B22: IQ-516 | C22: X" icon is not aligned properly when user clicks on zoom icon | D22: 6.1.0 | E22: Sunbird Inquiry | F22: Question Set Player (QuML) | H22: QA_Required | I22: Yes | J22: Yes | K22: Yes | L22: Naveen | M22: Pass
A23: Bug | B23: IQ-512 | C23: Select video popup is not closing when creator clicks on the outside of popup | D23: 6.1.0 | E23: Sunbird Inquiry | F23: Question Set Editor | H23: QA_Required | I23: Yes | J23: Yes | K23: Yes | L23: Naveen | M23: Pass
A24: Bug | B24: IQ-487 | C24: If user mouseover on the tool tip of the each field name and its showing at the Icon name field | D24: 6.1.0 | E24: Sunbird Inquiry | F24: Question Set Editor | H24: QA_Required | I24: Yes | J24: Yes | K24: Yes | L24: Naveen | M24: Pass
A25: Minor-Enhancement | B25: IQ-476 | C25: Script for Migrating Questions and Question sets in Q 1.0 to Q 1.1 | D25: 6.1.0 | E25: Sunbird Inquiry | F25: Question and Question Set Service | H25: QA_Required | I25: Yes | J25: Yes | K25: Yes | L25: Naveen | M25: Pass
A26: Minor-Enhancement | B26: IQ-439 | C26: Clean-up and Streamline the inQuiry BB code | D26: 6.1.0 | E26: Sunbird Inquiry | F26: Question and Question Set Service | G26: Yes | H26: QA_Required | I26: No | J26: No
A27: Minor-Enhancement | B27: IQ-415 | C27: Enable Jira configuration for the inQuiry GitHub repo | D27: 6.1.0 | E27: Sunbird Inquiry | F27: Question Set Editor | H27: QA_Not_Required | I27: No | J27: No
A28: Minor-Enhancement | B28: IQ-522 | C28: Question set cleanup | D28: 6.1.0 | E28: Sunbird Inquiry | F28: Question and Question Set Service | H28: QA_Not_Required | I28: No | J28: No
A29: Bug | B29: IQ-513 | C29: Not able to open all the Question sets | D29: 6.1.0 | E29: Sunbird Inquiry | F29: Question Set Editor | H29: QA_Required | I29: Yes | J29: Yes | K29: Yes | L29: Naveem | M29: Pass
A30: Minor-Enhancement | B30: IQ-550 | C30: Code cleanup - Proxy server files for local development | D30: 6.2.0 | E30: Sunbird Inquiry | F30: Question Set Editor | H30: QA_Not_Required | I30: No | J30: No
A31: Minor-Enhancement | B31: IQ-549 | C31: QuML Editor configuration injection changes | D31: 6.2.0 | E31: Sunbird Inquiry | F31: Question Set Editor | G31: Yes | H31: QA_Required | I31: No | J31: No
A32: Minor-Enhancement | B32: IQ-548 | C32: Migration Documentation CLONE | D32: 6.2.0 | E32: Sunbird Inquiry | F32: Question and Question Set Service | H32: QA_Not_Required | I32: No | J32: No
A33: Minor-Enhancement | B33: IQ-546 | C33: Move environment variables from server.js to .env file | D33: 6.2.0 | E33: Sunbird Inquiry | F33: Question Set Editor | H33: QA_Not_Required | I33: No | J33: No
A34: Minor-Enhancement | B34: IQ-544 | C34: Testing of JIRA workflow enabled for editor and player | D34: 6.2.0 | E34: Sunbird Inquiry | F34: Question Set Editor | H34: QA_Not_Required | I34: No | J34: No
A35: Minor-Enhancement | B35: IQ-543 | C35: Scala Upgrade | D35: 6.2.0 | E35: Sunbird Inquiry | F35: Question and Question Set Service | H35: QA_Not_Required | I35: No | J35: No
A36: Minor-Enhancement | B36: IQ-541 | C36: Analyse how APIs errors are consumed by the QuMLPlayer | D36: 6.2.0 | E36: Sunbird Inquiry | F36: Question Set Player (QuML) | H36: QA_Not_Required | I36: No | J36: No
A37: Minor-Enhancement | B37: IQ-537 | C37: C4GT Support | D37: 6.2.0 | E37: Sunbird Inquiry | F37: Question and Question Set Service | H37: QA_Not_Required | I37: No | J37: No
A38: Minor-Enhancement | B38: IQ-526 | C38: Analyse how APIs errors are consumed by Editor | D38: 6.2.0 | E38: Sunbird Inquiry | F38: Question Set Editor | H38: QA_Not_Required | I38: No | J38: No
A39: Bug | B39: IQ-521 | C39: If we give images in options, image size is coming larger than actual size on the solution | D39: 6.2.0 | E39: Sunbird Inquiry | F39: Question Set Player (QuML) | H39: QA_Required | I39: Yes | J39: Yes | K39: Yes | L39: Naveem | M39: Pass
A40: Bug | B40: IQ-515 | C40: Zoom icon overlapping with image if user use the resolution for 25% in Horizontal layout | D40: 6.2.0 | E40: Sunbird Inquiry | F40: Question Set Player (QuML) | H40: QA_Required | I40: Yes | J40: Yes | K40: Yes | L40: Naveem | M40: Pass
A41: Minor-Enhancement | B41: IQ-450 | C41: Cleanup of unused configuration and code from QuML Editor | D41: 6.2.0 | E41: Sunbird Inquiry | F41: Question Set Editor | G41: Yes | H41: QA_Required | I41: No | J41: No
A42: Bug | B42: IQ-558 | C42: GET questionset v2 hierarchy API is returning timeLimits in wrong format | D42: 6.2.0 | E42: Sunbird Inquiry | F42: Question and Question Set Service | H42: QA_Required | I42: Yes | J42: Yes | K42: Yes | L42: Naveem | M42: Pass
A43: Minor-Enhancement | B43: IQ-551 | C43: Restore the sample data for player behaviour in inQuiry portal | D43: 6.2.0 | E43: Sunbird Inquiry | F43: Question Set Player (QuML) | G43: Yes | H43: QA_Required | I43: No | J43: No
A44: Minor-Enhancement | B44: IQ-638 | C44: [inQuiry] Removal of hardcoding in Question Editor | D44: 7.0.0 | E44: Sunbird Inquiry | F44: Question Set Editor | H44: QA_Required | I44: Yes | J44: Yes | K44: Yes | L44: Naveem | M44: Pass
A45: Minor-Enhancement | B45: IQ-604 | C45: Upgrade coKreat to v2 APIs | D45: 7.0.0 | E45: Sunbird Inquiry | F45: Question and Question Set Service | H45: QA_Required | I45: Yes | J45: Yes
A46: Bug | B46: IQ-591 | C46: Deployment failure in OCI because of Sunbird related variables | D46: 7.0.0 | E46: Sunbird Inquiry | F46: Question and Question Set Service | H46: QA_Not_Required | I46: No | J46: No
A47: Minor-Enhancement | B47: IQ-585 | C47: Productionise inquiry V2 | D47: 7.0.0 | E47: Sunbird Inquiry | F47: Question and Question Set Service | H47: QA_Required | I47: Yes | J47: Yes | K47: Yes | L47: Naveem | M47: Pass
A48: Minor-Enhancement | B48: IQ-584 | C48: User Account Deletion | D48: 7.0.0 | E48: Sunbird Inquiry | F48: Question and Question Set Service | H48: QA_Required | I48: Yes | J48: Yes | K48: Yes | L48: Naveem | M48: Pass
A49: Minor-Enhancement | B49: IQ-580 | C49: Enabling of V2 Questionset Editor in sunbirdEd-portal | D49: 7.0.0 | E49: Sunbird Inquiry | F49: Question Set Editor | G49: Yes | H49: QA_Required | I49: No | J49: No
A50: Bug | B50: IQ-567 | C50: Error Event is generated on Telemetry while preview the Question set | D50: 7.0.0 | E50: Sunbird Inquiry | F50: Question Set Player (QuML) | H50: QA_Required | I50: Yes | J50: Yes | K50: Yes | L50: Naveem | M50: Pass
A51: Minor-Enhancement | B51: IQ-560 | C51: [inQuiry ] Removal of Hardcoding from inQuiry components | D51: 7.0.0 | E51: Sunbird Inquiry | F51: Question and Question Set Service | H51: QA_Required | I51: Yes | J51: Yes | K51: Yes | L51: Naveem | M51: Pass
A52: Minor-Enhancement | B52: IQ-559 | C52: Merging the inQuiry dev infra to Ed dev infra | D52: 7.0.0 | E52: Sunbird Inquiry | F52: Question and Question Set Service | H52: QA_Not_Required | I52: No | J52: No
A53: Minor-Enhancement | B53: IQ-646 | C53: Deploy user-pii-updater flink job in cokreat infra | D53: 7.0.0 | E53: Sunbird Inquiry | F53: Question and Question Set Service | H53: QA_Not_Required | I53: No | J53: No
A54: Minor-Enhancement | B54: IQ-645 | C54: Jenkins script for data pipeline | D54: 7.0.0 | E54: Sunbird Inquiry | F54: Question and Question Set Service | H54: QA_Not_Required | I54: No | J54: No
A55: Minor-Enhancement | B55: IQ-652 | C55: quml-migrator: make parallelism configurable | D55: 7.0.0 | E55: Sunbird Inquiry | F55: Question and Question Set Service | H55: QA_Not_Required | I55: No | J55: No
A56: Minor-Enhancement | B56: IQ-674 | C56: Enhancing the web-component to accept the config from Parent App | D56: 7.0.0 | E56: Sunbird Inquiry | F56: Question Set Player (QuML) | H56: QA_Not_Required | I56: No | J56: No
A57: Bug | B57: IQ-664 | C57: Compatibility Level is not changed for migration (runtime transformation / migration) | D57: 7.0.0 | E57: Sunbird Inquiry | F57: Question and Question Set Service | H57: QA_Not_Required | I57: No | J57: No
A58: Minor Enhancement | B58: KN-882 | C58: Change players to web components in Resource library | D58: 5.6.0 Sprint 1 | E58: Sunbird Knowlg | G58: Yes | H58: QA_Required | I58: No | J58: No | K58: Yes | L58: Priya | M58: Pass
A59: RFC | B59: KN-869 | C59: POC: Change of Graph Database for Sunbird Knowlg | D59: 5.6.0 Sprint 1 | E59: Sunbird Knowlg | H59: QA_Not_Required | I59: No | J59: No
A60: Minor Enhancement | B60: KN-868 | C60: Updating PDF, Video, Epub player from angular libraries to web component in Collection editor | D60: 5.6.0 Sprint 1 | E60: Sunbird Knowlg | G60: Yes | H60: QA_Required | I60: No | J60: No | K60: Yes | L60: Priya | M60: Pass
A61: Minor Enhancement | B61: KN-848 | C61: [Stack] Update scala version | D61: 5.6.0 Sprint 1 | E61: Sunbird Knowlg | G61: Yes | H61: QA_Required | I61: No | J61: No | K61: Yes | L61: Priya | M61: Pass
A62: RFC | B62: KN-10 | C62: Refactoring taxonomy API's | D62: 5.6.0 Sprint 1 | E62: Sunbird Knowlg | G62: No | H62: QA_Required | I62: Yes | J62: Yes | K62: Yes | L62: Priya | M62: Pass
A63: Documentation issue | B63: KN-896 | C63: Sunbird collection editor web component developer documentation | D63: 5.6.0 Sprint 2 | E63: Sunbird Knowlg | H63: QA_Not_Required | I63: No | J63: No
A64: Bug | B64: KN-894 | C64: Sunbird pdf player issue on navigation on last page with scroll | D64: 5.6.0 Sprint 2 | E64: Sunbird Knowlg | G64: No | H64: QA_Required | I64: Yes | J64: Yes | K64: Yes | L64: Priya | M64: Pass
A65: Bug | B65: KN-893 | C65: Sunbird epub player flickering issue on navigation | D65: 5.6.0 Sprint 2 | E65: Sunbird Knowlg | G65: No | H65: QA_Required | I65: Yes | J65: Yes | K65: Yes | L65: Priya | M65: Pass
A66: Minor-Enhancement | B66: KN-908 | C66: List Lock API refactoring | D66: 5.7.0 Sprint 1 | E66: Sunbird Knowlg | G66: Yes | H66: QA_Required | I66: No | J66: No | K66: Yes | L66: Priya | M66: Pass
A67: Minor-Enhancement | B67: KN-907 | C67: Retire Lock API refactoring | D67: 5.7.0 Sprint 1 | E67: Sunbird Knowlg | G67: Yes | H67: QA_Required | I67: No | J67: No | K67: Yes | L67: Priya | M67: Pass
A68: Minor-Enhancement | B68: KN-906 | C68: Refresh Lock API refactoring | D68: 5.7.0 Sprint 1 | E68: Sunbird Knowlg | G68: Yes | H68: QA_Required | I68: No | J68: No | K68: Yes | L68: Priya | M68: Pass
A69: Minor-Enhancement | B69: KN-903 | C69: Generalisation of object creation in Knowlg | D69: 5.7.0 Sprint 1 | E69: Sunbird Knowlg | H69: QA_Not_Required | I69: No | J69: No
A70: Minor-Enhancement | B70: KN-902 | C70: Knowlg CSP changes | D70: 5.7.0 Sprint 1 | E70: Sunbird Knowlg | G70: Yes | H70: QA_Required | I70: No | J70: No | K70: Yes | L70: Priya | M70: Pass | O70: Already verified in ED Rel 6.0
A71: Minor-Enhancement | B71: KN-880 | C71: Create Lock API refactoring | D71: 5.7.0 Sprint 1 | E71: Sunbird Knowlg | G71: Yes | H71: QA_Required | I71: No | J71: No | K71: Yes | L71: Priya | M71: Pass
A72: Minor-Enhancement | B72: KN-920 | C72: Knowlg CSP changes | D72: 5.7.0 Sprint 1 | E72: Sunbird Knowlg | G72: Yes | H72: QA_Required | I72: No | J72: No | K72: Yes | L72: Priya | M72: Pass | O72: Already verified in ED Rel 6.0
A73: Minor-enhancement | B73: KN-934 | C73: Knowlg: Configuration Options for Enabling or Disabling of Cassandra Database in Taxonomy Service | D73: 5.8.0 Sprint 1 | E73: Sunbird Knowlg | H73: QA_Not_Required | I73: No | J73: No
A74: Minor-enhancement | B74: KN-931 | C74: Merge both audit-event-generator and audit-history-indexer jobs | D74: 5.8.0 Sprint 1 | E74: Sunbird Knowlg | G74: Yes | H74: QA_Required | I74: No | J74: No | K74: Yes | L74: Priya | M74: Pass
A75: Minor-enhancement | B75: KN-930 | C75: Knowlg Generalization: Refactoring of knowlg code | D75: 5.8.0 Sprint 1 | E75: Sunbird Knowlg | G75: Yes | H75: QA_Required | I75: No | J75: No | K75: Yes | L75: Priya | M75: Pass
A76: Minor-enhancement | B76: KN-927 | C76: Knowlg APIs: Updated postman collections provided in the Knowlg microsite | D76: 5.8.0 Sprint 1 | E76: Sunbird Knowlg | H76: QA_Not_Required | I76: No | J76: No
A77: Bug | B77: KN-926 | C77: CLONE - When Book creator tries to upload csv file, it keeps on loading | D77: 5.8.0 Sprint 1 | E77: Sunbird Knowlg | G77: No | H77: QA_Required | I77: Yes | J77: Yes | K77: Yes | L77: Priya | M77: Pass
A78: Bug | B78: KN-925 | C78: CLONE - Add activity plugin is not available on resource editor | D78: 5.8.0 Sprint 1 | E78: Sunbird Knowlg | G78: No | H78: QA_Required | I78: Yes | J78: Yes | K78: Yes | L78: Priya | M78: Pass
A79: Minor-enhancement | B79: KN-935 | C79: sunbird file upload library unit test cases | D79: 5.8.0 Sprint 2 | E79: Sunbird Knowlg | H79: QA_Not_Required | I79: No | J79: No
A80: Minor-enhancement | B80: KN-932 | C80: Knowlg Search API code separaction | D80: 5.8.0 Sprint 2 | E80: Sunbird Knowlg | G80: Yes | H80: QA_Required | I80: No | J80: No | K80: Yes | L80: Priya | M80: Pass
A81: Minor-enhancement | B81: KN-929 | C81: Enable deployment of Knowlg completely on Kubernetes cluster (including microservices, jobs & databases). | D81: 5.8.0 Sprint 2 | E81: Sunbird Knowlg | H81: QA_Not_Required | I81: No | J81: No
A82: Minor-enhancement | B82: KN-943 | C82: Knowlg: Tika Core Dependency update | D82: 5.8.0 Sprint 2 | E82: Sunbird Knowlg | G82: Yes | H82: QA_Required | I82: No | J82: No | K82: Yes | L82: Priya | M82: Pass
A83: Minor-enhancement | B83: KN-942 | C83: Knowlg: Adopter Support and Community threads | D83: 5.8.0 Sprint 2 | E83: Sunbird Knowlg | H83: QA_Not_Required | I83: No | J83: No
A84: Minor-enhancement | B84: KN-938 | C84: sunbird file upload library content type changes for single file upload | D84: 5.8.0 Sprint 2 | E84: Sunbird Knowlg | G84: Yes | H84: QA_Required | I84: No | J84: No | K84: Yes | L84: Priya | M84: Pass
A85: Minor Enhancement | B85: LR-676 | C85: User PII Information and account deletion from LERN DBs | D85: Lern Rel 7.0.0 Sprint 1 | E85: Sunbird Lern | F85: User & Org Service | H85: QA_Required | I85: Yes | J85: Yes | K85: Yes | L85: Namrata | M85: Pass | P85: Ekstep
A86: Minor Enhancement | B86: LR-699 | C86: [LERN] Making BMGS configurable | D86: Lern Rel 7.0.0 Sprint 1 | E86: Sunbird Lern | F86: User & Org Service, Batch service, Groups, Discussion forum, Notification service | H86: QA_Required | I86: Yes | J86: Yes | K86: Yes | L86: Namrata | M86: Pass | P86: Ekstep
A87: Minor Enhancement | B87: LR-687 | C87: Removal of Adopter specific keywords from LERN repos | D87: Lern Rel 7.0.0 Sprint 1 | E87: Sunbird Lern | F87: User & Org Service, Batch service, Groups, Discussion forum, Notification service | H87: QA_Required | I87: No | J87: No
A88: Minor Enhancement | B88: LR-686 | C88: Create and register new OTP template | D88: Lern Rel 7.0.0 Sprint 1 | E88: Sunbird Lern | F88: User & Org Service | H88: QA_Required | I88: Yes | J88: Yes | K88: Yes | L88: Namrata
A89: Minor Enhancement | B89: LR-684 | C89: Delete User Flink Job | D89: Lern Rel 7.0.0 Sprint 1 | E89: Sunbird Lern | F89: User & Org Service | H89: QA_Required | I89: No | J89: No
A90: RFC | B90: LR-627 | C90: Cloud Agnostic Changes | D90: Lern Rel 7.0.0 Sprint 1 | E90: Sunbird Lern | F90: User & Org Service, Batch service | H90: QA_Required | I90: No | J90: No
A91: Minor Enhancement | B91: ED-3183 | C91: Vulnerabilities: sunbird-client-service library | D91: 7.0.0 | E91: Sunbird ED | F91: Reference Learning Web App | H91: QA_Not_Required | I91: No | J91: No
A92: Minor Enhancement | B92: ED-3073 | C92: [CSL] Common service class for default framework categories | D92: 7.0.0 | E92: Sunbird ED | F92: Reference Learning Web App | H92: QA_Not_Required | I92: No | J92: No
A93: Minor Enhancement | B93: ED-3146 | C93: Integrate the API with the front end code and test the delete user flow | D93: 7.0.0 | E93: Sunbird ED | F93: Reference Learning Web App | H93: QA_Required | I93: Yes | J93: Yes | K93: Yes | L93: Namrata | M93: Pass
A94: Minor Enhancement | B94: ED-3123 | C94: Write unit testcase for Delete user functionality | D94: 7.0.0 | E94: Sunbird ED | F94: Reference Learning Web App | H94: QA_Not_Required | I94: No | J94: No
A95: Minor Enhancement | B95: ED-3073 | C95: [CSL] Common service class for default framework categories | D95: 7.0.0 | E95: Sunbird ED | F95: Reference Learning Mobile App | H95: QA_Not_Required | I95: No | J95: No
A96: Minor Enhancement | B96: ED-3042 | C96: [ED-Portal]: Generic implementation of Hardcoded BMGS | D96: 7.0.0 | E96: Sunbird ED | F96: Reference Learning Web App | H96: QA_Required | I96: Yes | J96: Yes | K96: Done
A97: Minor Enhancement | B97: ED-2950 | C97: Improve TestCase of sunbird portal from 60% to 70% | D97: 7.0.0 | E97: Sunbird ED | F97: Reference Learning Web App | H97: QA_Not_Required | I97: No | J97: No
A98: Minor Enhancement | B98: ED-2933 | C98: Branch merging activity release-6.0.0 to release-7.0.0 | D98: 7.0.0 | E98: Sunbird ED | F98: Reference Learning Web App | H98: QA_Not_Required | I98: No | J98: No
A99: Minor Enhancement | B99: ED-2894 | C99: Delete user functionality in mobile | D99: 7.0.0 | E99: Sunbird ED | F99: Reference Learning Mobile App | H99: QA_Required | I99: Yes | J99: Yes | K99: Yes | L99: Namrata | M99: Pass
A100: Minor Enhancement | B100: ED-2848 | C100: Delete user functionality in Portal | D100: 7.0.0 | E100: Sunbird ED | F100: Reference Learning Web App | H100: QA_Required | I100: Yes | J100: Yes | K100: Yes | L100: Namrata | M100: Pass
...

Sheet R7.0.0 QA_Not_Required Scope
A1: ISSUE TYPE | B1: JIRA ID | C1: SUMMARY | D1: SPRINT | E1: BUILDING BLOCKS | F1: LATEST COMPONENT | G1: TO BE COVERED IN REG? | H1: QA_NOT_REQUIRED | I1: TC NEEDED | J1: TC WRITTEN? | K1: Verification Status (Sunbird ED Env) | L1: VERIFIED BY | M1: STATUS | N1: OPEN DEFECTS | O1: REMARKS | P1: CONTRIBUTOR
A2: Minor-Enhancement | B2: IQ-393 | C2: Error standardisation | D2: 6.0.0 | E2: Sunbird Inquiry | F2: Question and Question Set Service | H2: QA_Not_Required | I2: No | J2: No
A3: Minor-Enhancement | B3: IQ-272 | C3: Sunbird Inquiry - QuML Design Changes to ensure QuML complaince | D3: 6.0.0 | E3: Sunbird Inquiry | F3: Question Set Editor | H3: QA_Not_Required | I3: No | J3: No
A4: Minor-Enhancement | B4: IQ-443 | C4: Documentation | D4: 6.0.0 | E4: Sunbird Inquiry | F4: Question and Question Set Service | H4: QA_Not_Required | I4: No | J4: No
A5: Minor-Enhancement | B5: IQ-414 | C5: Editor/Player: Update the Node version from 14 to 16 | D5: 6.0.0 | E5: Sunbird Inquiry | F5: Question Set Editor | H5: QA_Not_Required | I5: No | J5: No
A6: Minor-Enhancement | B6: IQ-468 | C6: Remove hard coding in the QuML Player | D6: 6.0.0 | E6: Sunbird Inquiry | F6: Question Set Editor | H6: QA_Not_Required | I6: No | J6: No
A7: Minor-Enhancement | B7: IQ-480 | C7: Integrate V2 player and Editor in the inQuiry Portal | D7: 6.0.0 | E7: Sunbird Inquiry | F7: Question Set Editor | H7: QA_Not_Required | I7: No | J7: No
A8: Minor-Enhancement | B8: IQ-415 | C8: Enable Jira configuration for the inQuiry GitHub repo | D8: 6.1.0 | E8: Sunbird Inquiry | F8: Question Set Editor | H8: QA_Not_Required | I8: No | J8: No
A9: Minor-Enhancement | B9: IQ-522 | C9: Question set cleanup | D9: 6.1.0 | E9: Sunbird Inquiry | F9: Question and Question Set Service | H9: QA_Not_Required | I9: No | J9: No
A10: Minor-Enhancement | B10: IQ-550 | C10: Code cleanup - Proxy server files for local development | D10: 6.2.0 | E10: Sunbird Inquiry | F10: Question Set Editor | H10: QA_Not_Required | I10: No | J10: No
A11: Minor-Enhancement | B11: IQ-548 | C11: Migration Documentation CLONE | D11: 6.2.0 | E11: Sunbird Inquiry | F11: Question and Question Set Service | H11: QA_Not_Required | I11: No | J11: No
A12: Minor-Enhancement | B12: IQ-546 | C12: Move environment variables from server.js to .env file | D12: 6.2.0 | E12: Sunbird Inquiry | F12: Question Set Editor | H12: QA_Not_Required | I12: No | J12: No
A13: Minor-Enhancement | B13: IQ-544 | C13: Testing of JIRA workflow enabled for editor and player | D13: 6.2.0 | E13: Sunbird Inquiry | F13: Question Set Editor | H13: QA_Not_Required | I13: No | J13: No
... A24: Bug | B24: IQ-664 | C24: Compatibility Level is not changed for migration (runtime transformation / migration) | D24: 7.0.0 | E24: Sunbird Inquiry | F24: Question and Question Set Service | H24: QA_Not_Required | I24: No | J24: No
A25: RFC | B25: KN-869 | C25: POC: Change of Graph Database for Sunbird Knowlg | D25: 5.6.0 Sprint 1 | E25: Sunbird Knowlg | H25: QA_Not_Required | I25: No | J25: No
A26: Documentation issue | B26: KN-896 | C26: Sunbird collection editor web component developer documentation | D26: 5.6.0 Sprint 2 | E26: Sunbird Knowlg | H26: QA_Not_Required | I26: No | J26: No
A27: Minor-Enhancement | B27: KN-903 | C27: Generalisation of object creation in Knowlg | D27: 5.7.0 Sprint 1 | E27: Sunbird Knowlg | H27: QA_Not_Required | I27: No | J27: No
A28: Minor-enhancement | B28: KN-934 | C28: Knowlg: Configuration Options for Enabling or Disabling of Cassandra Database in Taxonomy Service | D28: 5.8.0 Sprint 1 | E28: Sunbird Knowlg | H28: QA_Not_Required | I28: No | J28: No
A29: Minor-enhancement | B29: KN-927 | C29: Knowlg APIs: Updated postman collections provided in the Knowlg microsite | D29: 5.8.0 Sprint 1 | E29: Sunbird Knowlg | H29: QA_Not_Required | I29: No | J29: No
A30: Minor-enhancement | B30: KN-935 | C30: sunbird file upload library unit test cases | D30: 5.8.0 Sprint 2 | E30: Sunbird Knowlg | H30: QA_Not_Required | I30: No | J30: No
A31: Minor-enhancement | B31: KN-929 | C31: Enable deployment of Knowlg completely on Kubernetes cluster (including microservices, jobs & databases). | D31: 5.8.0 Sprint 2 | E31: Sunbird Knowlg | H31: QA_Not_Required | I31: No | J31: No
A32: Minor-enhancement | B32: KN-942 | C32: Knowlg: Adopter Support and Community threads | D32: 5.8.0 Sprint 2 | E32: Sunbird Knowlg | H32: QA_Not_Required | I32: No | J32: No
A33: Minor Enhancement | B33: ED-3183 | C33: Vulnerabilities: sunbird-client-service library | D33: 7.0.0 | E33: Sunbird ED | F33: Reference Learning Web App | H33: QA_Not_Required | I33: No | J33: No
A34: Minor Enhancement | B34: ED-3073 | C34: [CSL] Common service class for default framework categories | D34: 7.0.0 | E34: Sunbird ED | F34: Reference Learning Web App | H34: QA_Not_Required | I34: No | J34: No
